Workbook
Name L_MixNom: Listes!$A$2:$A$8
Name L_MixVal: Listes!$B$2:$B$8
Name L_MixSrc: Listes!$C$2:$C$8
Name D_Date: 'Données'!$A:$A
Name D_Prod: 'Données'!$C:$C
Name D_I: 'Données'!$S:$S
Name D_O: 'Données'!$T:$T
Name D_CR: 'Données'!$U:$U
Name D_CW: 'Données'!$V:$V
Name D_Mod: 'Données'!$W:$W
Name D_Jour: 'Données'!$X:$X
Name D_Cle: 'Données'!$Y:$Y
Name D_Grp: 'Données'!$AA:$AA
Name D_TO: 'Données'!$AC:$AC
Name D_kWh: 'Données'!$AD:$AD
Name D_CO2: 'Données'!$AE:$AE
Name D_Brut: 'Données'!$AF:$AF
Name D_An: 'Données'!$AG:$AG
Name D_Mois: 'Données'!$AH:$AH
Name D_C2: 'Données'!$AI:$AI
Name D_C4F: 'Données'!$AJ:$AJ
Name D_C4CW: 'Données'!$AK:$AK
Name P_Source: Calcul!$C$6
Name P_MixNom: Calcul!$C$7
Name P_MixPerso: Calcul!$C$8
Name P_Mix: Calcul!$C$9
Name P_Fab: Calcul!$C$10
Name P_Lo: Calcul!$C$11
Name P_Hi: Calcul!$C$12
Name P_N: Calcul!$C$13
Name P_Adj: Calcul!$C$14
Name M_Nom: Calcul!$B$30:$B$118
Name M_Fam: Calcul!$C$30:$C$118
Name M_Force: Calcul!$D$30:$D$118
Name M_Conv: Calcul!$E$30:$E$118
Name M_Orig: Calcul!$F$30:$F$118
Name M_Delta: Calcul!$G$30:$G$118
Name M_Eps: Calcul!$H$30:$H$118
Name M_PI: Calcul!$I$30:$I$118
Name M_PCR: Calcul!$J$30:$J$118
Name M_PCW: Calcul!$K$30:$K$118
Name M_PO: Calcul!$L$30:$L$118
Name M_Avant: Calcul!$M$30:$M$118
Name M_sI: Calcul!$N$30:$N$118
Name M_sCR: Calcul!$O$30:$O$118
Name M_sCW: Calcul!$P$30:$P$118
Name M_Scen: Calcul!$Q$30:$Q$118
Name M_eO: Calcul!$R$30:$R$118
Name M_PUE: Calcul!$S$30:$S$118
Name M_Fab: Calcul!$T$30:$T$118
Name M_FET: Calcul!$U$30:$U$118
Name M_Stat: Calcul!$V$30:$V$118
Name M_FEF: Calcul!$W$30:$W$118
Name M_FEC: Calcul!$X$30:$X$118
Name M_FE: Calcul!$Y$30:$Y$118
Name M_Src: Calcul!$Z$30:$Z$118
Name F_Fam: Calcul!$G$7:$G$14
Name F_Conv: Calcul!$H$7:$H$14
Name S_Has: Interne!$C$4
Name S_Last: Interne!$C$5

Sheet Mode d'emploi
B2: Mode d'emploi
B3: Déclinaison Excel du tableau de bord « Empreinte carbone de GitHub Copilot ».
B5: 1 | C5: Exportez le rapport d'usage Copilot (CSV « AI usage report ») depuis GitHub.
B6: 2 | C6: Dans l'onglet Données, videz l'ancien contenu s'il y en a : sélectionnez les lignes du tableau sous l'en-tête, clic droit › Supprimer › Lignes du tableau.
B7: 3 | C7: Ouvrez le CSV, copiez toutes les lignes sous l'en-tête (colonnes date à cache_write, dans l'ordre de l'export) et collez-les en A2 de l'onglet Données. Le tableau s'agrandit et les colonnes bleues se calculent seules. Si les nombres décimaux sont mal lus (Excel en français), passez par Données › À partir d'un fichier texte/CSV, avec « Origine du fichier » 65001 : Unicode (UTF-8) et la virgule comme délimiteur, puis copiez le résultat.
B8: 4 | C8: Ouvrez l'onglet Synthèse. L'année affichée est la dernière des données ; tapez une autre année dans la cellule jaune pour changer.
B9: 5 | C9: Réglez les hypothèses dans l'onglet Calcul (source des facteurs, mix électrique, fabrication, fourchette, projection, paramètres par modèle). Vérifiez l'onglet Contrôles après chaque nouvel import, en particulier les modèles inconnus (C1).
B11: Légende
C12: Cellule jaune, texte bleu : saisie ou hypothèse modifiable.
C13: En-tête bleu dans Données : colonne calculée, ne pas modifier.
C14: Tout le reste est calculé par formules. Les tokens s'affichent en k, M et Mds ; les émissions en kg puis en t au-delà de 1 000 kg.
B16: Format attendu (une ligne d'exemple, ne pas la coller)
C17: date : 2026-10-21
C18: username : jdupont
C19: product : copilot
C20: sku : copilot_ai_credits
C21: model : Claude Sonnet 4.6
C22: quantity : 168.25
C23: unit-type : ai-credits
C24: applied_cost_per_quantity : 0.04
C25: gross_amount : 6.73
C26: discount_amount : 0
C27: net_amount : 6.73
C28: total_monthly_quota : (vide)
... C38: cache_write : 509724
B40: Onglets
C41: • Synthèse : indicateurs clés de l'année, tendance, graphique mensuel, modèles les plus émetteurs, phrases à retenir.
C42: • Empreinte : tableau mois par mois (réel et projeté), répartition par modèle, cumul, série quotidienne, classement complet des modèles.
C43: • Calcul : formules, réglages globaux et paramètres par modèle (prix, convention, e_O, facteurs).
C44: • Contrôles : C1 à C6.
C45: • Méthodologie : sources et choix de méthode.
C46: • Données : l'export collé et les colonnes calculées.
C47: • Interne et Listes : calculs intermédiaires et listes de choix, à ne pas modifier.

Sheet Synthèse
B2: Empreinte carbone de GitHub Copilot
B3: ="Inférence des modèles utilisés via Copilot · facteurs : "&P_Source&" · méthode du 20/10/2026" -> Inférence des modèles utilisés via Copilot · facteurs : Table fournie · méthode du 20/10/2026
B4: =IF(S_Has,"Données du "&RIGHT("0"&DAY(S_First),2)&"/"&RIGHT("0"&MONTH(S_First),2)&"/"&YEAR(S_First)&" au "&RIGHT("0"&DAY(S_Last),2)&"/"&RIGHT("0"&MONTH(S_Last),2)&"/"&YEAR(S_Last)&" · "&FIXED(COUNT(D_Jour),0)&" lignes","Aucune donnée : collez votre export dans l'onglet Données (voir Mode d'emploi).") -> Aucune donnée : collez votre export dans l'onglet Données (voir Mode d'emploi).
B6: Année | C6: =YEAR(IF(COUNT(D_Jour)>0,MAX(D_Jour),TODAY())) -> 2026 | D6: ← saisissez une autre année pour changer toute la synthèse et l'onglet Empreinte (par défaut : la dernière année des données).
B8: ="Émissions "&S_An -> Émissions 2026 | E8: =IF(S_Cur,"Atterrissage fin "&S_An,"Bilan "&S_An) -> Bilan 2026 | H8: Tokens équivalent output | K8: Coût brut
B9: =S_YTD -> 0 | E9: =S_Land -> 0 | H9: =S_TO -> 0 | K9: =S_Brut -> 0
B10: ="Fourchette "&IF(S_YTD*P_Lo>=1000,FIXED(S_YTD*P_Lo/1000,2)&" t",FIXED(S_YTD*P_Lo,1)&" kg")&" – "&IF(S_YTD*P_Hi>=1000,FIXED(S_YTD*P_Hi/1000,2)&" t",FIXED(S_YTD*P_Hi,1)&" kg") -> Fourchette 0.0 kg – 0.0 kg | E10: =IF(S_Cur,"Déjà émis "&IF(S_YTD>=1000,FIXED(S_YTD/1000,2)&" t",FIXED(S_YTD,1)&" kg")&" · fourchette "&IF(S_Land*P_Lo>=1000,FIXED(S_Land*P_Lo/1000,2)&" t",FIXED(S_Land*P_Lo,1)&" kg")&" – "&IF(S_Land*P_Hi>=1000,FIXED(S_Land*P_Hi/1000,2)&" t",FIXED(S_Land*P_Hi,1)&" kg"),"Année close : émissions réelles") -> Année close : émissions réelles | H10: ="Énergie "&IF(S_kWh>=1000,FIXED(S_kWh/1000,2)&" MWh",FIXED(S_kWh,1)&" kWh")&" (e_O × PUE, EcoLogits v2)" -> Énergie 0.0 kWh (e_O × PUE, EcoLogits v2) | K10: =IF(S_Brut>0,FIXED(S_YTD*1000/S_Brut,1)&" gCO₂e par dollar","Pas de montant dans l'export") -> Pas de montant dans l'export
B12: Tendance
B13: =IF(S_Cur,S_An&" à date vs même période "&(S_An-1),S_An&" vs "&(S_An-1)) -> 2026 vs 2025 | F13: ="Dernier mois complet ("&INDEX(L_Mois,MONTH(S_LCM))&" "&YEAR(S_LCM)&") vs "&(YEAR(S_LCM)-1) -> Dernier mois complet (déc. 2026) vs 2025 | J13: ="Projection "&S_An&" vs "&(S_An-1) -> Projection 2026 vs 2025
B14: =IF(S_PrevSame>0,S_CurSame/S_PrevSame-1,"—") -> — | F14: =IF(S_LCMp>0,S_LCMv/S_LCMp-1,"—") -> — | J14: =IF(S_PrevTot>0,S_Land/S_PrevTot-1,"—") -> —
B15: =IF(S_CurSame>=1000,FIXED(S_CurSame/1000,2)&" t",FIXED(S_CurSame,1)&" kg")&" CO₂e"&" contre "&IF(S_PrevSame>=1000,FIXED(S_PrevSame/1000,2)&" t",FIXED(S_PrevSame,1)&" kg")&" CO₂e" -> 0.0 kg CO₂e contre 0.0 kg CO₂e | F15: =IF(S_LCMv>=1000,FIXED(S_LCMv/1000,2)&" t",FIXED(S_LCMv,1)&" kg")&" CO₂e"&" contre "&IF(S_LCMp>=1000,FIXED(S_LCMp/1000,2)&" t",FIXED(S_LCMp,1)&" kg")&" CO₂e" -> 0.0 kg CO₂e contre 0.0 kg CO₂e | J15: =IF(S_Cur,"Rythme des "&P_N&" derniers jours : "&FIXED(S_Rate,2)&" kg/jour","Bilan "&S_An&" contre "&IF(S_PrevTot>=1000,FIXED(S_PrevTot/1000,2)&" t",FIXED(S_PrevTot,1)&" kg")&" CO₂e"&" en "&(S_An-1)) -> Bilan 2026 contre 0.0 kg CO₂e en 2025
B17: Émissions mensuelles
B36: Modèles les plus émetteurs
B37: Rang | C37: Modèle | G37: kgCO₂e | I37: Part | J37: Source du FE
B38: =Empreinte!B40 | C38: =Empreinte!C40 | G38: =Empreinte!D40 | I38: =Empreinte!E40 | J38: =Empreinte!K40
B39: =Empreinte!B41 | C39: =Empreinte!C41 | G39: =Empreinte!D41 | I39: =Empreinte!E41 | J39: =Empreinte!K41
B40: =Empreinte!B42 | C40: =Empreinte!C42 | G40: =Empreinte!D42 | I40: =Empreinte!E42 | J40: =Empreinte!K42
B41: =Empreinte!B43 | C41: =Empreinte!C43 | G41: =Empreinte!D43 | I41: =Empreinte!E43 | J41: =Empreinte!K43
B42: =Empreinte!B44 | C42: =Empreinte!C44 | G42: =Empreinte!D44 | I42: =Empreinte!E44 | J42: =Empreinte!K44
B45: À retenir
B46: =IF(S_Has,"En "&S_An&", l'usage de GitHub Copilot a émis "&IF(S_YTD>=1000,FIXED(S_YTD/1000,2)&" t",FIXED(S_YTD,1)&" kg")&" CO₂e"&" (fourchette "&IF(S_YTD*P_Lo>=1000,FIXED(S_YTD*P_Lo/1000,2)&" t",FIXED(S_YTD*P_Lo,1)&" kg")&" CO₂e"&" à "&IF(S_YTD*P_Hi>=1000,FIXED(S_YTD*P_Hi/1000,2)&" t",FIXED(S_YTD*P_Hi,1)&" kg")&" CO₂e"&") pour "&IF(S_TO>=1000000000,FIXED(S_TO/1000000000,1)&" Mds",FIXED(S_TO/1000000,1)&" M")&" de tokens équivalent output.","Importez un export pour obtenir la synthèse.") -> Importez un export pour obtenir la synthèse.
B47: =IF(Empreinte!C40="","","Le premier modèle, "&Empreinte!C40&", représente "&FIXED(Empreinte!E40*100,0)&" % des émissions de l'année ; les cinq premiers en représentent "&FIXED(SUM(Empreinte!E40:E44)*100,0)&" %.")
B48: =IF(NOT(S_Has),"",IF(S_Cur,"Au rythme des "&P_N&" derniers jours, l'année se terminerait vers "&IF(S_Land>=1000,FIXED(S_Land/1000,2)&" t",FIXED(S_Land,1)&" kg")&" CO₂e"&IF(S_PrevTot>0," ("&IF(S_Land>=S_PrevTot,"+","")&FIXED((S_Land/S_PrevTot-1)*100,0)&" % par rapport à "&(S_An-1)&").","."),"L'année "&S_An&" est close : bilan de "&IF(S_YTD>=1000,FIXED(S_YTD/1000,2)&" t",FIXED(S_YTD,1)&" kg")&" CO₂e"&"."))
B49: =IF(S_Brut>0,"Intensité : "&FIXED(S_YTD*1000/S_Brut,1)&" gCO₂e par dollar facturé (montant brut).","")

Sheet Empreinte
B2: Empreinte
B3: ="Année "&S_An&" · facteurs : "&P_Source&" · mix "&P_MixNom&IF(S_Cur," · projection au rythme des "&P_N&" derniers jours","") -> Année 2026 · facteurs : Table fournie · mix France (2020, EEA)
B5: Mois par mois
B6: Mois | C6: Réel (kgCO₂e) | D6: Projeté (kgCO₂e) | E6: Total (kgCO₂e) | F6: Cumul réel | G6: Cumul projeté | H6: Énergie | I6: Tokens éq. output | J6: Coût brut | K6: gCO₂e par $
B7: janv. | C7: =SUMIFS(D_CO2,D_An,S_An,D_Mois,1) -> 0 | D7: =IF(S_Cur,S_Rate*MAX(0,EOMONTH(DATE(S_An,1,1),0)-MAX(S_Last,DATE(S_An,1,1)-1)),0) -> 0 | E7: =C7+D7 -> 0 | F7: =SUM(C$7:C7) -> 0 | G7: =SUM(D$7:D7) -> 0 | H7: =SUMIFS(D_kWh,D_An,S_An,D_Mois,1) -> 0 | I7: =SUMIFS(D_TO,D_An,S_An,D_Mois,1) -> 0 | J7: =SUMIFS(D_Brut,D_An,S_An,D_Mois,1) -> 0 | K7: =IF(J7>0,C7*1000/J7,"")
B8: févr. | C8: =SUMIFS(D_CO2,D_An,S_An,D_Mois,2) -> 0 | D8: =IF(S_Cur,S_Rate*MAX(0,EOMONTH(DATE(S_An,2,1),0)-MAX(S_Last,DATE(S_An,2,1)-1)),0) -> 0 | E8: =C8+D8 -> 0 | F8: =SUM(C$7:C8) -> 0 | G8: =SUM(D$7:D8) -> 0 | H8: =SUMIFS(D_kWh,D_An,S_An,D_Mois,2) -> 0 | I8: =SUMIFS(D_TO,D_An,S_An,D_Mois,2) -> 0 | J8: =SUMIFS(D_Brut,D_An,S_An,D_Mois,2) -> 0 | K8: =IF(J8>0,C8*1000/J8,"")
B9: mars | C9: =SUMIFS(D_CO2,D_An,S_An,D_Mois,3) -> 0 | D9: =IF(S_Cur,S_Rate*MAX(0,EOMONTH(DATE(S_An,3,1),0)-MAX(S_Last,DATE(S_An,3,1)-1)),0) -> 0 | E9: =C9+D9 -> 0 | F9: =SUM(C$7:C9) -> 0 | G9: =SUM(D$7:D9) -> 0 | H9: =SUMIFS(D_kWh,D_An,S_An,D_Mois,3) -> 0 | I9: =SUMIFS(D_TO,D_An,S_An,D_Mois,3) -> 0 | J9: =SUMIFS(D_Brut,D_An,S_An,D_Mois,3) -> 0 | K9: =IF(J9>0,C9*1000/J9,"")
B10: avr. | C10: =SUMIFS(D_CO2,D_An,S_An,D_Mois,4) -> 0 | D10: =IF(S_Cur,S_Rate*MAX(0,EOMONTH(DATE(S_An,4,1),0)-MAX(S_Last,DATE(S_An,4,1)-1)),0) -> 0 | E10: =C10+D10 -> 0 | F10: =SUM(C$7:C10) -> 0 | G10: =SUM(D$7:D10) -> 0 | H10: =SUMIFS(D_kWh,D_An,S_An,D_Mois,4) -> 0 | I10: =SUMIFS(D_TO,D_An,S_An,D_Mois,4) -> 0 | J10: =SUMIFS(D_Brut,D_An,S_An,D_Mois,4) -> 0 | K10: =IF(J10>0,C10*1000/J10,"")
B11: mai | C11: =SUMIFS(D_CO2,D_An,S_An,D_Mois,5) -> 0 | D11: =IF(S_Cur,S_Rate*MAX(0,EOMONTH(DATE(S_An,5,1),0)-MAX(S_Last,DATE(S_An,5,1)-1)),0) -> 0 | E11: =C11+D11 -> 0 | F11: =SUM(C$7:C11) -> 0 | G11: =SUM(D$7:D11) -> 0 | H11: =SUMIFS(D_kWh,D_An,S_An,D_Mois,5) -> 0 | I11: =SUMIFS(D_TO,D_An,S_An,D_Mois,5) -> 0 | J11: =SUMIFS(D_Brut,D_An,S_An,D_Mois,5) -> 0 | K11: =IF(J11>0,C11*1000/J11,"")
B12: juin | C12: =SUMIFS(D_CO2,D_An,S_An,D_Mois,6) -> 0 | D12: =IF(S_Cur,S_Rate*MAX(0,EOMONTH(DATE(S_An,6,1),0)-MAX(S_Last,DATE(S_An,6,1)-1)),0) -> 0 | E12: =C12+D12 -> 0 | F12: =SUM(C$7:C12) -> 0 | G12: =SUM(D$7:D12) -> 0 | H12: =SUMIFS(D_kWh,D_An,S_An,D_Mois,6) -> 0 | I12: =SUMIFS(D_TO,D_An,S_An,D_Mois,6) -> 0 | J12: =SUMIFS(D_Brut,D_An,S_An,D_Mois,6) -> 0 | K12: =IF(J12>0,C12*1000/J12,"")
B13: juil. | C13: =SUMIFS(D_CO2,D_An,S_An,D_Mois,7) -> 0 | D13: =IF(S_Cur,S_Rate*MAX(0,EOMONTH(DATE(S_An,7,1),0)-MAX(S_Last,DATE(S_An,7,1)-1)),0) -> 0 | E13: =C13+D13 -> 0 | F13: =SUM(C$7:C13) -> 0 | G13: =SUM(D$7:D13) -> 0 | H13: =SUMIFS(D_kWh,D_An,S_An,D_Mois,7) -> 0 | I13: =SUMIFS(D_TO,D_An,S_An,D_Mois,7) -> 0 | J13: =SUMIFS(D_Brut,D_An,S_An,D_Mois,7) -> 0 | K13: =IF(J13>0,C13*1000/J13,"")
B14: août | C14: =SUMIFS(D_CO2,D_An,S_An,D_Mois,8) -> 0 | D14: =IF(S_Cur,S_Rate*MAX(0,EOMONTH(DATE(S_An,8,1),0)-MAX(S_Last,DATE(S_An,8,1)-1)),0) -> 0 | E14: =C14+D14 -> 0 | F14: =SUM(C$7:C14) -> 0 | G14: =SUM(D$7:D14) -> 0 | H14: =SUMIFS(D_kWh,D_An,S_An,D_Mois,8) -> 0 | I14: =SUMIFS(D_TO,D_An,S_An,D_Mois,8) -> 0 | J14: =SUMIFS(D_Brut,D_An,S_An,D_Mois,8) -> 0 | K14: =IF(J14>0,C14*1000/J14,"")
B15: sept. | C15: =SUMIFS(D_CO2,D_An,S_An,D_Mois,9) -> 0 | D15: =IF(S_Cur,S_Rate*MAX(0,EOMONTH(DATE(S_An,9,1),0)-MAX(S_Last,DATE(S_An,9,1)-1)),0) -> 0 | E15: =C15+D15 -> 0 | F15: =SUM(C$7:C15) -> 0 | G15: =SUM(D$7:D15) -> 0 | H15: =SUMIFS(D_kWh,D_An,S_An,D_Mois,9) -> 0 | I15: =SUMIFS(D_TO,D_An,S_An,D_Mois,9) -> 0 | J15: =SUMIFS(D_Brut,D_An,S_An,D_Mois,9) -> 0 | K15: =IF(J15>0,C15*1000/J15,"")
B16: oct. | C16: =SUMIFS(D_CO2,D_An,S_An,D_Mois,10) -> 0 | D16: =IF(S_Cur,S_Rate*MAX(0,EOMONTH(DATE(S_An,10,1),0)-MAX(S_Last,DATE(S_An,10,1)-1)),0) -> 0 | E16: =C16+D16 -> 0 | F16: =SUM(C$7:C16) -> 0 | G16: =SUM(D$7:D16) -> 0 | H16: =SUMIFS(D_kWh,D_An,S_An,D_Mois,10) -> 0 | I16: =SUMIFS(D_TO,D_An,S_An,D_Mois,10) -> 0 | J16: =SUMIFS(D_Brut,D_An,S_An,D_Mois,10) -> 0 | K16: =IF(J16>0,C16*1000/J16,"")
B17: nov. | C17: =SUMIFS(D_CO2,D_An,S_An,D_Mois,11) -> 0 | D17: =IF(S_Cur,S_Rate*MAX(0,EOMONTH(DATE(S_An,11,1),0)-MAX(S_Last,DATE(S_An,11,1)-1)),0) -> 0 | E17: =C17+D17 -> 0 | F17: =SUM(C$7:C17) -> 0 | G17: =SUM(D$7:D17) -> 0 | H17: =SUMIFS(D_kWh,D_An,S_An,D_Mois,11) -> 0 | I17: =SUMIFS(D_TO,D_An,S_An,D_Mois,11) -> 0 | J17: =SUMIFS(D_Brut,D_An,S_An,D_Mois,11) -> 0 | K17: =IF(J17>0,C17*1000/J17,"")
B18: déc. | C18: =SUMIFS(D_CO2,D_An,S_An,D_Mois,12) -> 0 | D18: =IF(S_Cur,S_Rate*MAX(0,EOMONTH(DATE(S_An,12,1),0)-MAX(S_Last,DATE(S_An,12,1)-1)),0) -> 0 | E18: =C18+D18 -> 0 | F18: =SUM(C$7:C18) -> 0 | G18: =SUM(D$7:D18) -> 0 | H18: =SUMIFS(D_kWh,D_An,S_An,D_Mois,12) -> 0 | I18: =SUMIFS(D_TO,D_An,S_An,D_Mois,12) -> 0 | J18: =SUMIFS(D_Brut,D_An,S_An,D_Mois,12) -> 0 | K18: =IF(J18>0,C18*1000/J18,"")
B19: Total | C19: =SUM(C7:C18) -> 0 | D19: =SUM(D7:D18) -> 0 | E19: =SUM(E7:E18) -> 0 | H19: =SUM(H7:H18) -> 0 | I19: =SUM(I7:I18) -> 0 | J19: =SUM(J7:J18) -> 0 | K19: =IF(J19>0,C19*1000/J19,"")
B20: Projeté : rythme quotidien moyen des derniers jours (réglage dans Calcul), appliqué aux jours restants jusqu'au 31 décembre.
B22: Par modèle (8 premiers modèles de l'année + autres), kgCO₂e
B23: Mois | C23: =IF(INDEX(I_Top,1)="","—",INDEX(I_Top,1)) -> — | D23: =IF(INDEX(I_Top,2)="","—",INDEX(I_Top,2)) -> — | E23: =IF(INDEX(I_Top,3)="","—",INDEX(I_Top,3)) -> — | F23: =IF(INDEX(I_Top,4)="","—",INDEX(I_Top,4)) -> — | G23: =IF(INDEX(I_Top,5)="","—",INDEX(I_Top,5)) -> — | H23: =IF(INDEX(I_Top,6)="","—",INDEX(I_Top,6)) -> — | I23: =IF(INDEX(I_Top,7)="","—",INDEX(I_Top,7)) -> — | J23: =IF(INDEX(I_Top,8)="","—",INDEX(I_Top,8)) -> — | K23: Autres
B24: janv. | C24: =IF(INDEX(I_Top,1)="",0,SUMIFS(D_CO2,D_Grp,INDEX(I_Top,1),D_An,S_An,D_Mois,1)) -> 0 | D24: =IF(INDEX(I_Top,2)="",0,SUMIFS(D_CO2,D_Grp,INDEX(I_Top,2),D_An,S_An,D_Mois,1)) -> 0 | E24: =IF(INDEX(I_Top,3)="",0,SUMIFS(D_CO2,D_Grp,INDEX(I_Top,3),D_An,S_An,D_Mois,1)) -> 0 | F24: =IF(INDEX(I_Top,4)="",0,SUMIFS(D_CO2,D_Grp,INDEX(I_Top,4),D_An,S_An,D_Mois,1)) -> 0 | G24: =IF(INDEX(I_Top,5)="",0,SUMIFS(D_CO2,D_Grp,INDEX(I_Top,5),D_An,S_An,D_Mois,1)) -> 0 | H24: =IF(INDEX(I_Top,6)="",0,SUMIFS(D_CO2,D_Grp,INDEX(I_Top,6),D_An,S_An,D_Mois,1)) -> 0 | I24: =IF(INDEX(I_Top,7)="",0,SUMIFS(D_CO2,D_Grp,INDEX(I_Top,7),D_An,S_An,D_Mois,1)) -> 0 | J24: =IF(INDEX(I_Top,8)="",0,SUMIFS(D_CO2,D_Grp,INDEX(I_Top,8),D_An,S_An,D_Mois,1)) -> 0 | K24: =MAX(0,C7-SUM(C24:J24)) -> 0
B25: févr. | C25: =IF(INDEX(I_Top,1)="",0,SUMIFS(D_CO2,D_Grp,INDEX(I_Top,1),D_An,S_An,D_Mois,2)) -> 0 | D25: =IF(INDEX(I_Top,2)="",0,SUMIFS(D_CO2,D_Grp,INDEX(I_Top,2),D_An,S_An,D_Mois,2)) -> 0 | E25: =IF(INDEX(I_Top,3)="",0,SUMIFS(D_CO2,D_Grp,INDEX(I_Top,3),D_An,S_An,D_Mois,2)) -> 0 | F25: =IF(INDEX(I_Top,4)="",0,SUMIFS(D_CO2,D_Grp,INDEX(I_Top,4),D_An,S_An,D_Mois,2)) -> 0 | G25: =IF(INDEX(I_Top,5)="",0,SUMIFS(D_CO2,D_Grp,INDEX(I_Top,5),D_An,S_An,D_Mois,2)) -> 0 | H25: =IF(INDEX(I_Top,6)="",0,SUMIFS(D_CO2,D_Grp,INDEX(I_Top,6),D_An,S_An,D_Mois,2)) -> 0 | I25: =IF(INDEX(I_Top,7)="",0,SUMIFS(D_CO2,D_Grp,INDEX(I_Top,7),D_An,S_An,D_Mois,2)) -> 0 | J25: =IF(INDEX(I_Top,8)="",0,SUMIFS(D_CO2,D_Grp,INDEX(I_Top,8),D_An,S_An,D_Mois,2)) -> 0 | K25: =MAX(0,C8-SUM(C25:J25)) -> 0
B26: mars | C26: =IF(INDEX(I_Top,1)="",0,SUMIFS(D_CO2,D_Grp,INDEX(I_Top,1),D_An,S_An,D_Mois,3)) -> 0 | D26: =IF(INDEX(I_Top,2)="",0,SUMIFS(D_CO2,D_Grp,INDEX(I_Top,2),D_An,S_An,D_Mois,3)) -> 0 | E26: =IF(INDEX(I_Top,3)="",0,SUMIFS(D_CO2,D_Grp,INDEX(I_Top,3),D_An,S_An,D_Mois,3)) -> 0 | F26: =IF(INDEX(I_Top,4)="",0,SUMIFS(D_CO2,D_Grp,INDEX(I_Top,4),D_An,S_An,D_Mois,3)) -> 0 | G26: =IF(INDEX(I_Top,5)="",0,SUMIFS(D_CO2,D_Grp,INDEX(I_Top,5),D_An,S_An,D_Mois,3)) -> 0 | H26: =IF(INDEX(I_Top,6)="",0,SUMIFS(D_CO2,D_Grp,INDEX(I_Top,6),D_An,S_An,D_Mois,3)) -> 0 | I26: =IF(INDEX(I_Top,7)="",0,SUMIFS(D_CO2,D_Grp,INDEX(I_Top,7),D_An,S_An,D_Mois,3)) -> 0 | J26: =IF(INDEX(I_Top,8)="",0,SUMIFS(D_CO2,D_Grp,INDEX(I_Top,8),D_An,S_An,D_Mois,3)) -> 0 | K26: =MAX(0,C9-SUM(C26:J26)) -> 0
B27: avr. | C27: =IF(INDEX(I_Top,1)="",0,SUMIFS(D_CO2,D_Grp,INDEX(I_Top,1),D_An,S_An,D_Mois,4)) -> 0 | D27: =IF(INDEX(I_Top,2)="",0,SUMIFS(D_CO2,D_Grp,INDEX(I_Top,2),D_An,S_An,D_Mois,4)) -> 0 | E27: =IF(INDEX(I_Top,3)="",0,SUMIFS(D_CO2,D_Grp,INDEX(I_Top,3),D_An,S_An,D_Mois,4)) -> 0 | F27: =IF(INDEX(I_Top,4)="",0,SUMIFS(D_CO2,D_Grp,INDEX(I_Top,4),D_An,S_An,D_Mois,4)) -> 0 | G27: =IF(INDEX(I_Top,5)="",0,SUMIFS(D_CO2,D_Grp,INDEX(I_Top,5),D_An,S_An,D_Mois,4)) -> 0 | H27: =IF(INDEX(I_Top,6)="",0,SUMIFS(D_CO2,D_Grp,INDEX(I_Top,6),D_An,S_An,D_Mois,4)) -> 0 | I27: =IF(INDEX(I_Top,7)="",0,SUMIFS(D_CO2,D_Grp,INDEX(I_Top,7),D_An,S_An,D_Mois,4)) -> 0 | J27: =IF(INDEX(I_Top,8)="",0,SUMIFS(D_CO2,D_Grp,INDEX(I_Top,8),D_An,S_An,D_Mois,4)) -> 0 | K27: =MAX(0,C10-SUM(C27:J27)) -> 0
B28: mai | C28: =IF(INDEX(I_Top,1)="",0,SUMIFS(D_CO2,D_Grp,INDEX(I_Top,1),D_An,S_An,D_Mois,5)) -> 0 | D28: =IF(INDEX(I_Top,2)="",0,SUMIFS(D_CO2,D_Grp,INDEX(I_Top,2),D_An,S_An,D_Mois,5)) -> 0 | E28: =IF(INDEX(I_Top,3)="",0,SUMIFS(D_CO2,D_Grp,INDEX(I_Top,3),D_An,S_An,D_Mois,5)) -> 0 | F28: =IF(INDEX(I_Top,4)="",0,SUMIFS(D_CO2,D_Grp,INDEX(I_Top,4),D_An,S_An,D_Mois,5)) -> 0 | G28: =IF(INDEX(I_Top,5)="",0,SUMIFS(D_CO2,D_Grp,INDEX(I_Top,5),D_An,S_An,D_Mois,5)) -> 0 | H28: =IF(INDEX(I_Top,6)="",0,SUMIFS(D_CO2,D_Grp,INDEX(I_Top,6),D_An,S_An,D_Mois,5)) -> 0 | I28: =IF(INDEX(I_Top,7)="",0,SUMIFS(D_CO2,D_Grp,INDEX(I_Top,7),D_An,S_An,D_Mois,5)) -> 0 | J28: =IF(INDEX(I_Top,8)="",0,SUMIFS(D_CO2,D_Grp,INDEX(I_Top,8),D_An,S_An,D_Mois,5)) -> 0 | K28: =MAX(0,C11-SUM(C28:J28)) -> 0
B29: juin | C29: =IF(INDEX(I_Top,1)="",0,SUMIFS(D_CO2,D_Grp,INDEX(I_Top,1),D_An,S_An,D_Mois,6)) -> 0 | D29: =IF(INDEX(I_Top,2)="",0,SUMIFS(D_CO2,D_Grp,INDEX(I_Top,2),D_An,S_An,D_Mois,6)) -> 0 | E29: =IF(INDEX(I_Top,3)="",0,SUMIFS(D_CO2,D_Grp,INDEX(I_Top,3),D_An,S_An,D_Mois,6)) -> 0 | F29: =IF(INDEX(I_Top,4)="",0,SUMIFS(D_CO2,D_Grp,INDEX(I_Top,4),D_An,S_An,D_Mois,6)) -> 0 | G29: =IF(INDEX(I_Top,5)="",0,SUMIFS(D_CO2,D_Grp,INDEX(I_Top,5),D_An,S_An,D_Mois,6)) -> 0 | H29: =IF(INDEX(I_Top,6)="",0,SUMIFS(D_CO2,D_Grp,INDEX(I_Top,6),D_An,S_An,D_Mois,6)) -> 0 | I29: =IF(INDEX(I_Top,7)="",0,SUMIFS(D_CO2,D_Grp,INDEX(I_Top,7),D_An,S_An,D_Mois,6)) -> 0 | J29: =IF(INDEX(I_Top,8)="",0,SUMIFS(D_CO2,D_Grp,INDEX(I_Top,8),D_An,S_An,D_Mois,6)) -> 0 | K29: =MAX(0,C12-SUM(C29:J29)) -> 0
B30: juil. | C30: =IF(INDEX(I_Top,1)="",0,SUMIFS(D_CO2,D_Grp,INDEX(I_Top,1),D_An,S_An,D_Mois,7)) -> 0 | D30: =IF(INDEX(I_Top,2)="",0,SUMIFS(D_CO2,D_Grp,INDEX(I_Top,2),D_An,S_An,D_Mois,7)) -> 0 | E30: =IF(INDEX(I_Top,3)="",0,SUMIFS(D_CO2,D_Grp,INDEX(I_Top,3),D_An,S_An,D_Mois,7)) -> 0 | F30: =IF(INDEX(I_Top,4)="",0,SUMIFS(D_CO2,D_Grp,INDEX(I_Top,4),D_An,S_An,D_Mois,7)) -> 0 | G30: =IF(INDEX(I_Top,5)="",0,SUMIFS(D_CO2,D_Grp,INDEX(I_Top,5),D_An,S_An,D_Mois,7)) -> 0 | H30: =IF(INDEX(I_Top,6)="",0,SUMIFS(D_CO2,D_Grp,INDEX(I_Top,6),D_An,S_An,D_Mois,7)) -> 0 | I30: =IF(INDEX(I_Top,7)="",0,SUMIFS(D_CO2,D_Grp,INDEX(I_Top,7),D_An,S_An,D_Mois,7)) -> 0 | J30: =IF(INDEX(I_Top,8)="",0,SUMIFS(D_CO2,D_Grp,INDEX(I_Top,8),D_An,S_An,D_Mois,7)) -> 0 | K30: =MAX(0,C13-SUM(C30:J30)) -> 0
B31: août | C31: =IF(INDEX(I_Top,1)="",0,SUMIFS(D_CO2,D_Grp,INDEX(I_Top,1),D_An,S_An,D_Mois,8)) -> 0 | D31: =IF(INDEX(I_Top,2)="",0,SUMIFS(D_CO2,D_Grp,INDEX(I_Top,2),D_An,S_An,D_Mois,8)) -> 0 | E31: =IF(INDEX(I_Top,3)="",0,SUMIFS(D_CO2,D_Grp,INDEX(I_Top,3),D_An,S_An,D_Mois,8)) -> 0 | F31: =IF(INDEX(I_Top,4)="",0,SUMIFS(D_CO2,D_Grp,INDEX(I_Top,4),D_An,S_An,D_Mois,8)) -> 0 | G31: =IF(INDEX(I_Top,5)="",0,SUMIFS(D_CO2,D_Grp,INDEX(I_Top,5),D_An,S_An,D_Mois,8)) -> 0 | H31: =IF(INDEX(I_Top,6)="",0,SUMIFS(D_CO2,D_Grp,INDEX(I_Top,6),D_An,S_An,D_Mois,8)) -> 0 | I31: =IF(INDEX(I_Top,7)="",0,SUMIFS(D_CO2,D_Grp,INDEX(I_Top,7),D_An,S_An,D_Mois,8)) -> 0 | J31: =IF(INDEX(I_Top,8)="",0,SUMIFS(D_CO2,D_Grp,INDEX(I_Top,8),D_An,S_An,D_Mois,8)) -> 0 | K31: =MAX(0,C14-SUM(C31:J31)) -> 0
B32: sept. | C32: =IF(INDEX(I_Top,1)="",0,SUMIFS(D_CO2,D_Grp,INDEX(I_Top,1),D_An,S_An,D_Mois,9)) -> 0 | D32: =IF(INDEX(I_Top,2)="",0,SUMIFS(D_CO2,D_Grp,INDEX(I_Top,2),D_An,S_An,D_Mois,9)) -> 0 | E32: =IF(INDEX(I_Top,3)="",0,SUMIFS(D_CO2,D_Grp,INDEX(I_Top,3),D_An,S_An,D_Mois,9)) -> 0 | F32: =IF(INDEX(I_Top,4)="",0,SUMIFS(D_CO2,D_Grp,INDEX(I_Top,4),D_An,S_An,D_Mois,9)) -> 0 | G32: =IF(INDEX(I_Top,5)="",0,SUMIFS(D_CO2,D_Grp,INDEX(I_Top,5),D_An,S_An,D_Mois,9)) -> 0 | H32: =IF(INDEX(I_Top,6)="",0,SUMIFS(D_CO2,D_Grp,INDEX(I_Top,6),D_An,S_An,D_Mois,9)) -> 0 | I32: =IF(INDEX(I_Top,7)="",0,SUMIFS(D_CO2,D_Grp,INDEX(I_Top,7),D_An,S_An,D_Mois,9)) -> 0 | J32: =IF(INDEX(I_Top,8)="",0,SUMIFS(D_CO2,D_Grp,INDEX(I_Top,8),D_An,S_An,D_Mois,9)) -> 0 | K32: =MAX(0,C15-SUM(C32:J32)) -> 0
B33: oct. | C33: =IF(INDEX(I_Top,1)="",0,SUMIFS(D_CO2,D_Grp,INDEX(I_Top,1),D_An,S_An,D_Mois,10)) -> 0 | D33: =IF(INDEX(I_Top,2)="",0,SUMIFS(D_CO2,D_Grp,INDEX(I_Top,2),D_An,S_An,D_Mois,10)) -> 0 | E33: =IF(INDEX(I_Top,3)="",0,SUMIFS(D_CO2,D_Grp,INDEX(I_Top,3),D_An,S_An,D_Mois,10)) -> 0 | F33: =IF(INDEX(I_Top,4)="",0,SUMIFS(D_CO2,D_Grp,INDEX(I_Top,4),D_An,S_An,D_Mois,10)) -> 0 | G33: =IF(INDEX(I_Top,5)="",0,SUMIFS(D_CO2,D_Grp,INDEX(I_Top,5),D_An,S_An,D_Mois,10)) -> 0 | H33: =IF(INDEX(I_Top,6)="",0,SUMIFS(D_CO2,D_Grp,INDEX(I_Top,6),D_An,S_An,D_Mois,10)) -> 0 | I33: =IF(INDEX(I_Top,7)="",0,SUMIFS(D_CO2,D_Grp,INDEX(I_Top,7),D_An,S_An,D_Mois,10)) -> 0 | J33: =IF(INDEX(I_Top,8)="",0,SUMIFS(D_CO2,D_Grp,INDEX(I_Top,8),D_An,S_An,D_Mois,10)) -> 0 | K33: =MAX(0,C16-SUM(C33:J33)) -> 0
B34: nov. | C34: =IF(INDEX(I_Top,1)="",0,SUMIFS(D_CO2,D_Grp,INDEX(I_Top,1),D_An,S_An,D_Mois,11)) -> 0 | D34: =IF(INDEX(I_Top,2)="",0,SUMIFS(D_CO2,D_Grp,INDEX(I_Top,2),D_An,S_An,D_Mois,11)) -> 0 | E34: =IF(INDEX(I_Top,3)="",0,SUMIFS(D_CO2,D_Grp,INDEX(I_Top,3),D_An,S_An,D_Mois,11)) -> 0 | F34: =IF(INDEX(I_Top,4)="",0,SUMIFS(D_CO2,D_Grp,INDEX(I_Top,4),D_An,S_An,D_Mois,11)) -> 0 | G34: =IF(INDEX(I_Top,5)="",0,SUMIFS(D_CO2,D_Grp,INDEX(I_Top,5),D_An,S_An,D_Mois,11)) -> 0 | H34: =IF(INDEX(I_Top,6)="",0,SUMIFS(D_CO2,D_Grp,INDEX(I_Top,6),D_An,S_An,D_Mois,11)) -> 0 | I34: =IF(INDEX(I_Top,7)="",0,SUMIFS(D_CO2,D_Grp,INDEX(I_Top,7),D_An,S_An,D_Mois,11)) -> 0 | J34: =IF(INDEX(I_Top,8)="",0,SUMIFS(D_CO2,D_Grp,INDEX(I_Top,8),D_An,S_An,D_Mois,11)) -> 0 | K34: =MAX(0,C17-SUM(C34:J34)) -> 0
B35: déc. | C35: =IF(INDEX(I_Top,1)="",0,SUMIFS(D_CO2,D_Grp,INDEX(I_Top,1),D_An,S_An,D_Mois,12)) -> 0 | D35: =IF(INDEX(I_Top,2)="",0,SUMIFS(D_CO2,D_Grp,INDEX(I_Top,2),D_An,S_An,D_Mois,12)) -> 0 | E35: =IF(INDEX(I_Top,3)="",0,SUMIFS(D_CO2,D_Grp,INDEX(I_Top,3),D_An,S_An,D_Mois,12)) -> 0 | F35: =IF(INDEX(I_Top,4)="",0,SUMIFS(D_CO2,D_Grp,INDEX(I_Top,4),D_An,S_An,D_Mois,12)) -> 0 | G35: =IF(INDEX(I_Top,5)="",0,SUMIFS(D_CO2,D_Grp,INDEX(I_Top,5),D_An,S_An,D_Mois,12)) -> 0 | H35: =IF(INDEX(I_Top,6)="",0,SUMIFS(D_CO2,D_Grp,INDEX(I_Top,6),D_An,S_An,D_Mois,12)) -> 0 | I35: =IF(INDEX(I_Top,7)="",0,SUMIFS(D_CO2,D_Grp,INDEX(I_Top,7),D_An,S_An,D_Mois,12)) -> 0 | J35: =IF(INDEX(I_Top,8)="",0,SUMIFS(D_CO2,D_Grp,INDEX(I_Top,8),D_An,S_An,D_Mois,12)) -> 0 | K35: =MAX(0,C18-SUM(C35:J35)) -> 0
B38: Classement des modèles (année affichée)
B39: Rang | C39: Modèle | D39: kgCO₂e | E39: Part | F39: Énergie | G39: Tokens éq. output | H39: Coût brut | I39: gCO₂e par $ | J39: FE retenu (kgCO₂e/token) | K39: Source du FE
B40: =IF(C40="","",1) | C40: =IF(INDEX(I_CO2,L40)>0,INDEX(I_Nom,L40),"") | D40: =IF(C40="","",INDEX(I_CO2,L40)) | E40: =IF(C40="","",D40/S_YTD) | F40: =IF(C40="","",INDEX(I_kWh,L40)) | G40: =IF(C40="","",INDEX(I_TO,L40)) | H40: =IF(C40="","",INDEX(I_Brut,L40)) | I40: =IF(C40="","",IF(H40>0,D40*1000/H40,"")) | J40: =IF(C40="","",INDEX(M_FE,L40)) | K40: =IF(C40="","",INDEX(M_Src,L40)) | L40: =MATCH(LARGE(I_Key,1),I_Key,0) -> 1
B41: =IF(C41="","",2) | C41: =IF(INDEX(I_CO2,L41)>0,INDEX(I_Nom,L41),"") | D41: =IF(C41="","",INDEX(I_CO2,L41)) | E41: =IF(C41="","",D41/S_YTD) | F41: =IF(C41="","",INDEX(I_kWh,L41)) | G41: =IF(C41="","",INDEX(I_TO,L41)) | H41: =IF(C41="","",INDEX(I_Brut,L41)) | I41: =IF(C41="","",IF(H41>0,D41*1000/H41,"")) | J41: =IF(C41="","",INDEX(M_FE,L41)) | K41: =IF(C41="","",INDEX(M_Src,L41)) | L41: =MATCH(LARGE(I_Key,2),I_Key,0) -> 2
B42: =IF(C42="","",3) | C42: =IF(INDEX(I_CO2,L42)>0,INDEX(I_Nom,L42),"") | D42: =IF(C42="","",INDEX(I_CO2,L42)) | E42: =IF(C42="","",D42/S_YTD) | F42: =IF(C42="","",INDEX(I_kWh,L42)) | G42: =IF(C42="","",INDEX(I_TO,L42)) | H42: =IF(C42="","",INDEX(I_Brut,L42)) | I42: =IF(C42="","",IF(H42>0,D42*1000/H42,"")) | J42: =IF(C42="","",INDEX(M_FE,L42)) | K42: =IF(C42="","",INDEX(M_Src,L42)) | L42: =MATCH(LARGE(I_Key,3),I_Key,0) -> 3
B43: =IF(C43="","",4) | C43: =IF(INDEX(I_CO2,L43)>0,INDEX(I_Nom,L43),"") | D43: =IF(C43="","",INDEX(I_CO2,L43)) | E43: =IF(C43="","",D43/S_YTD) | F43: =IF(C43="","",INDEX(I_kWh,L43)) | G43: =IF(C43="","",INDEX(I_TO,L43)) | H43: =IF(C43="","",INDEX(I_Brut,L43)) | I43: =IF(C43="","",IF(H43>0,D43*1000/H43,"")) | J43: =IF(C43="","",INDEX(M_FE,L43)) | K43: =IF(C43="","",INDEX(M_Src,L43)) | L43: =MATCH(LARGE(I_Key,4),I_Key,0) -> 4
B44: =IF(C44="","",5) | C44: =IF(INDEX(I_CO2,L44)>0,INDEX(I_Nom,L44),"") | D44: =IF(C44="","",INDEX(I_CO2,L44)) | E44: =IF(C44="","",D44/S_YTD) | F44: =IF(C44="","",INDEX(I_kWh,L44)) | G44: =IF(C44="","",INDEX(I_TO,L44)) | H44: =IF(C44="","",INDEX(I_Brut,L44)) | I44: =IF(C44="","",IF(H44>0,D44*1000/H44,"")) | J44: =IF(C44="","",INDEX(M_FE,L44)) | K44: =IF(C44="","",INDEX(M_Src,L44)) | L44: =MATCH(LARGE(I_Key,5),I_Key,0) -> 5
B45: =IF(C45="","",6) | C45: =IF(INDEX(I_CO2,L45)>0,INDEX(I_Nom,L45),"") | D45: =IF(C45="","",INDEX(I_CO2,L45)) | E45: =IF(C45="","",D45/S_YTD) | F45: =IF(C45="","",INDEX(I_kWh,L45)) | G45: =IF(C45="","",INDEX(I_TO,L45)) | H45: =IF(C45="","",INDEX(I_Brut,L45)) | I45: =IF(C45="","",IF(H45>0,D45*1000/H45,"")) | J45: =IF(C45="","",INDEX(M_FE,L45)) | K45: =IF(C45="","",INDEX(M_Src,L45)) | L45: =MATCH(LARGE(I_Key,6),I_Key,0) -> 6
B46: =IF(C46="","",7) | C46: =IF(INDEX(I_CO2,L46)>0,INDEX(I_Nom,L46),"") | D46: =IF(C46="","",INDEX(I_CO2,L46)) | E46: =IF(C46="","",D46/S_YTD) | F46: =IF(C46="","",INDEX(I_kWh,L46)) | G46: =IF(C46="","",INDEX(I_TO,L46)) | H46: =IF(C46="","",INDEX(I_Brut,L46)) | I46: =IF(C46="","",IF(H46>0,D46*1000/H46,"")) | J46: =IF(C46="","",INDEX(M_FE,L46)) | K46: =IF(C46="","",INDEX(M_Src,L46)) | L46: =MATCH(LARGE(I_Key,7),I_Key,0) -> 7
B47: =IF(C47="","",8) | C47: =IF(INDEX(I_CO2,L47)>0,INDEX(I_Nom,L47),"") | D47: =IF(C47="","",INDEX(I_CO2,L47)) | E47: =IF(C47="","",D47/S_YTD) | F47: =IF(C47="","",INDEX(I_kWh,L47)) | G47: =IF(C47="","",INDEX(I_TO,L47)) | H47: =IF(C47="","",INDEX(I_Brut,L47)) | I47: =IF(C47="","",IF(H47>0,D47*1000/H47,"")) | J47: =IF(C47="","",INDEX(M_FE,L47)) | K47: =IF(C47="","",INDEX(M_Src,L47)) | L47: =MATCH(LARGE(I_Key,8),I_Key,0) -> 8
B48: =IF(C48="","",9) | C48: =IF(INDEX(I_CO2,L48)>0,INDEX(I_Nom,L48),"") | D48: =IF(C48="","",INDEX(I_CO2,L48)) | E48: =IF(C48="","",D48/S_YTD) | F48: =IF(C48="","",INDEX(I_kWh,L48)) | G48: =IF(C48="","",INDEX(I_TO,L48)) | H48: =IF(C48="","",INDEX(I_Brut,L48)) | I48: =IF(C48="","",IF(H48>0,D48*1000/H48,"")) | J48: =IF(C48="","",INDEX(M_FE,L48)) | K48: =IF(C48="","",INDEX(M_Src,L48)) | L48: =MATCH(LARGE(I_Key,9),I_Key,0) -> 9
B49: =IF(C49="","",10) | C49: =IF(INDEX(I_CO2,L49)>0,INDEX(I_Nom,L49),"") | D49: =IF(C49="","",INDEX(I_CO2,L49)) | E49: =IF(C49="","",D49/S_YTD) | F49: =IF(C49="","",INDEX(I_kWh,L49)) | G49: =IF(C49="","",INDEX(I_TO,L49)) | H49: =IF(C49="","",INDEX(I_Brut,L49)) | I49: =IF(C49="","",IF(H49>0,D49*1000/H49,"")) | J49: =IF(C49="","",INDEX(M_FE,L49)) | K49: =IF(C49="","",INDEX(M_Src,L49)) | L49: =MATCH(LARGE(I_Key,10),I_Key,0) -> 10
B50: =IF(C50="","",11) | C50: =IF(INDEX(I_CO2,L50)>0,INDEX(I_Nom,L50),"") | D50: =IF(C50="","",INDEX(I_CO2,L50)) | E50: =IF(C50="","",D50/S_YTD) | F50: =IF(C50="","",INDEX(I_kWh,L50)) | G50: =IF(C50="","",INDEX(I_TO,L50)) | H50: =IF(C50="","",INDEX(I_Brut,L50)) | I50: =IF(C50="","",IF(H50>0,D50*1000/H50,"")) | J50: =IF(C50="","",INDEX(M_FE,L50)) | K50: =IF(C50="","",INDEX(M_Src,L50)) | L50: =MATCH(LARGE(I_Key,11),I_Key,0) -> 11
B51: =IF(C51="","",12) | C51: =IF(INDEX(I_CO2,L51)>0,INDEX(I_Nom,L51),"") | D51: =IF(C51="","",INDEX(I_CO2,L51)) | E51: =IF(C51="","",D51/S_YTD) | F51: =IF(C51="","",INDEX(I_kWh,L51)) | G51: =IF(C51="","",INDEX(I_TO,L51)) | H51: =IF(C51="","",INDEX(I_Brut,L51)) | I51: =IF(C51="","",IF(H51>0,D51*1000/H51,"")) | J51: =IF(C51="","",INDEX(M_FE,L51)) | K51: =IF(C51="","",INDEX(M_Src,L51)) | L51: =MATCH(LARGE(I_Key,12),I_Key,0) -> 12
B52: =IF(C52="","",13) | C52: =IF(INDEX(I_CO2,L52)>0,INDEX(I_Nom,L52),"") | D52: =IF(C52="","",INDEX(I_CO2,L52)) | E52: =IF(C52="","",D52/S_YTD) | F52: =IF(C52="","",INDEX(I_kWh,L52)) | G52: =IF(C52="","",INDEX(I_TO,L52)) | H52: =IF(C52="","",INDEX(I_Brut,L52)) | I52: =IF(C52="","",IF(H52>0,D52*1000/H52,"")) | J52: =IF(C52="","",INDEX(M_FE,L52)) | K52: =IF(C52="","",INDEX(M_Src,L52)) | L52: =MATCH(LARGE(I_Key,13),I_Key,0) -> 13
B53: =IF(C53="","",14) | C53: =IF(INDEX(I_CO2,L53)>0,INDEX(I_Nom,L53),"") | D53: =IF(C53="","",INDEX(I_CO2,L53)) | E53: =IF(C53="","",D53/S_YTD) | F53: =IF(C53="","",INDEX(I_kWh,L53)) | G53: =IF(C53="","",INDEX(I_TO,L53)) | H53: =IF(C53="","",INDEX(I_Brut,L53)) | I53: =IF(C53="","",IF(H53>0,D53*1000/H53,"")) | J53: =IF(C53="","",INDEX(M_FE,L53)) | K53: =IF(C53="","",INDEX(M_Src,L53)) | L53: =MATCH(LARGE(I_Key,14),I_Key,0) -> 14
B54: =IF(C54="","",15) | C54: =IF(INDEX(I_CO2,L54)>0,INDEX(I_Nom,L54),"") | D54: =IF(C54="","",INDEX(I_CO2,L54)) | E54: =IF(C54="","",D54/S_YTD) | F54: =IF(C54="","",INDEX(I_kWh,L54)) | G54: =IF(C54="","",INDEX(I_TO,L54)) | H54: =IF(C54="","",INDEX(I_Brut,L54)) | I54: =IF(C54="","",IF(H54>0,D54*1000/H54,"")) | J54: =IF(C54="","",INDEX(M_FE,L54)) | K54: =IF(C54="","",INDEX(M_Src,L54)) | L54: =MATCH(LARGE(I_Key,15),I_Key,0) -> 15
B55: =IF(C55="","",16) | C55: =IF(INDEX(I_CO2,L55)>0,INDEX(I_Nom,L55),"") | D55: =IF(C55="","",INDEX(I_CO2,L55)) | E55: =IF(C55="","",D55/S_YTD) | F55: =IF(C55="","",INDEX(I_kWh,L55)) | G55: =IF(C55="","",INDEX(I_TO,L55)) | H55: =IF(C55="","",INDEX(I_Brut,L55)) | I55: =IF(C55="","",IF(H55>0,D55*1000/H55,"")) | J55: =IF(C55="","",INDEX(M_FE,L55)) | K55: =IF(C55="","",INDEX(M_Src,L55)) | L55: =MATCH(LARGE(I_Key,16),I_Key,0) -> 16
B56: =IF(C56="","",17) | C56: =IF(INDEX(I_CO2,L56)>0,INDEX(I_Nom,L56),"") | D56: =IF(C56="","",INDEX(I_CO2,L56)) | E56: =IF(C56="","",D56/S_YTD) | F56: =IF(C56="","",INDEX(I_kWh,L56)) | G56: =IF(C56="","",INDEX(I_TO,L56)) | H56: =IF(C56="","",INDEX(I_Brut,L56)) | I56: =IF(C56="","",IF(H56>0,D56*1000/H56,"")) | J56: =IF(C56="","",INDEX(M_FE,L56)) | K56: =IF(C56="","",INDEX(M_Src,L56)) | L56: =MATCH(LARGE(I_Key,17),I_Key,0) -> 17
B57: =IF(C57="","",18) | C57: =IF(INDEX(I_CO2,L57)>0,INDEX(I_Nom,L57),"") | D57: =IF(C57="","",INDEX(I_CO2,L57)) | E57: =IF(C57="","",D57/S_YTD) | F57: =IF(C57="","",INDEX(I_kWh,L57)) | G57: =IF(C57="","",INDEX(I_TO,L57)) | H57: =IF(C57="","",INDEX(I_Brut,L57)) | I57: =IF(C57="","",IF(H57>0,D57*1000/H57,"")) | J57: =IF(C57="","",INDEX(M_FE,L57)) | K57: =IF(C57="","",INDEX(M_Src,L57)) | L57: =MATCH(LARGE(I_Key,18),I_Key,0) -> 18
B58: =IF(C58="","",19) | C58: =IF(INDEX(I_CO2,L58)>0,INDEX(I_Nom,L58),"") | D58: =IF(C58="","",INDEX(I_CO2,L58)) | E58: =IF(C58="","",D58/S_YTD) | F58: =IF(C58="","",INDEX(I_kWh,L58)) | G58: =IF(C58="","",INDEX(I_TO,L58)) | H58: =IF(C58="","",INDEX(I_Brut,L58)) | I58: =IF(C58="","",IF(H58>0,D58*1000/H58,"")) | J58: =IF(C58="","",INDEX(M_FE,L58)) | K58: =IF(C58="","",INDEX(M_Src,L58)) | L58: =MATCH(LARGE(I_Key,19),I_Key,0) -> 19
B59: =IF(C59="","",20) | C59: =IF(INDEX(I_CO2,L59)>0,INDEX(I_Nom,L59),"") | D59: =IF(C59="","",INDEX(I_CO2,L59)) | E59: =IF(C59="","",D59/S_YTD) | F59: =IF(C59="","",INDEX(I_kWh,L59)) | G59: =IF(C59="","",INDEX(I_TO,L59)) | H59: =IF(C59="","",INDEX(I_Brut,L59)) | I59: =IF(C59="","",IF(H59>0,D59*1000/H59,"")) | J59: =IF(C59="","",INDEX(M_FE,L59)) | K59: =IF(C59="","",INDEX(M_Src,L59)) | L59: =MATCH(LARGE(I_Key,20),I_Key,0) -> 20
B60: =IF(C60="","",21) | C60: =IF(INDEX(I_CO2,L60)>0,INDEX(I_Nom,L60),"") | D60: =IF(C60="","",INDEX(I_CO2,L60)) | E60: =IF(C60="","",D60/S_YTD) | F60: =IF(C60="","",INDEX(I_kWh,L60)) | G60: =IF(C60="","",INDEX(I_TO,L60)) | H60: =IF(C60="","",INDEX(I_Brut,L60)) | I60: =IF(C60="","",IF(H60>0,D60*1000/H60,"")) | J60: =IF(C60="","",INDEX(M_FE,L60)) | K60: =IF(C60="","",INDEX(M_Src,L60)) | L60: =MATCH(LARGE(I_Key,21),I_Key,0) -> 21
B61: =IF(C61="","",22) | C61: =IF(INDEX(I_CO2,L61)>0,INDEX(I_Nom,L61),"") | D61: =IF(C61="","",INDEX(I_CO2,L61)) | E61: =IF(C61="","",D61/S_YTD) | F61: =IF(C61="","",INDEX(I_kWh,L61)) | G61: =IF(C61="","",INDEX(I_TO,L61)) | H61: =IF(C61="","",INDEX(I_Brut,L61)) | I61: =IF(C61="","",IF(H61>0,D61*1000/H61,"")) | J61: =IF(C61="","",INDEX(M_FE,L61)) | K61: =IF(C61="","",INDEX(M_Src,L61)) | L61: =MATCH(LARGE(I_Key,22),I_Key,0) -> 22
B62: =IF(C62="","",23) | C62: =IF(INDEX(I_CO2,L62)>0,INDEX(I_Nom,L62),"") | D62: =IF(C62="","",INDEX(I_CO2,L62)) | E62: =IF(C62="","",D62/S_YTD) | F62: =IF(C62="","",INDEX(I_kWh,L62)) | G62: =IF(C62="","",INDEX(I_TO,L62)) | H62: =IF(C62="","",INDEX(I_Brut,L62)) | I62: =IF(C62="","",IF(H62>0,D62*1000/H62,"")) | J62: =IF(C62="","",INDEX(M_FE,L62)) | K62: =IF(C62="","",INDEX(M_Src,L62)) | L62: =MATCH(LARGE(I_Key,23),I_Key,0) -> 23
B63: =IF(C63="","",24) | C63: =IF(INDEX(I_CO2,L63)>0,INDEX(I_Nom,L63),"") | D63: =IF(C63="","",INDEX(I_CO2,L63)) | E63: =IF(C63="","",D63/S_YTD) | F63: =IF(C63="","",INDEX(I_kWh,L63)) | G63: =IF(C63="","",INDEX(I_TO,L63)) | H63: =IF(C63="","",INDEX(I_Brut,L63)) | I63: =IF(C63="","",IF(H63>0,D63*1000/H63,"")) | J63: =IF(C63="","",INDEX(M_FE,L63)) | K63: =IF(C63="","",INDEX(M_Src,L63)) | L63: =MATCH(LARGE(I_Key,24),I_Key,0) -> 24
B64: =IF(C64="","",25) | C64: =IF(INDEX(I_CO2,L64)>0,INDEX(I_Nom,L64),"") | D64: =IF(C64="","",INDEX(I_CO2,L64)) | E64: =IF(C64="","",D64/S_YTD) | F64: =IF(C64="","",INDEX(I_kWh,L64)) | G64: =IF(C64="","",INDEX(I_TO,L64)) | H64: =IF(C64="","",INDEX(I_Brut,L64)) | I64: =IF(C64="","",IF(H64>0,D64*1000/H64,"")) | J64: =IF(C64="","",INDEX(M_FE,L64)) | K64: =IF(C64="","",INDEX(M_Src,L64)) | L64: =MATCH(LARGE(I_Key,25),I_Key,0) -> 25
B65: =IF(C65="","",26) | C65: =IF(INDEX(I_CO2,L65)>0,INDEX(I_Nom,L65),"") | D65: =IF(C65="","",INDEX(I_CO2,L65)) | E65: =IF(C65="","",D65/S_YTD) | F65: =IF(C65="","",INDEX(I_kWh,L65)) | G65: =IF(C65="","",INDEX(I_TO,L65)) | H65: =IF(C65="","",INDEX(I_Brut,L65)) | I65: =IF(C65="","",IF(H65>0,D65*1000/H65,"")) | J65: =IF(C65="","",INDEX(M_FE,L65)) | K65: =IF(C65="","",INDEX(M_Src,L65)) | L65: =MATCH(LARGE(I_Key,26),I_Key,0) -> 26
B66: =IF(C66="","",27) | C66: =IF(INDEX(I_CO2,L66)>0,INDEX(I_Nom,L66),"") | D66: =IF(C66="","",INDEX(I_CO2,L66)) | E66: =IF(C66="","",D66/S_YTD) | F66: =IF(C66="","",INDEX(I_kWh,L66)) | G66: =IF(C66="","",INDEX(I_TO,L66)) | H66: =IF(C66="","",INDEX(I_Brut,L66)) | I66: =IF(C66="","",IF(H66>0,D66*1000/H66,"")) | J66: =IF(C66="","",INDEX(M_FE,L66)) | K66: =IF(C66="","",INDEX(M_Src,L66)) | L66: =MATCH(LARGE(I_Key,27),I_Key,0) -> 27
B67: =IF(C67="","",28) | C67: =IF(INDEX(I_CO2,L67)>0,INDEX(I_Nom,L67),"") | D67: =IF(C67="","",INDEX(I_CO2,L67)) | E67: =IF(C67="","",D67/S_YTD) | F67: =IF(C67="","",INDEX(I_kWh,L67)) | G67: =IF(C67="","",INDEX(I_TO,L67)) | H67: =IF(C67="","",INDEX(I_Brut,L67)) | I67: =IF(C67="","",IF(H67>0,D67*1000/H67,"")) | J67: =IF(C67="","",INDEX(M_FE,L67)) | K67: =IF(C67="","",INDEX(M_Src,L67)) | L67: =MATCH(LARGE(I_Key,28),I_Key,0) -> 28
B68: =IF(C68="","",29) | C68: =IF(INDEX(I_CO2,L68)>0,INDEX(I_Nom,L68),"") | D68: =IF(C68="","",INDEX(I_CO2,L68)) | E68: =IF(C68="","",D68/S_YTD) | F68: =IF(C68="","",INDEX(I_kWh,L68)) | G68: =IF(C68="","",INDEX(I_TO,L68)) | H68: =IF(C68="","",INDEX(I_Brut,L68)) | I68: =IF(C68="","",IF(H68>0,D68*1000/H68,"")) | J68: =IF(C68="","",INDEX(M_FE,L68)) | K68: =IF(C68="","",INDEX(M_Src,L68)) | L68: =MATCH(LARGE(I_Key,29),I_Key,0) -> 29
B69: =IF(C69="","",30) | C69: =IF(INDEX(I_CO2,L69)>0,INDEX(I_Nom,L69),"") | D69: =IF(C69="","",INDEX(I_CO2,L69)) | E69: =IF(C69="","",D69/S_YTD) | F69: =IF(C69="","",INDEX(I_kWh,L69)) | G69: =IF(C69="","",INDEX(I_TO,L69)) | H69: =IF(C69="","",INDEX(I_Brut,L69)) | I69: =IF(C69="","",IF(H69>0,D69*1000/H69,"")) | J69: =IF(C69="","",INDEX(M_FE,L69)) | K69: =IF(C69="","",INDEX(M_Src,L69)) | L69: =MATCH(LARGE(I_Key,30),I_Key,0) -> 30
B70: =IF(C70="","",31) | C70: =IF(INDEX(I_CO2,L70)>0,INDEX(I_Nom,L70),"") | D70: =IF(C70="","",INDEX(I_CO2,L70)) | E70: =IF(C70="","",D70/S_YTD) | F70: =IF(C70="","",INDEX(I_kWh,L70)) | G70: =IF(C70="","",INDEX(I_TO,L70)) | H70: =IF(C70="","",INDEX(I_Brut,L70)) | I70: =IF(C70="","",IF(H70>0,D70*1000/H70,"")) | J70: =IF(C70="","",INDEX(M_FE,L70)) | K70: =IF(C70="","",INDEX(M_Src,L70)) | L70: =MATCH(LARGE(I_Key,31),I_Key,0) -> 31
B71: =IF(C71="","",32) | C71: =IF(INDEX(I_CO2,L71)>0,INDEX(I_Nom,L71),"") | D71: =IF(C71="","",INDEX(I_CO2,L71)) | E71: =IF(C71="","",D71/S_YTD) | F71: =IF(C71="","",INDEX(I_kWh,L71)) | G71: =IF(C71="","",INDEX(I_TO,L71)) | H71: =IF(C71="","",INDEX(I_Brut,L71)) | I71: =IF(C71="","",IF(H71>0,D71*1000/H71,"")) | J71: =IF(C71="","",INDEX(M_FE,L71)) | K71: =IF(C71="","",INDEX(M_Src,L71)) | L71: =MATCH(LARGE(I_Key,32),I_Key,0) -> 32
B72: =IF(C72="","",33) | C72: =IF(INDEX(I_CO2,L72)>0,INDEX(I_Nom,L72),"") | D72: =IF(C72="","",INDEX(I_CO2,L72)) | E72: =IF(C72="","",D72/S_YTD) | F72: =IF(C72="","",INDEX(I_kWh,L72)) | G72: =IF(C72="","",INDEX(I_TO,L72)) | H72: =IF(C72="","",INDEX(I_Brut,L72)) | I72: =IF(C72="","",IF(H72>0,D72*1000/H72,"")) | J72: =IF(C72="","",INDEX(M_FE,L72)) | K72: =IF(C72="","",INDEX(M_Src,L72)) | L72: =MATCH(LARGE(I_Key,33),I_Key,0) -> 33
B73: =IF(C73="","",34) | C73: =IF(INDEX(I_CO2,L73)>0,INDEX(I_Nom,L73),"") | D73: =IF(C73="","",INDEX(I_CO2,L73)) | E73: =IF(C73="","",D73/S_YTD) | F73: =IF(C73="","",INDEX(I_kWh,L73)) | G73: =IF(C73="","",INDEX(I_TO,L73)) | H73: =IF(C73="","",INDEX(I_Brut,L73)) | I73: =IF(C73="","",IF(H73>0,D73*1000/H73,"")) | J73: =IF(C73="","",INDEX(M_FE,L73)) | K73: =IF(C73="","",INDEX(M_Src,L73)) | L73: =MATCH(LARGE(I_Key,34),I_Key,0) -> 34
B74: =IF(C74="","",35) | C74: =IF(INDEX(I_CO2,L74)>0,INDEX(I_Nom,L74),"") | D74: =IF(C74="","",INDEX(I_CO2,L74)) | E74: =IF(C74="","",D74/S_YTD) | F74: =IF(C74="","",INDEX(I_kWh,L74)) | G74: =IF(C74="","",INDEX(I_TO,L74)) | H74: =IF(C74="","",INDEX(I_Brut,L74)) | I74: =IF(C74="","",IF(H74>0,D74*1000/H74,"")) | J74: =IF(C74="","",INDEX(M_FE,L74)) | K74: =IF(C74="","",INDEX(M_Src,L74)) | L74: =MATCH(LARGE(I_Key,35),I_Key,0) -> 35
B75: =IF(C75="","",36) | C75: =IF(INDEX(I_CO2,L75)>0,INDEX(I_Nom,L75),"") | D75: =IF(C75="","",INDEX(I_CO2,L75)) | E75: =IF(C75="","",D75/S_YTD) | F75: =IF(C75="","",INDEX(I_kWh,L75)) | G75: =IF(C75="","",INDEX(I_TO,L75)) | H75: =IF(C75="","",INDEX(I_Brut,L75)) | I75: =IF(C75="","",IF(H75>0,D75*1000/H75,"")) | J75: =IF(C75="","",INDEX(M_FE,L75)) | K75: =IF(C75="","",INDEX(M_Src,L75)) | L75: =MATCH(LARGE(I_Key,36),I_Key,0) -> 36
B76: =IF(C76="","",37) | C76: =IF(INDEX(I_CO2,L76)>0,INDEX(I_Nom,L76),"") | D76: =IF(C76="","",INDEX(I_CO2,L76)) | E76: =IF(C76="","",D76/S_YTD) | F76: =IF(C76="","",INDEX(I_kWh,L76)) | G76: =IF(C76="","",INDEX(I_TO,L76)) | H76: =IF(C76="","",INDEX(I_Brut,L76)) | I76: =IF(C76="","",IF(H76>0,D76*1000/H76,"")) | J76: =IF(C76="","",INDEX(M_FE,L76)) | K76: =IF(C76="","",INDEX(M_Src,L76)) | L76: =MATCH(LARGE(I_Key,37),I_Key,0) -> 37
B77: =IF(C77="","",38) | C77: =IF(INDEX(I_CO2,L77)>0,INDEX(I_Nom,L77),"") | D77: =IF(C77="","",INDEX(I_CO2,L77)) | E77: =IF(C77="","",D77/S_YTD) | F77: =IF(C77="","",INDEX(I_kWh,L77)) | G77: =IF(C77="","",INDEX(I_TO,L77)) | H77: =IF(C77="","",INDEX(I_Brut,L77)) | I77: =IF(C77="","",IF(H77>0,D77*1000/H77,"")) | J77: =IF(C77="","",INDEX(M_FE,L77)) | K77: =IF(C77="","",INDEX(M_Src,L77)) | L77: =MATCH(LARGE(I_Key,38),I_Key,0) -> 38
B78: =IF(C78="","",39) | C78: =IF(INDEX(I_CO2,L78)>0,INDEX(I_Nom,L78),"") | D78: =IF(C78="","",INDEX(I_CO2,L78)) | E78: =IF(C78="","",D78/S_YTD) | F78: =IF(C78="","",INDEX(I_kWh,L78)) | G78: =IF(C78="","",INDEX(I_TO,L78)) | H78: =IF(C78="","",INDEX(I_Brut,L78)) | I78: =IF(C78="","",IF(H78>0,D78*1000/H78,"")) | J78: =IF(C78="","",INDEX(M_FE,L78)) | K78: =IF(C78="","",INDEX(M_Src,L78)) | L78: =MATCH(LARGE(I_Key,39),I_Key,0) -> 39
B79: =IF(C79="","",40) | C79: =IF(INDEX(I_CO2,L79)>0,INDEX(I_Nom,L79),"") | D79: =IF(C79="","",INDEX(I_CO2,L79)) | E79: =IF(C79="","",D79/S_YTD) | F79: =IF(C79="","",INDEX(I_kWh,L79)) | G79: =IF(C79="","",INDEX(I_TO,L79)) | H79: =IF(C79="","",INDEX(I_Brut,L79)) | I79: =IF(C79="","",IF(H79>0,D79*1000/H79,"")) | J79: =IF(C79="","",INDEX(M_FE,L79)) | K79: =IF(C79="","",INDEX(M_Src,L79)) | L79: =MATCH(LARGE(I_Key,40),I_Key,0) -> 40
B80: =IF(C80="","",41) | C80: =IF(INDEX(I_CO2,L80)>0,INDEX(I_Nom,L80),"") | D80: =IF(C80="","",INDEX(I_CO2,L80)) | E80: =IF(C80="","",D80/S_YTD) | F80: =IF(C80="","",INDEX(I_kWh,L80)) | G80: =IF(C80="","",INDEX(I_TO,L80)) | H80: =IF(C80="","",INDEX(I_Brut,L80)) | I80: =IF(C80="","",IF(H80>0,D80*1000/H80,"")) | J80: =IF(C80="","",INDEX(M_FE,L80)) | K80: =IF(C80="","",INDEX(M_Src,L80)) | L80: =MATCH(LARGE(I_Key,41),I_Key,0) -> 41
B81: =IF(C81="","",42) | C81: =IF(INDEX(I_CO2,L81)>0,INDEX(I_Nom,L81),"") | D81: =IF(C81="","",INDEX(I_CO2,L81)) | E81: =IF(C81="","",D81/S_YTD) | F81: =IF(C81="","",INDEX(I_kWh,L81)) | G81: =IF(C81="","",INDEX(I_TO,L81)) | H81: =IF(C81="","",INDEX(I_Brut,L81)) | I81: =IF(C81="","",IF(H81>0,D81*1000/H81,"")) | J81: =IF(C81="","",INDEX(M_FE,L81)) | K81: =IF(C81="","",INDEX(M_Src,L81)) | L81: =MATCH(LARGE(I_Key,42),I_Key,0) -> 42
B82: =IF(C82="","",43) | C82: =IF(INDEX(I_CO2,L82)>0,INDEX(I_Nom,L82),"") | D82: =IF(C82="","",INDEX(I_CO2,L82)) | E82: =IF(C82="","",D82/S_YTD) | F82: =IF(C82="","",INDEX(I_kWh,L82)) | G82: =IF(C82="","",INDEX(I_TO,L82)) | H82: =IF(C82="","",INDEX(I_Brut,L82)) | I82: =IF(C82="","",IF(H82>0,D82*1000/H82,"")) | J82: =IF(C82="","",INDEX(M_FE,L82)) | K82: =IF(C82="","",INDEX(M_Src,L82)) | L82: =MATCH(LARGE(I_Key,43),I_Key,0) -> 43
B83: =IF(C83="","",44) | C83: =IF(INDEX(I_CO2,L83)>0,INDEX(I_Nom,L83),"") | D83: =IF(C83="","",INDEX(I_CO2,L83)) | E83: =IF(C83="","",D83/S_YTD) | F83: =IF(C83="","",INDEX(I_kWh,L83)) | G83: =IF(C83="","",INDEX(I_TO,L83)) | H83: =IF(C83="","",INDEX(I_Brut,L83)) | I83: =IF(C83="","",IF(H83>0,D83*1000/H83,"")) | J83: =IF(C83="","",INDEX(M_FE,L83)) | K83: =IF(C83="","",INDEX(M_Src,L83)) | L83: =MATCH(LARGE(I_Key,44),I_Key,0) -> 44
B84: =IF(C84="","",45) | C84: =IF(INDEX(I_CO2,L84)>0,INDEX(I_Nom,L84),"") | D84: =IF(C84="","",INDEX(I_CO2,L84)) | E84: =IF(C84="","",D84/S_YTD) | F84: =IF(C84="","",INDEX(I_kWh,L84)) | G84: =IF(C84="","",INDEX(I_TO,L84)) | H84: =IF(C84="","",INDEX(I_Brut,L84)) | I84: =IF(C84="","",IF(H84>0,D84*1000/H84,"")) | J84: =IF(C84="","",INDEX(M_FE,L84)) | K84: =IF(C84="","",INDEX(M_Src,L84)) | L84: =MATCH(LARGE(I_Key,45),I_Key,0) -> 45
B85: =IF(C85="","",46) | C85: =IF(INDEX(I_CO2,L85)>0,INDEX(I_Nom,L85),"") | D85: =IF(C85="","",INDEX(I_CO2,L85)) | E85: =IF(C85="","",D85/S_YTD) | F85: =IF(C85="","",INDEX(I_kWh,L85)) | G85: =IF(C85="","",INDEX(I_TO,L85)) | H85: =IF(C85="","",INDEX(I_Brut,L85)) | I85: =IF(C85="","",IF(H85>0,D85*1000/H85,"")) | J85: =IF(C85="","",INDEX(M_FE,L85)) | K85: =IF(C85="","",INDEX(M_Src,L85)) | L85: =MATCH(LARGE(I_Key,46),I_Key,0) -> 46
B86: =IF(C86="","",47) | C86: =IF(INDEX(I_CO2,L86)>0,INDEX(I_Nom,L86),"") | D86: =IF(C86="","",INDEX(I_CO2,L86)) | E86: =IF(C86="","",D86/S_YTD) | F86: =IF(C86="","",INDEX(I_kWh,L86)) | G86: =IF(C86="","",INDEX(I_TO,L86)) | H86: =IF(C86="","",INDEX(I_Brut,L86)) | I86: =IF(C86="","",IF(H86>0,D86*1000/H86,"")) | J86: =IF(C86="","",INDEX(M_FE,L86)) | K86: =IF(C86="","",INDEX(M_Src,L86)) | L86: =MATCH(LARGE(I_Key,47),I_Key,0) -> 47
B87: =IF(C87="","",48) | C87: =IF(INDEX(I_CO2,L87)>0,INDEX(I_Nom,L87),"") | D87: =IF(C87="","",INDEX(I_CO2,L87)) | E87: =IF(C87="","",D87/S_YTD) | F87: =IF(C87="","",INDEX(I_kWh,L87)) | G87: =IF(C87="","",INDEX(I_TO,L87)) | H87: =IF(C87="","",INDEX(I_Brut,L87)) | I87: =IF(C87="","",IF(H87>0,D87*1000/H87,"")) | J87: =IF(C87="","",INDEX(M_FE,L87)) | K87: =IF(C87="","",INDEX(M_Src,L87)) | L87: =MATCH(LARGE(I_Key,48),I_Key,0) -> 48
B88: =IF(C88="","",49) | C88: =IF(INDEX(I_CO2,L88)>0,INDEX(I_Nom,L88),"") | D88: =IF(C88="","",INDEX(I_CO2,L88)) | E88: =IF(C88="","",D88/S_YTD) | F88: =IF(C88="","",INDEX(I_kWh,L88)) | G88: =IF(C88="","",INDEX(I_TO,L88)) | H88: =IF(C88="","",INDEX(I_Brut,L88)) | I88: =IF(C88="","",IF(H88>0,D88*1000/H88,"")) | J88: =IF(C88="","",INDEX(M_FE,L88)) | K88: =IF(C88="","",INDEX(M_Src,L88)) | L88: =MATCH(LARGE(I_Key,49),I_Key,0) -> 49
B89: =IF(C89="","",50) | C89: =IF(INDEX(I_CO2,L89)>0,INDEX(I_Nom,L89),"") | D89: =IF(C89="","",INDEX(I_CO2,L89)) | E89: =IF(C89="","",D89/S_YTD) | F89: =IF(C89="","",INDEX(I_kWh,L89)) | G89: =IF(C89="","",INDEX(I_TO,L89)) | H89: =IF(C89="","",INDEX(I_Brut,L89)) | I89: =IF(C89="","",IF(H89>0,D89*1000/H89,"")) | J89: =IF(C89="","",INDEX(M_FE,L89)) | K89: =IF(C89="","",INDEX(M_Src,L89)) | L89: =MATCH(LARGE(I_Key,50),I_Key,0) -> 50
B90: =IF(C90="","",51) | C90: =IF(INDEX(I_CO2,L90)>0,INDEX(I_Nom,L90),"") | D90: =IF(C90="","",INDEX(I_CO2,L90)) | E90: =IF(C90="","",D90/S_YTD) | F90: =IF(C90="","",INDEX(I_kWh,L90)) | G90: =IF(C90="","",INDEX(I_TO,L90)) | H90: =IF(C90="","",INDEX(I_Brut,L90)) | I90: =IF(C90="","",IF(H90>0,D90*1000/H90,"")) | J90: =IF(C90="","",INDEX(M_FE,L90)) | K90: =IF(C90="","",INDEX(M_Src,L90)) | L90: =MATCH(LARGE(I_Key,51),I_Key,0) -> 51
B91: =IF(C91="","",52) | C91: =IF(INDEX(I_CO2,L91)>0,INDEX(I_Nom,L91),"") | D91: =IF(C91="","",INDEX(I_CO2,L91)) | E91: =IF(C91="","",D91/S_YTD) | F91: =IF(C91="","",INDEX(I_kWh,L91)) | G91: =IF(C91="","",INDEX(I_TO,L91)) | H91: =IF(C91="","",INDEX(I_Brut,L91)) | I91: =IF(C91="","",IF(H91>0,D91*1000/H91,"")) | J91: =IF(C91="","",INDEX(M_FE,L91)) | K91: =IF(C91="","",INDEX(M_Src,L91)) | L91: =MATCH(LARGE(I_Key,52),I_Key,0) -> 52
B92: =IF(C92="","",53) | C92: =IF(INDEX(I_CO2,L92)>0,INDEX(I_Nom,L92),"") | D92: =IF(C92="","",INDEX(I_CO2,L92)) | E92: =IF(C92="","",D92/S_YTD) | F92: =IF(C92="","",INDEX(I_kWh,L92)) | G92: =IF(C92="","",INDEX(I_TO,L92)) | H92: =IF(C92="","",INDEX(I_Brut,L92)) | I92: =IF(C92="","",IF(H92>0,D92*1000/H92,"")) | J92: =IF(C92="","",INDEX(M_FE,L92)) | K92: =IF(C92="","",INDEX(M_Src,L92)) | L92: =MATCH(LARGE(I_Key,53),I_Key,0) -> 53
B93: =IF(C93="","",54) | C93: =IF(INDEX(I_CO2,L93)>0,INDEX(I_Nom,L93),"") | D93: =IF(C93="","",INDEX(I_CO2,L93)) | E93: =IF(C93="","",D93/S_YTD) | F93: =IF(C93="","",INDEX(I_kWh,L93)) | G93: =IF(C93="","",INDEX(I_TO,L93)) | H93: =IF(C93="","",INDEX(I_Brut,L93)) | I93: =IF(C93="","",IF(H93>0,D93*1000/H93,"")) | J93: =IF(C93="","",INDEX(M_FE,L93)) | K93: =IF(C93="","",INDEX(M_Src,L93)) | L93: =MATCH(LARGE(I_Key,54),I_Key,0) -> 54
B94: =IF(C94="","",55) | C94: =IF(INDEX(I_CO2,L94)>0,INDEX(I_Nom,L94),"") | D94: =IF(C94="","",INDEX(I_CO2,L94)) | E94: =IF(C94="","",D94/S_YTD) | F94: =IF(C94="","",INDEX(I_kWh,L94)) | G94: =IF(C94="","",INDEX(I_TO,L94)) | H94: =IF(C94="","",INDEX(I_Brut,L94)) | I94: =IF(C94="","",IF(H94>0,D94*1000/H94,"")) | J94: =IF(C94="","",INDEX(M_FE,L94)) | K94: =IF(C94="","",INDEX(M_Src,L94)) | L94: =MATCH(LARGE(I_Key,55),I_Key,0) -> 55
B95: =IF(C95="","",56) | C95: =IF(INDEX(I_CO2,L95)>0,INDEX(I_Nom,L95),"") | D95: =IF(C95="","",INDEX(I_CO2,L95)) | E95: =IF(C95="","",D95/S_YTD) | F95: =IF(C95="","",INDEX(I_kWh,L95)) | G95: =IF(C95="","",INDEX(I_TO,L95)) | H95: =IF(C95="","",INDEX(I_Brut,L95)) | I95: =IF(C95="","",IF(H95>0,D95*1000/H95,"")) | J95: =IF(C95="","",INDEX(M_FE,L95)) | K95: =IF(C95="","",INDEX(M_Src,L95)) | L95: =MATCH(LARGE(I_Key,56),I_Key,0) -> 56
B96: =IF(C96="","",57) | C96: =IF(INDEX(I_CO2,L96)>0,INDEX(I_Nom,L96),"") | D96: =IF(C96="","",INDEX(I_CO2,L96)) | E96: =IF(C96="","",D96/S_YTD) | F96: =IF(C96="","",INDEX(I_kWh,L96)) | G96: =IF(C96="","",INDEX(I_TO,L96)) | H96: =IF(C96="","",INDEX(I_Brut,L96)) | I96: =IF(C96="","",IF(H96>0,D96*1000/H96,"")) | J96: =IF(C96="","",INDEX(M_FE,L96)) | K96: =IF(C96="","",INDEX(M_Src,L96)) | L96: =MATCH(LARGE(I_Key,57),I_Key,0) -> 57
B97: =IF(C97="","",58) | C97: =IF(INDEX(I_CO2,L97)>0,INDEX(I_Nom,L97),"") | D97: =IF(C97="","",INDEX(I_CO2,L97)) | E97: =IF(C97="","",D97/S_YTD) | F97: =IF(C97="","",INDEX(I_kWh,L97)) | G97: =IF(C97="","",INDEX(I_TO,L97)) | H97: =IF(C97="","",INDEX(I_Brut,L97)) | I97: =IF(C97="","",IF(H97>0,D97*1000/H97,"")) | J97: =IF(C97="","",INDEX(M_FE,L97)) | K97: =IF(C97="","",INDEX(M_Src,L97)) | L97: =MATCH(LARGE(I_Key,58),I_Key,0) -> 58
B98: =IF(C98="","",59) | C98: =IF(INDEX(I_CO2,L98)>0,INDEX(I_Nom,L98),"") | D98: =IF(C98="","",INDEX(I_CO2,L98)) | E98: =IF(C98="","",D98/S_YTD) | F98: =IF(C98="","",INDEX(I_kWh,L98)) | G98: =IF(C98="","",INDEX(I_TO,L98)) | H98: =IF(C98="","",INDEX(I_Brut,L98)) | I98: =IF(C98="","",IF(H98>0,D98*1000/H98,"")) | J98: =IF(C98="","",INDEX(M_FE,L98)) | K98: =IF(C98="","",INDEX(M_Src,L98)) | L98: =MATCH(LARGE(I_Key,59),I_Key,0) -> 59
B99: =IF(C99="","",60) | C99: =IF(INDEX(I_CO2,L99)>0,INDEX(I_Nom,L99),"") | D99: =IF(C99="","",INDEX(I_CO2,L99)) | E99: =IF(C99="","",D99/S_YTD) | F99: =IF(C99="","",INDEX(I_kWh,L99)) | G99: =IF(C99="","",INDEX(I_TO,L99)) | H99: =IF(C99="","",INDEX(I_Brut,L99)) | I99: =IF(C99="","",IF(H99>0,D99*1000/H99,"")) | J99: =IF(C99="","",INDEX(M_FE,L99)) | K99: =IF(C99="","",INDEX(M_Src,L99)) | L99: =MATCH(LARGE(I_Key,60),I_Key,0) -> 60
B100: =IF(C100="","",61) | C100: =IF(INDEX(I_CO2,L100)>0,INDEX(I_Nom,L100),"") | D100: =IF(C100="","",INDEX(I_CO2,L100)) | E100: =IF(C100="","",D100/S_YTD) | F100: =IF(C100="","",INDEX(I_kWh,L100)) | G100: =IF(C100="","",INDEX(I_TO,L100)) | H100: =IF(C100="","",INDEX(I_Brut,L100)) | I100: =IF(C100="","",IF(H100>0,D100*1000/H100,"")) | J100: =IF(C100="","",INDEX(M_FE,L100)) | K100: =IF(C100="","",INDEX(M_Src,L100)) | L100: =MATCH(LARGE(I_Key,61),I_Key,0) -> 61
B101: =IF(C101="","",62) | C101: =IF(INDEX(I_CO2,L101)>0,INDEX(I_Nom,L101),"") | D101: =IF(C101="","",INDEX(I_CO2,L101)) | E101: =IF(C101="","",D101/S_YTD) | F101: =IF(C101="","",INDEX(I_kWh,L101)) | G101: =IF(C101="","",INDEX(I_TO,L101)) | H101: =IF(C101="","",INDEX(I_Brut,L101)) | I101: =IF(C101="","",IF(H101>0,D101*1000/H101,"")) | J101: =IF(C101="","",INDEX(M_FE,L101)) | K101: =IF(C101="","",INDEX(M_Src,L101)) | L101: =MATCH(LARGE(I_Key,62),I_Key,0) -> 62
B102: =IF(C102="","",63) | C102: =IF(INDEX(I_CO2,L102)>0,INDEX(I_Nom,L102),"") | D102: =IF(C102="","",INDEX(I_CO2,L102)) | E102: =IF(C102="","",D102/S_YTD) | F102: =IF(C102="","",INDEX(I_kWh,L102)) | G102: =IF(C102="","",INDEX(I_TO,L102)) | H102: =IF(C102="","",INDEX(I_Brut,L102)) | I102: =IF(C102="","",IF(H102>0,D102*1000/H102,"")) | J102: =IF(C102="","",INDEX(M_FE,L102)) | K102: =IF(C102="","",INDEX(M_Src,L102)) | L102: =MATCH(LARGE(I_Key,63),I_Key,0) -> 63
B103: =IF(C103="","",64) | C103: =IF(INDEX(I_CO2,L103)>0,INDEX(I_Nom,L103),"") | D103: =IF(C103="","",INDEX(I_CO2,L103)) | E103: =IF(C103="","",D103/S_YTD) | F103: =IF(C103="","",INDEX(I_kWh,L103)) | G103: =IF(C103="","",INDEX(I_TO,L103)) | H103: =IF(C103="","",INDEX(I_Brut,L103)) | I103: =IF(C103="","",IF(H103>0,D103*1000/H103,"")) | J103: =IF(C103="","",INDEX(M_FE,L103)) | K103: =IF(C103="","",INDEX(M_Src,L103)) | L103: =MATCH(LARGE(I_Key,64),I_Key,0) -> 64
B104: =IF(C104="","",65) | C104: =IF(INDEX(I_CO2,L104)>0,INDEX(I_Nom,L104),"") | D104: =IF(C104="","",INDEX(I_CO2,L104)) | E104: =IF(C104="","",D104/S_YTD) | F104: =IF(C104="","",INDEX(I_kWh,L104)) | G104: =IF(C104="","",INDEX(I_TO,L104)) | H104: =IF(C104="","",INDEX(I_Brut,L104)) | I104: =IF(C104="","",IF(H104>0,D104*1000/H104,"")) | J104: =IF(C104="","",INDEX(M_FE,L104)) | K104: =IF(C104="","",INDEX(M_Src,L104)) | L104: =MATCH(LARGE(I_Key,65),I_Key,0) -> 65
B105: =IF(C105="","",66) | C105: =IF(INDEX(I_CO2,L105)>0,INDEX(I_Nom,L105),"") | D105: =IF(C105="","",INDEX(I_CO2,L105)) | E105: =IF(C105="","",D105/S_YTD) | F105: =IF(C105="","",INDEX(I_kWh,L105)) | G105: =IF(C105="","",INDEX(I_TO,L105)) | H105: =IF(C105="","",INDEX(I_Brut,L105)) | I105: =IF(C105="","",IF(H105>0,D105*1000/H105,"")) | J105: =IF(C105="","",INDEX(M_FE,L105)) | K105: =IF(C105="","",INDEX(M_Src,L105)) | L105: =MATCH(LARGE(I_Key,66),I_Key,0) -> 66
...

Sheet Calcul
B2: Calcul
B3: Formules, paramètres globaux et paramètres par modèle. Les cellules jaunes sont modifiables ; tout le classeur se recalcule.
B5: Réglages généraux | G5: Familles : convention par défaut (API du fournisseur)
B6: Source des facteurs d'émission | C6: Table fournie | D6: « Table fournie » = votre table kgCO₂e/token (23/10/2026). Les modèles absents de la table passent par le Calculateur de Boris. | G6: Famille | H6: Convention | I6: Source
B7: Mix électrique (Calculateur de Boris) | C7: France (2020, EEA) | D7: Sert au calcul des modèles absents de la table, et à la vue de sensibilité C6. | G7: Anthropic | H7: Exclusive | I7: Doc Anthropic : total = cache read + cache creation + input
B8: Mix personnalisé (gCO₂e/kWh) | C8: 300 | D8: Utilisé seulement si le mix choisi est « Personnalisé ». | G8: OpenAI ≥ GPT-5.6 | H8: Inclusive | I8: Doc OpenAI : input ordinaire = input − cached − write
B9: Mix retenu (gCO₂e/kWh) | C9: =IF(P_MixNom="Personnalisé",P_MixPerso,INDEX(L_MixVal,MATCH(P_MixNom,L_MixNom,0))) -> 51.1 | D9: =INDEX(L_MixSrc,MATCH(P_MixNom,L_MixNom,0)) -> EEA, défaut du Calculateur de Boris | G9: OpenAI < GPT-5.6 | H9: Inclusive | I9: Doc OpenAI : pas d'écriture facturée (ε sans objet)
B10: Inclure la fabrication (scope 3) | C10: Oui | D10: Le Calculateur de Boris ajoute la fabrication du matériel par token. Votre méthode l'exclut : mettre « Non » pour s'y conformer. | G10: Google Gemini | H10: Inclusive | I10: Doc Gemini : promptTokenCount inclut le cache
B11: Fourchette d'incertitude basse (×) | C11: 0.5 | D11: Multiplicateur appliqué au résultat central pour la borne basse. | G11: xAI Grok | H11: Inclusive | I11: Doc xAI : le total du prompt compte le cache
B12: Fourchette d'incertitude haute (×) | C12: 2 | D12: Multiplicateur appliqué au résultat central pour la borne haute. | G12: Moonshot Kimi | H12: Inclusive | I12: Doc Fireworks : cache inclus dans le total du prompt
B13: Projection : fenêtre (jours) | C13: 28 | D13: Rythme quotidien moyen des N derniers jours de données, prolongé jusqu'au 31 décembre. | G13: Microsoft MAI | H13: Inclusive | I13: Aucune source trouvée : inclusive par défaut
B14: Projection : ajustement | C14: 0 | D14: Hausse ou baisse appliquée au rythme projeté (ex. +10 % si le déploiement s'élargit). | G14: Hors grille | H14: Inclusive | I14: Modèle absent de la grille : inclusive par défaut
G15: Ordre d'application : convention forcée, sinon C2 (cache > input sur une ligne : exclusive), sinon C3 (rapprochement des coûts de la famille), sinon cette valeur.
B16: Formules (par ligne de l'export)
B17: Input frais (tokens) | C17: F = max(0, I − δ·CR − ε·CW)
B18: Tokens équivalent output | C18: T_O = F·s_I + CR·s_CR + CW·s_CW + O
B19: Énergie (kWh) | C19: E = T_O × e_O × PUE / 1000
B20: Empreinte (kgCO₂e) | C20: CO₂e = T_O × FE_token
B21: FE_token calculé (Calculateur de Boris) | C21: FE = e_O × PUE × FE_mix / 10⁶ + fab
B23: I, O, CR, CW : colonnes input, output, cache_read, cache_write. δ, ε : convention de l'input (1 = l'input contient déjà le cache). s_I, s_CR, s_CW : prix rapportés au prix de l'output. Les formules sont dans les colonnes bleues de l'onglet Données.
B27: Paramètres par modèle
B28: Grille GitHub du 20/10/2026 ($ par million de tokens). Pour un nouveau modèle, remplissez une ligne vide en bas de la table (au minimum Modèle, prix et e_O). Les noms « Auto: X » utilisent la ligne de X. « (Autre modèle) » sert aux modèles inconnus.
B29: Modèle | C29: Famille | D29: Convention forcée | E29: Convention appliquée | F29: Origine | G29: δ | H29: ε | I29: P_I | J29: P_CR | K29: P_CW | L29: P_O | M29: Tarif valable avant le | N29: s_I | O29: s_CR | P29: s_CW | Q29: Scénario EcoLogits | R29: e_O (Wh/token) | S29: PUE | T29: fab (kgCO₂e/token) | U29: FE table (kgCO₂e/token) | V29: S/H | W29: FE forcé (kgCO₂e/token) | X29: FE calculé (kgCO₂e/token) | Y29: FE retenu (kgCO₂e/token) | Z29: Source du FE
B30: GPT-5.3-Codex | C30: OpenAI < GPT-5.6 | E30: =IF(B30="","",IF(D30<>"",D30,IF('Contrôles'!$J$62>0,"Exclusive",IF('Contrôles'!$U$62<>"",'Contrôles'!$U$62,IFERROR(INDEX(F_Conv,MATCH(C30,F_Fam,0)),"Inclusive"))))) -> Inclusive | F30: =IF(B30="","",IF(D30<>"","Forcée",IF('Contrôles'!$J$62>0,"C2",IF('Contrôles'!$U$62<>"","C3","Défaut API")))) -> Défaut API | G30: =IF(B30="","",IF(E30="Exclusive",0,1)) -> 1 | H30: =IF(B30="","",IF(E30="Inclusive",1,0)) -> 1 | I30: 1.75 | J30: 0.175 | L30: 14 | N30: =IF(B30="","",IF(N(L30)>0,I30/L30,0.2)) -> 0.125 | O30: =IF(B30="","",IF(N(L30)>0,J30/L30,0.02)) -> 0.0125 | P30: =IF(B30="","",IF(N(L30)>0,IF(K30="",I30,K30)/L30,0.25)) -> 0.125 | Q30: gpt-5.3-codex | R30: 0.0020268642 | S30: 1.2 | T30: 5.124195e-08 | U30: 5.9e-07 | V30: H | X30: =IF(B30="","",R30*S30*P_Mix/1000000+IF(P_Fab="Oui",T30,0)) -> 1.7552926e-07 | Y30: =IF(B30="","",IF(W30<>"",W30,IF(AND(P_Source="Table fournie",U30<>""),U30,X30))) -> 5.9e-07 | Z30: =IF(B30="","",IF(W30<>"","Forcé",IF(AND(P_Source="Table fournie",U30<>""),IF(V30="H","Table (hypothèse)","Table (sourcé)"),"Calculateur de Boris"))) -> Table (hypothèse)
B31: GPT-5.4 nano | C31: OpenAI < GPT-5.6 | E31: =IF(B31="","",IF(D31<>"",D31,IF('Contrôles'!$J$63>0,"Exclusive",IF('Contrôles'!$U$63<>"",'Contrôles'!$U$63,IFERROR(INDEX(F_Conv,MATCH(C31,F_Fam,0)),"Inclusive"))))) -> Inclusive | F31: =IF(B31="","",IF(D31<>"","Forcée",IF('Contrôles'!$J$63>0,"C2",IF('Contrôles'!$U$63<>"","C3","Défaut API")))) -> Défaut API | G31: =IF(B31="","",IF(E31="Exclusive",0,1)) -> 1 | H31: =IF(B31="","",IF(E31="Inclusive",1,0)) -> 1 | I31: 0.2 | J31: 0.02 | L31: 1.25 | N31: =IF(B31="","",IF(N(L31)>0,I31/L31,0.2)) -> 0.16 | O31: =IF(B31="","",IF(N(L31)>0,J31/L31,0.02)) -> 0.016 | P31: =IF(B31="","",IF(N(L31)>0,IF(K31="",I31,K31)/L31,0.25)) -> 0.16 | Q31: gpt-5-nano (proxy) | R31: 5.6971481e-05 | S31: 1.2 | T31: 1.756778e-09 | U31: 1.659e-08 | V31: H | X31: =IF(B31="","",R31*S31*P_Mix/1000000+IF(P_Fab="Oui",T31,0)) -> 5.2502692e-09 | Y31: =IF(B31="","",IF(W31<>"",W31,IF(AND(P_Source="Table fournie",U31<>""),U31,X31))) -> 1.659e-08 | Z31: =IF(B31="","",IF(W31<>"","Forcé",IF(AND(P_Source="Table fournie",U31<>""),IF(V31="H","Table (hypothèse)","Table (sourcé)"),"Calculateur de Boris"))) -> Table (hypothèse)
B32: GPT-5.6 Luna | C32: OpenAI ≥ GPT-5.6 | E32: =IF(B32="","",IF(D32<>"",D32,IF('Contrôles'!$J$64>0,"Exclusive",IF('Contrôles'!$U$64<>"",'Contrôles'!$U$64,IFERROR(INDEX(F_Conv,MATCH(C32,F_Fam,0)),"Inclusive"))))) -> Inclusive | F32: =IF(B32="","",IF(D32<>"","Forcée",IF('Contrôles'!$J$64>0,"C2",IF('Contrôles'!$U$64<>"","C3","Défaut API")))) -> Défaut API | G32: =IF(B32="","",IF(E32="Exclusive",0,1)) -> 1 | H32: =IF(B32="","",IF(E32="Inclusive",1,0)) -> 1 | I32: 0.2 | J32: 0.02 | K32: 0.25 | L32: 1.2 | N32: =IF(B32="","",IF(N(L32)>0,I32/L32,0.2)) -> 0.16666667 | O32: =IF(B32="","",IF(N(L32)>0,J32/L32,0.02)) -> 0.016666667 | P32: =IF(B32="","",IF(N(L32)>0,IF(K32="",I32,K32)/L32,0.25)) -> 0.20833333 | Q32: gpt-5-mini (proxy) | R32: 0.00037684316 | S32: 1.2 | T32: 1.229372e-08 | U32: 1e-08 | V32: S | X32: =IF(B32="","",R32*S32*P_Mix/1000000+IF(P_Fab="Oui",T32,0)) -> 3.5401743e-08 | Y32: =IF(B32="","",IF(W32<>"",W32,IF(AND(P_Source="Table fournie",U32<>""),U32,X32))) -> 1e-08 | Z32: =IF(B32="","",IF(W32<>"","Forcé",IF(AND(P_Source="Table fournie",U32<>""),IF(V32="H","Table (hypothèse)","Table (sourcé)"),"Calculateur de Boris"))) -> Table (sourcé)
B33: GPT-5.6 Terra | C33: OpenAI ≥ GPT-5.6 | E33: =IF(B33="","",IF(D33<>"",D33,IF('Contrôles'!$J$65>0,"Exclusive",IF('Contrôles'!$U$65<>"",'Contrôles'!$U$65,IFERROR(INDEX(F_Conv,MATCH(C33,F_Fam,0)),"Inclusive"))))) -> Inclusive | F33: =IF(B33="","",IF(D33<>"","Forcée",IF('Contrôles'!$J$65>0,"C2",IF('Contrôles'!$U$65<>"","C3","Défaut API")))) -> Défaut API | G33: =IF(B33="","",IF(E33="Exclusive",0,1)) -> 1 | H33: =IF(B33="","",IF(E33="Inclusive",1,0)) -> 1 | I33: 2 | J33: 0.2 | K33: 2.5 | L33: 12 | N33: =IF(B33="","",IF(N(L33)>0,I33/L33,0.2)) -> 0.16666667 | O33: =IF(B33="","",IF(N(L33)>0,J33/L33,0.02)) -> 0.016666667 | P33: =IF(B33="","",IF(N(L33)>0,IF(K33="",I33,K33)/L33,0.25)) -> 0.20833333 | Q33: gpt-5.4 (proxy) | R33: 0.0017884687 | S33: 1.2 | T33: 5.090409e-08 | U33: 1e-07 | V33: S | X33: =IF(B33="","",R33*S33*P_Mix/1000000+IF(P_Fab="Oui",T33,0)) -> 1.6057299e-07 | Y33: =IF(B33="","",IF(W33<>"",W33,IF(AND(P_Source="Table fournie",U33<>""),U33,X33))) -> 1e-07 | Z33: =IF(B33="","",IF(W33<>"","Forcé",IF(AND(P_Source="Table fournie",U33<>""),IF(V33="H","Table (hypothèse)","Table (sourcé)"),"Calculateur de Boris"))) -> Table (sourcé)
B34: GPT-5.6 Sol | C34: OpenAI ≥ GPT-5.6 | E34: =IF(B34="","",IF(D34<>"",D34,IF('Contrôles'!$J$66>0,"Exclusive",IF('Contrôles'!$U$66<>"",'Contrôles'!$U$66,IFERROR(INDEX(F_Conv,MATCH(C34,F_Fam,0)),"Inclusive"))))) -> Inclusive | F34: =IF(B34="","",IF(D34<>"","Forcée",IF('Contrôles'!$J$66>0,"C2",IF('Contrôles'!$U$66<>"","C3","Défaut API")))) -> Défaut API | G34: =IF(B34="","",IF(E34="Exclusive",0,1)) -> 1 | H34: =IF(B34="","",IF(E34="Inclusive",1,0)) -> 1 | I34: 4 | J34: 0.4 | K34: 5 | L34: 20 | N34: =IF(B34="","",IF(N(L34)>0,I34/L34,0.2)) -> 0.2 | O34: =IF(B34="","",IF(N(L34)>0,J34/L34,0.02)) -> 0.02 | P34: =IF(B34="","",IF(N(L34)>0,IF(K34="",I34,K34)/L34,0.25)) -> 0.25 | Q34: gpt-5.5 (proxy) | R34: 0.0054568626 | S34: 1.2 | T34: 1.146602e-07 | U34: 5.9e-07 | V34: S | X34: =IF(B34="","",R34*S34*P_Mix/1000000+IF(P_Fab="Oui",T34,0)) -> 4.4927501e-07 | Y34: =IF(B34="","",IF(W34<>"",W34,IF(AND(P_Source="Table fournie",U34<>""),U34,X34))) -> 5.9e-07 | Z34: =IF(B34="","",IF(W34<>"","Forcé",IF(AND(P_Source="Table fournie",U34<>""),IF(V34="H","Table (hypothèse)","Table (sourcé)"),"Calculateur de Boris"))) -> Table (sourcé)
B35: GPT-6 Luna | C35: OpenAI ≥ GPT-5.6 | E35: =IF(B35="","",IF(D35<>"",D35,IF('Contrôles'!$J$67>0,"Exclusive",IF('Contrôles'!$U$67<>"",'Contrôles'!$U$67,IFERROR(INDEX(F_Conv,MATCH(C35,F_Fam,0)),"Inclusive"))))) -> Inclusive | F35: =IF(B35="","",IF(D35<>"","Forcée",IF('Contrôles'!$J$67>0,"C2",IF('Contrôles'!$U$67<>"","C3","Défaut API")))) -> Défaut API | G35: =IF(B35="","",IF(E35="Exclusive",0,1)) -> 1 | H35: =IF(B35="","",IF(E35="Inclusive",1,0)) -> 1 | I35: 0.1 | J35: 0.01 | K35: 0.125 | L35: 0.5 | N35: =IF(B35="","",IF(N(L35)>0,I35/L35,0.2)) -> 0.2 | O35: =IF(B35="","",IF(N(L35)>0,J35/L35,0.02)) -> 0.02 | P35: =IF(B35="","",IF(N(L35)>0,IF(K35="",I35,K35)/L35,0.25)) -> 0.25 | Q35: gpt-5-nano (proxy) | R35: 5.6971481e-05 | S35: 1.2 | T35: 1.756778e-09 | U35: 1e-08 | V35: S | X35: =IF(B35="","",R35*S35*P_Mix/1000000+IF(P_Fab="Oui",T35,0)) -> 5.2502692e-09 | Y35: =IF(B35="","",IF(W35<>"",W35,IF(AND(P_Source="Table fournie",U35<>""),U35,X35))) -> 1e-08 | Z35: =IF(B35="","",IF(W35<>"","Forcé",IF(AND(P_Source="Table fournie",U35<>""),IF(V35="H","Table (hypothèse)","Table (sourcé)"),"Calculateur de Boris"))) -> Table (sourcé)
B36: GPT-6 Sol | C36: OpenAI ≥ GPT-5.6 | E36: =IF(B36="","",IF(D36<>"",D36,IF('Contrôles'!$J$68>0,"Exclusive",IF('Contrôles'!$U$68<>"",'Contrôles'!$U$68,IFERROR(INDEX(F_Conv,MATCH(C36,F_Fam,0)),"Inclusive"))))) -> Inclusive | F36: =IF(B36="","",IF(D36<>"","Forcée",IF('Contrôles'!$J$68>0,"C2",IF('Contrôles'!$U$68<>"","C3","Défaut API")))) -> Défaut API | G36: =IF(B36="","",IF(E36="Exclusive",0,1)) -> 1 | H36: =IF(B36="","",IF(E36="Inclusive",1,0)) -> 1 | I36: 2 | J36: 0.2 | K36: 2.5 | L36: 10 | N36: =IF(B36="","",IF(N(L36)>0,I36/L36,0.2)) -> 0.2 | O36: =IF(B36="","",IF(N(L36)>0,J36/L36,0.02)) -> 0.02 | P36: =IF(B36="","",IF(N(L36)>0,IF(K36="",I36,K36)/L36,0.25)) -> 0.25 | Q36: gpt-5.4 (proxy) | R36: 0.0017884687 | S36: 1.2 | T36: 5.090409e-08 | U36: 1e-08 | V36: H | X36: =IF(B36="","",R36*S36*P_Mix/1000000+IF(P_Fab="Oui",T36,0)) -> 1.6057299e-07 | Y36: =IF(B36="","",IF(W36<>"",W36,IF(AND(P_Source="Table fournie",U36<>""),U36,X36))) -> 1e-08 | Z36: =IF(B36="","",IF(W36<>"","Forcé",IF(AND(P_Source="Table fournie",U36<>""),IF(V36="H","Table (hypothèse)","Table (sourcé)"),"Calculateur de Boris"))) -> Table (hypothèse)
B37: GPT-6 Astra | C37: OpenAI ≥ GPT-5.6 | E37: =IF(B37="","",IF(D37<>"",D37,IF('Contrôles'!$J$69>0,"Exclusive",IF('Contrôles'!$U$69<>"",'Contrôles'!$U$69,IFERROR(INDEX(F_Conv,MATCH(C37,F_Fam,0)),"Inclusive"))))) -> Inclusive | F37: =IF(B37="","",IF(D37<>"","Forcée",IF('Contrôles'!$J$69>0,"C2",IF('Contrôles'!$U$69<>"","C3","Défaut API")))) -> Défaut API | G37: =IF(B37="","",IF(E37="Exclusive",0,1)) -> 1 | H37: =IF(B37="","",IF(E37="Inclusive",1,0)) -> 1 | I37: 10 | J37: 1 | K37: 12.5 | L37: 50 | N37: =IF(B37="","",IF(N(L37)>0,I37/L37,0.2)) -> 0.2 | O37: =IF(B37="","",IF(N(L37)>0,J37/L37,0.02)) -> 0.02 | P37: =IF(B37="","",IF(N(L37)>0,IF(K37="",I37,K37)/L37,0.25)) -> 0.25 | Q37: gpt-5.5 (proxy) | R37: 0.0054568626 | S37: 1.2 | T37: 1.146602e-07 | U37: 1e-08 | V37: H | X37: =IF(B37="","",R37*S37*P_Mix/1000000+IF(P_Fab="Oui",T37,0)) -> 4.4927501e-07 | Y37: =IF(B37="","",IF(W37<>"",W37,IF(AND(P_Source="Table fournie",U37<>""),U37,X37))) -> 1e-08 | Z37: =IF(B37="","",IF(W37<>"","Forcé",IF(AND(P_Source="Table fournie",U37<>""),IF(V37="H","Table (hypothèse)","Table (sourcé)"),"Calculateur de Boris"))) -> Table (hypothèse)
B38: GPT-6.1 Sol | C38: OpenAI ≥ GPT-5.6 | E38: =IF(B38="","",IF(D38<>"",D38,IF('Contrôles'!$J$70>0,"Exclusive",IF('Contrôles'!$U$70<>"",'Contrôles'!$U$70,IFERROR(INDEX(F_Conv,MATCH(C38,F_Fam,0)),"Inclusive"))))) -> Inclusive | F38: =IF(B38="","",IF(D38<>"","Forcée",IF('Contrôles'!$J$70>0,"C2",IF('Contrôles'!$U$70<>"","C3","Défaut API")))) -> Défaut API | G38: =IF(B38="","",IF(E38="Exclusive",0,1)) -> 1 | H38: =IF(B38="","",IF(E38="Inclusive",1,0)) -> 1 | I38: 2 | J38: 0.1 | K38: 2.5 | L38: 10 | N38: =IF(B38="","",IF(N(L38)>0,I38/L38,0.2)) -> 0.2 | O38: =IF(B38="","",IF(N(L38)>0,J38/L38,0.02)) -> 0.01 | P38: =IF(B38="","",IF(N(L38)>0,IF(K38="",I38,K38)/L38,0.25)) -> 0.25 | Q38: gpt-5.4 (proxy) | R38: 0.0017884687 | S38: 1.2 | T38: 5.090409e-08 | U38: 1e-08 | V38: H | X38: =IF(B38="","",R38*S38*P_Mix/1000000+IF(P_Fab="Oui",T38,0)) -> 1.6057299e-07 | Y38: =IF(B38="","",IF(W38<>"",W38,IF(AND(P_Source="Table fournie",U38<>""),U38,X38))) -> 1e-08 | Z38: =IF(B38="","",IF(W38<>"","Forcé",IF(AND(P_Source="Table fournie",U38<>""),IF(V38="H","Table (hypothèse)","Table (sourcé)"),"Calculateur de Boris"))) -> Table (hypothèse)
B39: GPT-5 mini | C39: OpenAI < GPT-5.6 | E39: =IF(B39="","",IF(D39<>"",D39,IF('Contrôles'!$J$71>0,"Exclusive",IF('Contrôles'!$U$71<>"",'Contrôles'!$U$71,IFERROR(INDEX(F_Conv,MATCH(C39,F_Fam,0)),"Inclusive"))))) -> Inclusive | F39: =IF(B39="","",IF(D39<>"","Forcée",IF('Contrôles'!$J$71>0,"C2",IF('Contrôles'!$U$71<>"","C3","Défaut API")))) -> Défaut API | G39: =IF(B39="","",IF(E39="Exclusive",0,1)) -> 1 | H39: =IF(B39="","",IF(E39="Inclusive",1,0)) -> 1 | I39: 0.25 | J39: 0.025 | L39: 2 | N39: =IF(B39="","",IF(N(L39)>0,I39/L39,0.2)) -> 0.125 | O39: =IF(B39="","",IF(N(L39)>0,J39/L39,0.02)) -> 0.0125 | P39: =IF(B39="","",IF(N(L39)>0,IF(K39="",I39,K39)/L39,0.25)) -> 0.125 | Q39: gpt-5-mini | R39: 0.00037684316 | S39: 1.2 | T39: 1.229372e-08 | U39: 1.1039e-07 | V39: S | X39: =IF(B39="","",R39*S39*P_Mix/1000000+IF(P_Fab="Oui",T39,0)) -> 3.5401743e-08 | Y39: =IF(B39="","",IF(W39<>"",W39,IF(AND(P_Source="Table fournie",U39<>""),U39,X39))) -> 1.1039e-07 | Z39: =IF(B39="","",IF(W39<>"","Forcé",IF(AND(P_Source="Table fournie",U39<>""),IF(V39="H","Table (hypothèse)","Table (sourcé)"),"Calculateur de Boris"))) -> Table (sourcé)
B40: GPT-5.4 mini | C40: OpenAI < GPT-5.6 | E40: =IF(B40="","",IF(D40<>"",D40,IF('Contrôles'!$J$72>0,"Exclusive",IF('Contrôles'!$U$72<>"",'Contrôles'!$U$72,IFERROR(INDEX(F_Conv,MATCH(C40,F_Fam,0)),"Inclusive"))))) -> Inclusive | F40: =IF(B40="","",IF(D40<>"","Forcée",IF('Contrôles'!$J$72>0,"C2",IF('Contrôles'!$U$72<>"","C3","Défaut API")))) -> Défaut API | G40: =IF(B40="","",IF(E40="Exclusive",0,1)) -> 1 | H40: =IF(B40="","",IF(E40="Inclusive",1,0)) -> 1 | I40: 0.75 | J40: 0.075 | L40: 4.5 | N40: =IF(B40="","",IF(N(L40)>0,I40/L40,0.2)) -> 0.16666667 | O40: =IF(B40="","",IF(N(L40)>0,J40/L40,0.02)) -> 0.016666667 | P40: =IF(B40="","",IF(N(L40)>0,IF(K40="",I40,K40)/L40,0.25)) -> 0.16666667 | Q40: gpt-5-mini (proxy) | R40: 0.00037684316 | S40: 1.2 | T40: 1.229372e-08 | U40: 8.028e-08 | V40: H | X40: =IF(B40="","",R40*S40*P_Mix/1000000+IF(P_Fab="Oui",T40,0)) -> 3.5401743e-08 | Y40: =IF(B40="","",IF(W40<>"",W40,IF(AND(P_Source="Table fournie",U40<>""),U40,X40))) -> 8.028e-08 | Z40: =IF(B40="","",IF(W40<>"","Forcé",IF(AND(P_Source="Table fournie",U40<>""),IF(V40="H","Table (hypothèse)","Table (sourcé)"),"Calculateur de Boris"))) -> Table (hypothèse)
B41: GPT-5.4 | C41: OpenAI < GPT-5.6 | E41: =IF(B41="","",IF(D41<>"",D41,IF('Contrôles'!$J$73>0,"Exclusive",IF('Contrôles'!$U$73<>"",'Contrôles'!$U$73,IFERROR(INDEX(F_Conv,MATCH(C41,F_Fam,0)),"Inclusive"))))) -> Inclusive | F41: =IF(B41="","",IF(D41<>"","Forcée",IF('Contrôles'!$J$73>0,"C2",IF('Contrôles'!$U$73<>"","C3","Défaut API")))) -> Défaut API | G41: =IF(B41="","",IF(E41="Exclusive",0,1)) -> 1 | H41: =IF(B41="","",IF(E41="Inclusive",1,0)) -> 1 | I41: 2.5 | J41: 0.25 | L41: 15 | N41: =IF(B41="","",IF(N(L41)>0,I41/L41,0.2)) -> 0.16666667 | O41: =IF(B41="","",IF(N(L41)>0,J41/L41,0.02)) -> 0.016666667 | P41: =IF(B41="","",IF(N(L41)>0,IF(K41="",I41,K41)/L41,0.25)) -> 0.16666667 | Q41: gpt-5.4 | R41: 0.0017884687 | S41: 1.2 | T41: 5.090409e-08 | U41: 4.7e-07 | V41: S | X41: =IF(B41="","",R41*S41*P_Mix/1000000+IF(P_Fab="Oui",T41,0)) -> 1.6057299e-07 | Y41: =IF(B41="","",IF(W41<>"",W41,IF(AND(P_Source="Table fournie",U41<>""),U41,X41))) -> 4.7e-07 | Z41: =IF(B41="","",IF(W41<>"","Forcé",IF(AND(P_Source="Table fournie",U41<>""),IF(V41="H","Table (hypothèse)","Table (sourcé)"),"Calculateur de Boris"))) -> Table (sourcé)
B42: GPT-5.5 | C42: OpenAI < GPT-5.6 | E42: =IF(B42="","",IF(D42<>"",D42,IF('Contrôles'!$J$74>0,"Exclusive",IF('Contrôles'!$U$74<>"",'Contrôles'!$U$74,IFERROR(INDEX(F_Conv,MATCH(C42,F_Fam,0)),"Inclusive"))))) -> Inclusive | F42: =IF(B42="","",IF(D42<>"","Forcée",IF('Contrôles'!$J$74>0,"C2",IF('Contrôles'!$U$74<>"","C3","Défaut API")))) -> Défaut API | G42: =IF(B42="","",IF(E42="Exclusive",0,1)) -> 1 | H42: =IF(B42="","",IF(E42="Inclusive",1,0)) -> 1 | I42: 5 | J42: 0.5 | L42: 30 | N42: =IF(B42="","",IF(N(L42)>0,I42/L42,0.2)) -> 0.16666667 | O42: =IF(B42="","",IF(N(L42)>0,J42/L42,0.02)) -> 0.016666667 | P42: =IF(B42="","",IF(N(L42)>0,IF(K42="",I42,K42)/L42,0.25)) -> 0.16666667 | Q42: gpt-5.5 | R42: 0.0054568626 | S42: 1.2 | T42: 1.146602e-07 | U42: 1.42e-06 | V42: S | X42: =IF(B42="","",R42*S42*P_Mix/1000000+IF(P_Fab="Oui",T42,0)) -> 4.4927501e-07 | Y42: =IF(B42="","",IF(W42<>"",W42,IF(AND(P_Source="Table fournie",U42<>""),U42,X42))) -> 1.42e-06 | Z42: =IF(B42="","",IF(W42<>"","Forcé",IF(AND(P_Source="Table fournie",U42<>""),IF(V42="H","Table (hypothèse)","Table (sourcé)"),"Calculateur de Boris"))) -> Table (sourcé)
B43: Claude Haiku 4.5 | C43: Anthropic | E43: =IF(B43="","",IF(D43<>"",D43,IF('Contrôles'!$J$75>0,"Exclusive",IF('Contrôles'!$U$75<>"",'Contrôles'!$U$75,IFERROR(INDEX(F_Conv,MATCH(C43,F_Fam,0)),"Inclusive"))))) -> Exclusive | F43: =IF(B43="","",IF(D43<>"","Forcée",IF('Contrôles'!$J$75>0,"C2",IF('Contrôles'!$U$75<>"","C3","Défaut API")))) -> Défaut API | G43: =IF(B43="","",IF(E43="Exclusive",0,1)) -> 0 | H43: =IF(B43="","",IF(E43="Inclusive",1,0)) -> 0 | I43: 1 | J43: 0.1 | K43: 1.25 | L43: 5 | N43: =IF(B43="","",IF(N(L43)>0,I43/L43,0.2)) -> 0.2 | O43: =IF(B43="","",IF(N(L43)>0,J43/L43,0.02)) -> 0.02 | P43: =IF(B43="","",IF(N(L43)>0,IF(K43="",I43,K43)/L43,0.25)) -> 0.25 | Q43: claude-haiku-4-5 | R43: 6.1218155e-05 | S43: 1.2 | T43: 2.067979e-09 | U43: 1.8e-08 | V43: S | X43: =IF(B43="","",R43*S43*P_Mix/1000000+IF(P_Fab="Oui",T43,0)) -> 5.8218763e-09 | Y43: =IF(B43="","",IF(W43<>"",W43,IF(AND(P_Source="Table fournie",U43<>""),U43,X43))) -> 1.8e-08 | Z43: =IF(B43="","",IF(W43<>"","Forcé",IF(AND(P_Source="Table fournie",U43<>""),IF(V43="H","Table (hypothèse)","Table (sourcé)"),"Calculateur de Boris"))) -> Table (sourcé)
B44: Claude Haiku 5.5 | C44: Anthropic | E44: =IF(B44="","",IF(D44<>"",D44,IF('Contrôles'!$J$76>0,"Exclusive",IF('Contrôles'!$U$76<>"",'Contrôles'!$U$76,IFERROR(INDEX(F_Conv,MATCH(C44,F_Fam,0)),"Inclusive"))))) -> Exclusive | F44: =IF(B44="","",IF(D44<>"","Forcée",IF('Contrôles'!$J$76>0,"C2",IF('Contrôles'!$U$76<>"","C3","Défaut API")))) -> Défaut API | G44: =IF(B44="","",IF(E44="Exclusive",0,1)) -> 0 | H44: =IF(B44="","",IF(E44="Inclusive",1,0)) -> 0 | I44: 0.1 | J44: 0.01 | K44: 0.125 | L44: 0.5 | N44: =IF(B44="","",IF(N(L44)>0,I44/L44,0.2)) -> 0.2 | O44: =IF(B44="","",IF(N(L44)>0,J44/L44,0.02)) -> 0.02 | P44: =IF(B44="","",IF(N(L44)>0,IF(K44="",I44,K44)/L44,0.25)) -> 0.25 | Q44: claude-haiku-4-5 (proxy) | R44: 6.1218155e-05 | S44: 1.2 | T44: 2.067979e-09 | U44: 1.8e-08 | V44: H | X44: =IF(B44="","",R44*S44*P_Mix/1000000+IF(P_Fab="Oui",T44,0)) -> 5.8218763e-09 | Y44: =IF(B44="","",IF(W44<>"",W44,IF(AND(P_Source="Table fournie",U44<>""),U44,X44))) -> 1.8e-08 | Z44: =IF(B44="","",IF(W44<>"","Forcé",IF(AND(P_Source="Table fournie",U44<>""),IF(V44="H","Table (hypothèse)","Table (sourcé)"),"Calculateur de Boris"))) -> Table (hypothèse)
B45: Claude Sonnet 4 | C45: Anthropic | E45: =IF(B45="","",IF(D45<>"",D45,IF('Contrôles'!$J$77>0,"Exclusive",IF('Contrôles'!$U$77<>"",'Contrôles'!$U$77,IFERROR(INDEX(F_Conv,MATCH(C45,F_Fam,0)),"Inclusive"))))) -> Exclusive | F45: =IF(B45="","",IF(D45<>"","Forcée",IF('Contrôles'!$J$77>0,"C2",IF('Contrôles'!$U$77<>"","C3","Défaut API")))) -> Défaut API | G45: =IF(B45="","",IF(E45="Exclusive",0,1)) -> 0 | H45: =IF(B45="","",IF(E45="Inclusive",1,0)) -> 0 | I45: 3 | J45: 0.3 | K45: 3.75 | L45: 15 | N45: =IF(B45="","",IF(N(L45)>0,I45/L45,0.2)) -> 0.2 | O45: =IF(B45="","",IF(N(L45)>0,J45/L45,0.02)) -> 0.02 | P45: =IF(B45="","",IF(N(L45)>0,IF(K45="",I45,K45)/L45,0.25)) -> 0.25 | Q45: claude-sonnet-4 | R45: 0.0016896666 | S45: 1.2 | T45: 5.324451e-08 | U45: 4.9308e-07 | V45: S | X45: =IF(B45="","",R45*S45*P_Mix/1000000+IF(P_Fab="Oui",T45,0)) -> 1.5685487e-07 | Y45: =IF(B45="","",IF(W45<>"",W45,IF(AND(P_Source="Table fournie",U45<>""),U45,X45))) -> 4.9308e-07 | Z45: =IF(B45="","",IF(W45<>"","Forcé",IF(AND(P_Source="Table fournie",U45<>""),IF(V45="H","Table (hypothèse)","Table (sourcé)"),"Calculateur de Boris"))) -> Table (sourcé)
B46: Claude Sonnet 4.6 | C46: Anthropic | E46: =IF(B46="","",IF(D46<>"",D46,IF('Contrôles'!$J$78>0,"Exclusive",IF('Contrôles'!$U$78<>"",'Contrôles'!$U$78,IFERROR(INDEX(F_Conv,MATCH(C46,F_Fam,0)),"Inclusive"))))) -> Exclusive | F46: =IF(B46="","",IF(D46<>"","Forcée",IF('Contrôles'!$J$78>0,"C2",IF('Contrôles'!$U$78<>"","C3","Défaut API")))) -> Défaut API | G46: =IF(B46="","",IF(E46="Exclusive",0,1)) -> 0 | H46: =IF(B46="","",IF(E46="Inclusive",1,0)) -> 0 | I46: 3 | J46: 0.3 | K46: 3.75 | L46: 15 | N46: =IF(B46="","",IF(N(L46)>0,I46/L46,0.2)) -> 0.2 | O46: =IF(B46="","",IF(N(L46)>0,J46/L46,0.02)) -> 0.02 | P46: =IF(B46="","",IF(N(L46)>0,IF(K46="",I46,K46)/L46,0.25)) -> 0.25 | Q46: claude-sonnet-4-6 | R46: 0.0017018133 | S46: 1.2 | T46: 5.594532e-08 | U46: 4.4e-07 | V46: S | X46: =IF(B46="","",R46*S46*P_Mix/1000000+IF(P_Fab="Oui",T46,0)) -> 1.6030051e-07 | Y46: =IF(B46="","",IF(W46<>"",W46,IF(AND(P_Source="Table fournie",U46<>""),U46,X46))) -> 4.4e-07 | Z46: =IF(B46="","",IF(W46<>"","Forcé",IF(AND(P_Source="Table fournie",U46<>""),IF(V46="H","Table (hypothèse)","Table (sourcé)"),"Calculateur de Boris"))) -> Table (sourcé)
B47: Claude Sonnet 5 | C47: Anthropic | E47: =IF(B47="","",IF(D47<>"",D47,IF('Contrôles'!$J$79>0,"Exclusive",IF('Contrôles'!$U$79<>"",'Contrôles'!$U$79,IFERROR(INDEX(F_Conv,MATCH(C47,F_Fam,0)),"Inclusive"))))) -> Exclusive | F47: =IF(B47="","",IF(D47<>"","Forcée",IF('Contrôles'!$J$79>0,"C2",IF('Contrôles'!$U$79<>"","C3","Défaut API")))) -> Défaut API | G47: =IF(B47="","",IF(E47="Exclusive",0,1)) -> 0 | H47: =IF(B47="","",IF(E47="Inclusive",1,0)) -> 0 | I47: 2 | J47: 0.2 | K47: 2.5 | L47: 10 | N47: =IF(B47="","",IF(N(L47)>0,I47/L47,0.2)) -> 0.2 | O47: =IF(B47="","",IF(N(L47)>0,J47/L47,0.02)) -> 0.02 | P47: =IF(B47="","",IF(N(L47)>0,IF(K47="",I47,K47)/L47,0.25)) -> 0.25 | Q47: claude-sonnet-4-6 (proxy) | R47: 0.0017018133 | S47: 1.2 | T47: 5.594532e-08 | U47: 4.4e-07 | V47: H | X47: =IF(B47="","",R47*S47*P_Mix/1000000+IF(P_Fab="Oui",T47,0)) -> 1.6030051e-07 | Y47: =IF(B47="","",IF(W47<>"",W47,IF(AND(P_Source="Table fournie",U47<>""),U47,X47))) -> 4.4e-07 | Z47: =IF(B47="","",IF(W47<>"","Forcé",IF(AND(P_Source="Table fournie",U47<>""),IF(V47="H","Table (hypothèse)","Table (sourcé)"),"Calculateur de Boris"))) -> Table (hypothèse)
B48: Claude Sonnet 5.5 | C48: Anthropic | E48: =IF(B48="","",IF(D48<>"",D48,IF('Contrôles'!$J$80>0,"Exclusive",IF('Contrôles'!$U$80<>"",'Contrôles'!$U$80,IFERROR(INDEX(F_Conv,MATCH(C48,F_Fam,0)),"Inclusive"))))) -> Exclusive | F48: =IF(B48="","",IF(D48<>"","Forcée",IF('Contrôles'!$J$80>0,"C2",IF('Contrôles'!$U$80<>"","C3","Défaut API")))) -> Défaut API | G48: =IF(B48="","",IF(E48="Exclusive",0,1)) -> 0 | H48: =IF(B48="","",IF(E48="Inclusive",1,0)) -> 0 | I48: 2 | J48: 0.1 | K48: 2.5 | L48: 10 | N48: =IF(B48="","",IF(N(L48)>0,I48/L48,0.2)) -> 0.2 | O48: =IF(B48="","",IF(N(L48)>0,J48/L48,0.02)) -> 0.01 | P48: =IF(B48="","",IF(N(L48)>0,IF(K48="",I48,K48)/L48,0.25)) -> 0.25 | Q48: claude-sonnet-4-6 (proxy) | R48: 0.0017018133 | S48: 1.2 | T48: 5.594532e-08 | U48: 4.4e-07 | V48: H | X48: =IF(B48="","",R48*S48*P_Mix/1000000+IF(P_Fab="Oui",T48,0)) -> 1.6030051e-07 | Y48: =IF(B48="","",IF(W48<>"",W48,IF(AND(P_Source="Table fournie",U48<>""),U48,X48))) -> 4.4e-07 | Z48: =IF(B48="","",IF(W48<>"","Forcé",IF(AND(P_Source="Table fournie",U48<>""),IF(V48="H","Table (hypothèse)","Table (sourcé)"),"Calculateur de Boris"))) -> Table (hypothèse)
B49: Claude Sonnet 5.5 [ancien tarif] | C49: Anthropic | E49: =IF(B49="","",IF(D49<>"",D49,IF('Contrôles'!$J$81>0,"Exclusive",IF('Contrôles'!$U$81<>"",'Contrôles'!$U$81,IFERROR(INDEX(F_Conv,MATCH(C49,F_Fam,0)),"Inclusive"))))) -> Exclusive | F49: =IF(B49="","",IF(D49<>"","Forcée",IF('Contrôles'!$J$81>0,"C2",IF('Contrôles'!$U$81<>"","C3","Défaut API")))) -> Défaut API | G49: =IF(B49="","",IF(E49="Exclusive",0,1)) -> 0 | H49: =IF(B49="","",IF(E49="Inclusive",1,0)) -> 0 | I49: 2 | J49: 0.2 | K49: 2.5 | L49: 10 | M49: 46296 | N49: =IF(B49="","",IF(N(L49)>0,I49/L49,0.2)) -> 0.2 | O49: =IF(B49="","",IF(N(L49)>0,J49/L49,0.02)) -> 0.02 | P49: =IF(B49="","",IF(N(L49)>0,IF(K49="",I49,K49)/L49,0.25)) -> 0.25 | Q49: claude-sonnet-4-6 (proxy) | R49: 0.0017018133 | S49: 1.2 | T49: 5.594532e-08 | U49: 4.4e-07 | V49: H | X49: =IF(B49="","",R49*S49*P_Mix/1000000+IF(P_Fab="Oui",T49,0)) -> 1.6030051e-07 | Y49: =IF(B49="","",IF(W49<>"",W49,IF(AND(P_Source="Table fournie",U49<>""),U49,X49))) -> 4.4e-07 | Z49: =IF(B49="","",IF(W49<>"","Forcé",IF(AND(P_Source="Table fournie",U49<>""),IF(V49="H","Table (hypothèse)","Table (sourcé)"),"Calculateur de Boris"))) -> Table (hypothèse)
B50: Claude Opus 4.8 | C50: Anthropic | E50: =IF(B50="","",IF(D50<>"",D50,IF('Contrôles'!$J$82>0,"Exclusive",IF('Contrôles'!$U$82<>"",'Contrôles'!$U$82,IFERROR(INDEX(F_Conv,MATCH(C50,F_Fam,0)),"Inclusive"))))) -> Exclusive | F50: =IF(B50="","",IF(D50<>"","Forcée",IF('Contrôles'!$J$82>0,"C2",IF('Contrôles'!$U$82<>"","C3","Défaut API")))) -> Défaut API | G50: =IF(B50="","",IF(E50="Exclusive",0,1)) -> 0 | H50: =IF(B50="","",IF(E50="Inclusive",1,0)) -> 0 | I50: 5 | J50: 0.5 | K50: 6.25 | L50: 25 | N50: =IF(B50="","",IF(N(L50)>0,I50/L50,0.2)) -> 0.2 | O50: =IF(B50="","",IF(N(L50)>0,J50/L50,0.02)) -> 0.02 | P50: =IF(B50="","",IF(N(L50)>0,IF(K50="",I50,K50)/L50,0.25)) -> 0.25 | Q50: claude-opus-4-8 | R50: 0.0040886684 | S50: 1.2 | T50: 7.986676e-08 | U50: 1.06e-06 | V50: S | X50: =IF(B50="","",R50*S50*P_Mix/1000000+IF(P_Fab="Oui",T50,0)) -> 3.3058391e-07 | Y50: =IF(B50="","",IF(W50<>"",W50,IF(AND(P_Source="Table fournie",U50<>""),U50,X50))) -> 1.06e-06 | Z50: =IF(B50="","",IF(W50<>"","Forcé",IF(AND(P_Source="Table fournie",U50<>""),IF(V50="H","Table (hypothèse)","Table (sourcé)"),"Calculateur de Boris"))) -> Table (sourcé)
B51: Claude Opus 4.8 (fast mode) | C51: Anthropic | E51: =IF(B51="","",IF(D51<>"",D51,IF('Contrôles'!$J$83>0,"Exclusive",IF('Contrôles'!$U$83<>"",'Contrôles'!$U$83,IFERROR(INDEX(F_Conv,MATCH(C51,F_Fam,0)),"Inclusive"))))) -> Exclusive | F51: =IF(B51="","",IF(D51<>"","Forcée",IF('Contrôles'!$J$83>0,"C2",IF('Contrôles'!$U$83<>"","C3","Défaut API")))) -> Défaut API | G51: =IF(B51="","",IF(E51="Exclusive",0,1)) -> 0 | H51: =IF(B51="","",IF(E51="Inclusive",1,0)) -> 0 | I51: 10 | J51: 1 | K51: 12.5 | L51: 50 | N51: =IF(B51="","",IF(N(L51)>0,I51/L51,0.2)) -> 0.2 | O51: =IF(B51="","",IF(N(L51)>0,J51/L51,0.02)) -> 0.02 | P51: =IF(B51="","",IF(N(L51)>0,IF(K51="",I51,K51)/L51,0.25)) -> 0.25 | Q51: claude-opus-4-8 (proxy) | R51: 0.0040886684 | S51: 1.2 | T51: 7.986676e-08 | U51: 1.06e-06 | V51: H | X51: =IF(B51="","",R51*S51*P_Mix/1000000+IF(P_Fab="Oui",T51,0)) -> 3.3058391e-07 | Y51: =IF(B51="","",IF(W51<>"",W51,IF(AND(P_Source="Table fournie",U51<>""),U51,X51))) -> 1.06e-06 | Z51: =IF(B51="","",IF(W51<>"","Forcé",IF(AND(P_Source="Table fournie",U51<>""),IF(V51="H","Table (hypothèse)","Table (sourcé)"),"Calculateur de Boris"))) -> Table (hypothèse)
B52: Claude Opus 5 | C52: Anthropic | E52: =IF(B52="","",IF(D52<>"",D52,IF('Contrôles'!$J$84>0,"Exclusive",IF('Contrôles'!$U$84<>"",'Contrôles'!$U$84,IFERROR(INDEX(F_Conv,MATCH(C52,F_Fam,0)),"Inclusive"))))) -> Exclusive | F52: =IF(B52="","",IF(D52<>"","Forcée",IF('Contrôles'!$J$84>0,"C2",IF('Contrôles'!$U$84<>"","C3","Défaut API")))) -> Défaut API | G52: =IF(B52="","",IF(E52="Exclusive",0,1)) -> 0 | H52: =IF(B52="","",IF(E52="Inclusive",1,0)) -> 0 | I52: 5 | J52: 0.5 | K52: 6.25 | L52: 25 | N52: =IF(B52="","",IF(N(L52)>0,I52/L52,0.2)) -> 0.2 | O52: =IF(B52="","",IF(N(L52)>0,J52/L52,0.02)) -> 0.02 | P52: =IF(B52="","",IF(N(L52)>0,IF(K52="",I52,K52)/L52,0.25)) -> 0.25 | Q52: claude-opus-4-8 (proxy) | R52: 0.0040886684 | S52: 1.2 | T52: 7.986676e-08 | U52: 1.06e-06 | V52: H | X52: =IF(B52="","",R52*S52*P_Mix/1000000+IF(P_Fab="Oui",T52,0)) -> 3.3058391e-07 | Y52: =IF(B52="","",IF(W52<>"",W52,IF(AND(P_Source="Table fournie",U52<>""),U52,X52))) -> 1.06e-06 | Z52: =IF(B52="","",IF(W52<>"","Forcé",IF(AND(P_Source="Table fournie",U52<>""),IF(V52="H","Table (hypothèse)","Table (sourcé)"),"Calculateur de Boris"))) -> Table (hypothèse)
B53: Claude Opus 5.5 | C53: Anthropic | E53: =IF(B53="","",IF(D53<>"",D53,IF('Contrôles'!$J$85>0,"Exclusive",IF('Contrôles'!$U$85<>"",'Contrôles'!$U$85,IFERROR(INDEX(F_Conv,MATCH(C53,F_Fam,0)),"Inclusive"))))) -> Exclusive | F53: =IF(B53="","",IF(D53<>"","Forcée",IF('Contrôles'!$J$85>0,"C2",IF('Contrôles'!$U$85<>"","C3","Défaut API")))) -> Défaut API | G53: =IF(B53="","",IF(E53="Exclusive",0,1)) -> 0 | H53: =IF(B53="","",IF(E53="Inclusive",1,0)) -> 0 | I53: 4 | J53: 0.2 | K53: 5 | L53: 20 | N53: =IF(B53="","",IF(N(L53)>0,I53/L53,0.2)) -> 0.2 | O53: =IF(B53="","",IF(N(L53)>0,J53/L53,0.02)) -> 0.01 | P53: =IF(B53="","",IF(N(L53)>0,IF(K53="",I53,K53)/L53,0.25)) -> 0.25 | Q53: claude-opus-4-8 (proxy) | R53: 0.0040886684 | S53: 1.2 | T53: 7.986676e-08 | U53: 1.06e-06 | V53: H | X53: =IF(B53="","",R53*S53*P_Mix/1000000+IF(P_Fab="Oui",T53,0)) -> 3.3058391e-07 | Y53: =IF(B53="","",IF(W53<>"",W53,IF(AND(P_Source="Table fournie",U53<>""),U53,X53))) -> 1.06e-06 | Z53: =IF(B53="","",IF(W53<>"","Forcé",IF(AND(P_Source="Table fournie",U53<>""),IF(V53="H","Table (hypothèse)","Table (sourcé)"),"Calculateur de Boris"))) -> Table (hypothèse)
B54: Claude Fable 5 | C54: Anthropic | E54: =IF(B54="","",IF(D54<>"",D54,IF('Contrôles'!$J$86>0,"Exclusive",IF('Contrôles'!$U$86<>"",'Contrôles'!$U$86,IFERROR(INDEX(F_Conv,MATCH(C54,F_Fam,0)),"Inclusive"))))) -> Exclusive | F54: =IF(B54="","",IF(D54<>"","Forcée",IF('Contrôles'!$J$86>0,"C2",IF('Contrôles'!$U$86<>"","C3","Défaut API")))) -> Défaut API | G54: =IF(B54="","",IF(E54="Exclusive",0,1)) -> 0 | H54: =IF(B54="","",IF(E54="Inclusive",1,0)) -> 0 | I54: 10 | J54: 1 | K54: 12.5 | L54: 50 | N54: =IF(B54="","",IF(N(L54)>0,I54/L54,0.2)) -> 0.2 | O54: =IF(B54="","",IF(N(L54)>0,J54/L54,0.02)) -> 0.02 | P54: =IF(B54="","",IF(N(L54)>0,IF(K54="",I54,K54)/L54,0.25)) -> 0.25 | Q54: claude-opus-4-6 (proxy) | R54: 0.005568696 | S54: 1.2 | T54: 1.395263e-07 | U54: 1.06e-06 | V54: H | X54: =IF(B54="","",R54*S54*P_Mix/1000000+IF(P_Fab="Oui",T54,0)) -> 4.8099874e-07 | Y54: =IF(B54="","",IF(W54<>"",W54,IF(AND(P_Source="Table fournie",U54<>""),U54,X54))) -> 1.06e-06 | Z54: =IF(B54="","",IF(W54<>"","Forcé",IF(AND(P_Source="Table fournie",U54<>""),IF(V54="H","Table (hypothèse)","Table (sourcé)"),"Calculateur de Boris"))) -> Table (hypothèse)
B55: Claude Fable 5.1 | C55: Anthropic | E55: =IF(B55="","",IF(D55<>"",D55,IF('Contrôles'!$J$87>0,"Exclusive",IF('Contrôles'!$U$87<>"",'Contrôles'!$U$87,IFERROR(INDEX(F_Conv,MATCH(C55,F_Fam,0)),"Inclusive"))))) -> Exclusive | F55: =IF(B55="","",IF(D55<>"","Forcée",IF('Contrôles'!$J$87>0,"C2",IF('Contrôles'!$U$87<>"","C3","Défaut API")))) -> Défaut API | G55: =IF(B55="","",IF(E55="Exclusive",0,1)) -> 0 | H55: =IF(B55="","",IF(E55="Inclusive",1,0)) -> 0 | I55: 10 | J55: 0.25 | K55: 12.5 | L55: 50 | N55: =IF(B55="","",IF(N(L55)>0,I55/L55,0.2)) -> 0.2 | O55: =IF(B55="","",IF(N(L55)>0,J55/L55,0.02)) -> 0.005 | P55: =IF(B55="","",IF(N(L55)>0,IF(K55="",I55,K55)/L55,0.25)) -> 0.25 | Q55: claude-opus-4-6 (proxy) | R55: 0.005568696 | S55: 1.2 | T55: 1.395263e-07 | U55: 1.06e-06 | V55: H | X55: =IF(B55="","",R55*S55*P_Mix/1000000+IF(P_Fab="Oui",T55,0)) -> 4.8099874e-07 | Y55: =IF(B55="","",IF(W55<>"",W55,IF(AND(P_Source="Table fournie",U55<>""),U55,X55))) -> 1.06e-06 | Z55: =IF(B55="","",IF(W55<>"","Forcé",IF(AND(P_Source="Table fournie",U55<>""),IF(V55="H","Table (hypothèse)","Table (sourcé)"),"Calculateur de Boris"))) -> Table (hypothèse)
B56: Gemini 3.8 Flash | C56: Google Gemini | E56: =IF(B56="","",IF(D56<>"",D56,IF('Contrôles'!$J$88>0,"Exclusive",IF('Contrôles'!$U$88<>"",'Contrôles'!$U$88,IFERROR(INDEX(F_Conv,MATCH(C56,F_Fam,0)),"Inclusive"))))) -> Inclusive | F56: =IF(B56="","",IF(D56<>"","Forcée",IF('Contrôles'!$J$88>0,"C2",IF('Contrôles'!$U$88<>"","C3","Défaut API")))) -> Défaut API | G56: =IF(B56="","",IF(E56="Exclusive",0,1)) -> 1 | H56: =IF(B56="","",IF(E56="Inclusive",1,0)) -> 1 | I56: 0.75 | J56: 0.075 | L56: 3.75 | N56: =IF(B56="","",IF(N(L56)>0,I56/L56,0.2)) -> 0.2 | O56: =IF(B56="","",IF(N(L56)>0,J56/L56,0.02)) -> 0.02 | P56: =IF(B56="","",IF(N(L56)>0,IF(K56="",I56,K56)/L56,0.25)) -> 0.2 | Q56: gemini-2.5-flash (proxy) | R56: 0.001605908 | S56: 1.2 | T56: 3.462087e-08 | U56: 1.5e-07 | V56: S | X56: =IF(B56="","",R56*S56*P_Mix/1000000+IF(P_Fab="Oui",T56,0)) -> 1.3309515e-07 | Y56: =IF(B56="","",IF(W56<>"",W56,IF(AND(P_Source="Table fournie",U56<>""),U56,X56))) -> 1.5e-07 | Z56: =IF(B56="","",IF(W56<>"","Forcé",IF(AND(P_Source="Table fournie",U56<>""),IF(V56="H","Table (hypothèse)","Table (sourcé)"),"Calculateur de Boris"))) -> Table (sourcé)
B57: Gemini 4 Argon | C57: Google Gemini | E57: =IF(B57="","",IF(D57<>"",D57,IF('Contrôles'!$J$89>0,"Exclusive",IF('Contrôles'!$U$89<>"",'Contrôles'!$U$89,IFERROR(INDEX(F_Conv,MATCH(C57,F_Fam,0)),"Inclusive"))))) -> Inclusive | F57: =IF(B57="","",IF(D57<>"","Forcée",IF('Contrôles'!$J$89>0,"C2",IF('Contrôles'!$U$89<>"","C3","Défaut API")))) -> Défaut API | G57: =IF(B57="","",IF(E57="Exclusive",0,1)) -> 1 | H57: =IF(B57="","",IF(E57="Inclusive",1,0)) -> 1 | I57: 2 | J57: 0.1 | L57: 10 | N57: =IF(B57="","",IF(N(L57)>0,I57/L57,0.2)) -> 0.2 | O57: =IF(B57="","",IF(N(L57)>0,J57/L57,0.02)) -> 0.01 | P57: =IF(B57="","",IF(N(L57)>0,IF(K57="",I57,K57)/L57,0.25)) -> 0.2 | Q57: gemini-2.5-pro (proxy) | R57: 0.017628243 | S57: 1.2 | T57: 1.016964e-07 | U57: 4.69e-06 | V57: H | X57: =IF(B57="","",R57*S57*P_Mix/1000000+IF(P_Fab="Oui",T57,0)) -> 1.1826603e-06 | Y57: =IF(B57="","",IF(W57<>"",W57,IF(AND(P_Source="Table fournie",U57<>""),U57,X57))) -> 4.69e-06 | Z57: =IF(B57="","",IF(W57<>"","Forcé",IF(AND(P_Source="Table fournie",U57<>""),IF(V57="H","Table (hypothèse)","Table (sourcé)"),"Calculateur de Boris"))) -> Table (hypothèse)
B58: Gemini 3.7 Flash | C58: Google Gemini | E58: =IF(B58="","",IF(D58<>"",D58,IF('Contrôles'!$J$90>0,"Exclusive",IF('Contrôles'!$U$90<>"",'Contrôles'!$U$90,IFERROR(INDEX(F_Conv,MATCH(C58,F_Fam,0)),"Inclusive"))))) -> Inclusive | F58: =IF(B58="","",IF(D58<>"","Forcée",IF('Contrôles'!$J$90>0,"C2",IF('Contrôles'!$U$90<>"","C3","Défaut API")))) -> Défaut API | G58: =IF(B58="","",IF(E58="Exclusive",0,1)) -> 1 | H58: =IF(B58="","",IF(E58="Inclusive",1,0)) -> 1 | I58: 0.75 | J58: 0.075 | L58: 3.75 | N58: =IF(B58="","",IF(N(L58)>0,I58/L58,0.2)) -> 0.2 | O58: =IF(B58="","",IF(N(L58)>0,J58/L58,0.02)) -> 0.02 | P58: =IF(B58="","",IF(N(L58)>0,IF(K58="",I58,K58)/L58,0.25)) -> 0.2 | Q58: gemini-2.5-flash (proxy) | R58: 0.001605908 | S58: 1.2 | T58: 3.462087e-08 | U58: 1.5e-07 | V58: S | X58: =IF(B58="","",R58*S58*P_Mix/1000000+IF(P_Fab="Oui",T58,0)) -> 1.3309515e-07 | Y58: =IF(B58="","",IF(W58<>"",W58,IF(AND(P_Source="Table fournie",U58<>""),U58,X58))) -> 1.5e-07 | Z58: =IF(B58="","",IF(W58<>"","Forcé",IF(AND(P_Source="Table fournie",U58<>""),IF(V58="H","Table (hypothèse)","Table (sourcé)"),"Calculateur de Boris"))) -> Table (sourcé)
B59: Gemini 3.5 Flash | C59: Google Gemini | E59: =IF(B59="","",IF(D59<>"",D59,IF('Contrôles'!$J$91>0,"Exclusive",IF('Contrôles'!$U$91<>"",'Contrôles'!$U$91,IFERROR(INDEX(F_Conv,MATCH(C59,F_Fam,0)),"Inclusive"))))) -> Inclusive | F59: =IF(B59="","",IF(D59<>"","Forcée",IF('Contrôles'!$J$91>0,"C2",IF('Contrôles'!$U$91<>"","C3","Défaut API")))) -> Défaut API | G59: =IF(B59="","",IF(E59="Exclusive",0,1)) -> 1 | H59: =IF(B59="","",IF(E59="Inclusive",1,0)) -> 1 | I59: 1.5 | J59: 0.15 | L59: 9 | N59: =IF(B59="","",IF(N(L59)>0,I59/L59,0.2)) -> 0.16666667 | O59: =IF(B59="","",IF(N(L59)>0,J59/L59,0.02)) -> 0.016666667 | P59: =IF(B59="","",IF(N(L59)>0,IF(K59="",I59,K59)/L59,0.25)) -> 0.16666667 | Q59: gemini-2.5-flash (proxy) | R59: 0.001605908 | S59: 1.2 | T59: 3.462087e-08 | U59: 1.5e-07 | V59: S | X59: =IF(B59="","",R59*S59*P_Mix/1000000+IF(P_Fab="Oui",T59,0)) -> 1.3309515e-07 | Y59: =IF(B59="","",IF(W59<>"",W59,IF(AND(P_Source="Table fournie",U59<>""),U59,X59))) -> 1.5e-07 | Z59: =IF(B59="","",IF(W59<>"","Forcé",IF(AND(P_Source="Table fournie",U59<>""),IF(V59="H","Table (hypothèse)","Table (sourcé)"),"Calculateur de Boris"))) -> Table (sourcé)
B60: MAI-Code-1.1-Flash | C60: Microsoft MAI | E60: =IF(B60="","",IF(D60<>"",D60,IF('Contrôles'!$J$92>0,"Exclusive",IF('Contrôles'!$U$92<>"",'Contrôles'!$U$92,IFERROR(INDEX(F_Conv,MATCH(C60,F_Fam,0)),"Inclusive"))))) -> Inclusive | F60: =IF(B60="","",IF(D60<>"","Forcée",IF('Contrôles'!$J$92>0,"C2",IF('Contrôles'!$U$92<>"","C3","Défaut API")))) -> Défaut API | G60: =IF(B60="","",IF(E60="Exclusive",0,1)) -> 1 | H60: =IF(B60="","",IF(E60="Inclusive",1,0)) -> 1 | I60: 0.2 | J60: 0.02 | L60: 1.2 | N60: =IF(B60="","",IF(N(L60)>0,I60/L60,0.2)) -> 0.16666667 | O60: =IF(B60="","",IF(N(L60)>0,J60/L60,0.02)) -> 0.016666667 | P60: =IF(B60="","",IF(N(L60)>0,IF(K60="",I60,K60)/L60,0.25)) -> 0.16666667 | Q60: gpt-5-mini (proxy) | R60: 0.00037684316 | S60: 1.2 | T60: 1.229372e-08 | X60: =IF(B60="","",R60*S60*P_Mix/1000000+IF(P_Fab="Oui",T60,0)) -> 3.5401743e-08 | Y60: =IF(B60="","",IF(W60<>"",W60,IF(AND(P_Source="Table fournie",U60<>""),U60,X60))) -> 3.5401743e-08 | Z60: =IF(B60="","",IF(W60<>"","Forcé",IF(AND(P_Source="Table fournie",U60<>""),IF(V60="H","Table (hypothèse)","Table (sourcé)"),"Calculateur de Boris"))) -> Calculateur de Boris
B61: Grok 4.5 | C61: xAI Grok | E61: =IF(B61="","",IF(D61<>"",D61,IF('Contrôles'!$J$93>0,"Exclusive",IF('Contrôles'!$U$93<>"",'Contrôles'!$U$93,IFERROR(INDEX(F_Conv,MATCH(C61,F_Fam,0)),"Inclusive"))))) -> Inclusive | F61: =IF(B61="","",IF(D61<>"","Forcée",IF('Contrôles'!$J$93>0,"C2",IF('Contrôles'!$U$93<>"","C3","Défaut API")))) -> Défaut API | G61: =IF(B61="","",IF(E61="Exclusive",0,1)) -> 1 | H61: =IF(B61="","",IF(E61="Inclusive",1,0)) -> 1 | I61: 2 | J61: 0.5 | L61: 6 | N61: =IF(B61="","",IF(N(L61)>0,I61/L61,0.2)) -> 0.33333333 | O61: =IF(B61="","",IF(N(L61)>0,J61/L61,0.02)) -> 0.083333333 | P61: =IF(B61="","",IF(N(L61)>0,IF(K61="",I61,K61)/L61,0.25)) -> 0.33333333 | Q61: gpt-5.4 (proxy) | R61: 0.0017884687 | S61: 1.2 | T61: 5.090409e-08 | X61: =IF(B61="","",R61*S61*P_Mix/1000000+IF(P_Fab="Oui",T61,0)) -> 1.6057299e-07 | Y61: =IF(B61="","",IF(W61<>"",W61,IF(AND(P_Source="Table fournie",U61<>""),U61,X61))) -> 1.6057299e-07 | Z61: =IF(B61="","",IF(W61<>"","Forcé",IF(AND(P_Source="Table fournie",U61<>""),IF(V61="H","Table (hypothèse)","Table (sourcé)"),"Calculateur de Boris"))) -> Calculateur de Boris
B62: Grok 4.6 | C62: xAI Grok | E62: =IF(B62="","",IF(D62<>"",D62,IF('Contrôles'!$J$94>0,"Exclusive",IF('Contrôles'!$U$94<>"",'Contrôles'!$U$94,IFERROR(INDEX(F_Conv,MATCH(C62,F_Fam,0)),"Inclusive"))))) -> Inclusive | F62: =IF(B62="","",IF(D62<>"","Forcée",IF('Contrôles'!$J$94>0,"C2",IF('Contrôles'!$U$94<>"","C3","Défaut API")))) -> Défaut API | G62: =IF(B62="","",IF(E62="Exclusive",0,1)) -> 1 | H62: =IF(B62="","",IF(E62="Inclusive",1,0)) -> 1 | I62: 2 | J62: 0.5 | L62: 6 | N62: =IF(B62="","",IF(N(L62)>0,I62/L62,0.2)) -> 0.33333333 | O62: =IF(B62="","",IF(N(L62)>0,J62/L62,0.02)) -> 0.083333333 | P62: =IF(B62="","",IF(N(L62)>0,IF(K62="",I62,K62)/L62,0.25)) -> 0.33333333 | Q62: gpt-5.4 (proxy) | R62: 0.0017884687 | S62: 1.2 | T62: 5.090409e-08 | X62: =IF(B62="","",R62*S62*P_Mix/1000000+IF(P_Fab="Oui",T62,0)) -> 1.6057299e-07 | Y62: =IF(B62="","",IF(W62<>"",W62,IF(AND(P_Source="Table fournie",U62<>""),U62,X62))) -> 1.6057299e-07 | Z62: =IF(B62="","",IF(W62<>"","Forcé",IF(AND(P_Source="Table fournie",U62<>""),IF(V62="H","Table (hypothèse)","Table (sourcé)"),"Calculateur de Boris"))) -> Calculateur de Boris
B63: Grok 4.7 | C63: xAI Grok | E63: =IF(B63="","",IF(D63<>"",D63,IF('Contrôles'!$J$95>0,"Exclusive",IF('Contrôles'!$U$95<>"",'Contrôles'!$U$95,IFERROR(INDEX(F_Conv,MATCH(C63,F_Fam,0)),"Inclusive"))))) -> Inclusive | F63: =IF(B63="","",IF(D63<>"","Forcée",IF('Contrôles'!$J$95>0,"C2",IF('Contrôles'!$U$95<>"","C3","Défaut API")))) -> Défaut API | G63: =IF(B63="","",IF(E63="Exclusive",0,1)) -> 1 | H63: =IF(B63="","",IF(E63="Inclusive",1,0)) -> 1 | I63: 2 | J63: 0.5 | L63: 6 | N63: =IF(B63="","",IF(N(L63)>0,I63/L63,0.2)) -> 0.33333333 | O63: =IF(B63="","",IF(N(L63)>0,J63/L63,0.02)) -> 0.083333333 | P63: =IF(B63="","",IF(N(L63)>0,IF(K63="",I63,K63)/L63,0.25)) -> 0.33333333 | Q63: gpt-5.4 (proxy) | R63: 0.0017884687 | S63: 1.2 | T63: 5.090409e-08 | X63: =IF(B63="","",R63*S63*P_Mix/1000000+IF(P_Fab="Oui",T63,0)) -> 1.6057299e-07 | Y63: =IF(B63="","",IF(W63<>"",W63,IF(AND(P_Source="Table fournie",U63<>""),U63,X63))) -> 1.6057299e-07 | Z63: =IF(B63="","",IF(W63<>"","Forcé",IF(AND(P_Source="Table fournie",U63<>""),IF(V63="H","Table (hypothèse)","Table (sourcé)"),"Calculateur de Boris"))) -> Calculateur de Boris
B64: Kimi K3 | C64: Moonshot Kimi | E64: =IF(B64="","",IF(D64<>"",D64,IF('Contrôles'!$J$96>0,"Exclusive",IF('Contrôles'!$U$96<>"",'Contrôles'!$U$96,IFERROR(INDEX(F_Conv,MATCH(C64,F_Fam,0)),"Inclusive"))))) -> Inclusive | F64: =IF(B64="","",IF(D64<>"","Forcée",IF('Contrôles'!$J$96>0,"C2",IF('Contrôles'!$U$96<>"","C3","Défaut API")))) -> Défaut API | G64: =IF(B64="","",IF(E64="Exclusive",0,1)) -> 1 | H64: =IF(B64="","",IF(E64="Inclusive",1,0)) -> 1 | I64: 3 | J64: 0.3 | L64: 15 | N64: =IF(B64="","",IF(N(L64)>0,I64/L64,0.2)) -> 0.2 | O64: =IF(B64="","",IF(N(L64)>0,J64/L64,0.02)) -> 0.02 | P64: =IF(B64="","",IF(N(L64)>0,IF(K64="",I64,K64)/L64,0.25)) -> 0.2 | Q64: gpt-5.1 (proxy) | R64: 0.0014396287 | S64: 1.2 | T64: 5.436939e-08 | X64: =IF(B64="","",R64*S64*P_Mix/1000000+IF(P_Fab="Oui",T64,0)) -> 1.4264742e-07 | Y64: =IF(B64="","",IF(W64<>"",W64,IF(AND(P_Source="Table fournie",U64<>""),U64,X64))) -> 1.4264742e-07 | Z64: =IF(B64="","",IF(W64<>"","Forcé",IF(AND(P_Source="Table fournie",U64<>""),IF(V64="H","Table (hypothèse)","Table (sourcé)"),"Calculateur de Boris"))) -> Calculateur de Boris
B65: Claude Opus 4.5 | C65: Anthropic | E65: =IF(B65="","",IF(D65<>"",D65,IF('Contrôles'!$J$97>0,"Exclusive",IF('Contrôles'!$U$97<>"",'Contrôles'!$U$97,IFERROR(INDEX(F_Conv,MATCH(C65,F_Fam,0)),"Inclusive"))))) -> Exclusive | F65: =IF(B65="","",IF(D65<>"","Forcée",IF('Contrôles'!$J$97>0,"C2",IF('Contrôles'!$U$97<>"","C3","Défaut API")))) -> Défaut API | G65: =IF(B65="","",IF(E65="Exclusive",0,1)) -> 0 | H65: =IF(B65="","",IF(E65="Inclusive",1,0)) -> 0 | I65: 5 | J65: 0.5 | K65: 6.25 | L65: 25 | N65: =IF(B65="","",IF(N(L65)>0,I65/L65,0.2)) -> 0.2 | O65: =IF(B65="","",IF(N(L65)>0,J65/L65,0.02)) -> 0.02 | P65: =IF(B65="","",IF(N(L65)>0,IF(K65="",I65,K65)/L65,0.25)) -> 0.25 | Q65: claude-opus-4-6 (proxy) | R65: 0.005568696 | S65: 1.2 | T65: 1.395263e-07 | U65: 3.2e-07 | V65: H | X65: =IF(B65="","",R65*S65*P_Mix/1000000+IF(P_Fab="Oui",T65,0)) -> 4.8099874e-07 | Y65: =IF(B65="","",IF(W65<>"",W65,IF(AND(P_Source="Table fournie",U65<>""),U65,X65))) -> 3.2e-07 | Z65: =IF(B65="","",IF(W65<>"","Forcé",IF(AND(P_Source="Table fournie",U65<>""),IF(V65="H","Table (hypothèse)","Table (sourcé)"),"Calculateur de Boris"))) -> Table (hypothèse)
B66: Claude Opus 4.6 | C66: Anthropic | E66: =IF(B66="","",IF(D66<>"",D66,IF('Contrôles'!$J$98>0,"Exclusive",IF('Contrôles'!$U$98<>"",'Contrôles'!$U$98,IFERROR(INDEX(F_Conv,MATCH(C66,F_Fam,0)),"Inclusive"))))) -> Exclusive | F66: =IF(B66="","",IF(D66<>"","Forcée",IF('Contrôles'!$J$98>0,"C2",IF('Contrôles'!$U$98<>"","C3","Défaut API")))) -> Défaut API | G66: =IF(B66="","",IF(E66="Exclusive",0,1)) -> 0 | H66: =IF(B66="","",IF(E66="Inclusive",1,0)) -> 0 | I66: 5 | J66: 0.5 | K66: 6.25 | L66: 25 | N66: =IF(B66="","",IF(N(L66)>0,I66/L66,0.2)) -> 0.2 | O66: =IF(B66="","",IF(N(L66)>0,J66/L66,0.02)) -> 0.02 | P66: =IF(B66="","",IF(N(L66)>0,IF(K66="",I66,K66)/L66,0.25)) -> 0.25 | Q66: claude-opus-4-6 | R66: 0.005568696 | S66: 1.2 | T66: 1.395263e-07 | U66: 3.2e-07 | V66: S | X66: =IF(B66="","",R66*S66*P_Mix/1000000+IF(P_Fab="Oui",T66,0)) -> 4.8099874e-07 | Y66: =IF(B66="","",IF(W66<>"",W66,IF(AND(P_Source="Table fournie",U66<>""),U66,X66))) -> 3.2e-07 | Z66: =IF(B66="","",IF(W66<>"","Forcé",IF(AND(P_Source="Table fournie",U66<>""),IF(V66="H","Table (hypothèse)","Table (sourcé)"),"Calculateur de Boris"))) -> Table (sourcé)
B67: Claude Opus 4.7 | C67: Anthropic | E67: =IF(B67="","",IF(D67<>"",D67,IF('Contrôles'!$J$99>0,"Exclusive",IF('Contrôles'!$U$99<>"",'Contrôles'!$U$99,IFERROR(INDEX(F_Conv,MATCH(C67,F_Fam,0)),"Inclusive"))))) -> Exclusive | F67: =IF(B67="","",IF(D67<>"","Forcée",IF('Contrôles'!$J$99>0,"C2",IF('Contrôles'!$U$99<>"","C3","Défaut API")))) -> Défaut API | G67: =IF(B67="","",IF(E67="Exclusive",0,1)) -> 0 | H67: =IF(B67="","",IF(E67="Inclusive",1,0)) -> 0 | I67: 5 | J67: 0.5 | K67: 6.25 | L67: 25 | N67: =IF(B67="","",IF(N(L67)>0,I67/L67,0.2)) -> 0.2 | O67: =IF(B67="","",IF(N(L67)>0,J67/L67,0.02)) -> 0.02 | P67: =IF(B67="","",IF(N(L67)>0,IF(K67="",I67,K67)/L67,0.25)) -> 0.25 | Q67: claude-opus-4-7 | R67: 0.0041689948 | S67: 1.2 | T67: 9.772726e-08 | U67: 1.09e-06 | V67: S | X67: =IF(B67="","",R67*S67*P_Mix/1000000+IF(P_Fab="Oui",T67,0)) -> 3.5337002e-07 | Y67: =IF(B67="","",IF(W67<>"",W67,IF(AND(P_Source="Table fournie",U67<>""),U67,X67))) -> 1.09e-06 | Z67: =IF(B67="","",IF(W67<>"","Forcé",IF(AND(P_Source="Table fournie",U67<>""),IF(V67="H","Table (hypothèse)","Table (sourcé)"),"Calculateur de Boris"))) -> Table (sourcé)
B68: Claude Sonnet 4.5 | C68: Anthropic | E68: =IF(B68="","",IF(D68<>"",D68,IF('Contrôles'!$J$100>0,"Exclusive",IF('Contrôles'!$U$100<>"",'Contrôles'!$U$100,IFERROR(INDEX(F_Conv,MATCH(C68,F_Fam,0)),"Inclusive"))))) -> Exclusive | F68: =IF(B68="","",IF(D68<>"","Forcée",IF('Contrôles'!$J$100>0,"C2",IF('Contrôles'!$U$100<>"","C3","Défaut API")))) -> Défaut API | G68: =IF(B68="","",IF(E68="Exclusive",0,1)) -> 0 | H68: =IF(B68="","",IF(E68="Inclusive",1,0)) -> 0 | I68: 3 | J68: 0.3 | K68: 3.75 | L68: 15 | N68: =IF(B68="","",IF(N(L68)>0,I68/L68,0.2)) -> 0.2 | O68: =IF(B68="","",IF(N(L68)>0,J68/L68,0.02)) -> 0.02 | P68: =IF(B68="","",IF(N(L68)>0,IF(K68="",I68,K68)/L68,0.25)) -> 0.25 | Q68: claude-sonnet-4-5 | R68: 0.0017395549 | S68: 1.2 | T68: 6.433711e-08 | U68: 5.1716e-07 | V68: S | X68: =IF(B68="","",R68*S68*P_Mix/1000000+IF(P_Fab="Oui",T68,0)) -> 1.7100662e-07 | Y68: =IF(B68="","",IF(W68<>"",W68,IF(AND(P_Source="Table fournie",U68<>""),U68,X68))) -> 5.1716e-07 | Z68: =IF(B68="","",IF(W68<>"","Forcé",IF(AND(P_Source="Table fournie",U68<>""),IF(V68="H","Table (hypothèse)","Table (sourcé)"),"Calculateur de Boris"))) -> Table (sourcé)
B69: Gemini 2.5 Flash | C69: Hors grille | E69: =IF(B69="","",IF(D69<>"",D69,IF('Contrôles'!$J$101>0,"Exclusive",IF('Contrôles'!$U$101<>"",'Contrôles'!$U$101,IFERROR(INDEX(F_Conv,MATCH(C69,F_Fam,0)),"Inclusive"))))) -> Inclusive | F69: =IF(B69="","",IF(D69<>"","Forcée",IF('Contrôles'!$J$101>0,"C2",IF('Contrôles'!$U$101<>"","C3","Défaut API")))) -> Défaut API | G69: =IF(B69="","",IF(E69="Exclusive",0,1)) -> 1 | H69: =IF(B69="","",IF(E69="Inclusive",1,0)) -> 1 | N69: =IF(B69="","",IF(N(L69)>0,I69/L69,0.2)) -> 0.2 | O69: =IF(B69="","",IF(N(L69)>0,J69/L69,0.02)) -> 0.02 | P69: =IF(B69="","",IF(N(L69)>0,IF(K69="",I69,K69)/L69,0.25)) -> 0.25 | Q69: gpt-5.4 (proxy) | R69: 0.0017884687 | S69: 1.2 | T69: 5.090409e-08 | U69: 4.5265e-07 | V69: S | X69: =IF(B69="","",R69*S69*P_Mix/1000000+IF(P_Fab="Oui",T69,0)) -> 1.6057299e-07 | Y69: =IF(B69="","",IF(W69<>"",W69,IF(AND(P_Source="Table fournie",U69<>""),U69,X69))) -> 4.5265e-07 | Z69: =IF(B69="","",IF(W69<>"","Forcé",IF(AND(P_Source="Table fournie",U69<>""),IF(V69="H","Table (hypothèse)","Table (sourcé)"),"Calculateur de Boris"))) -> Table (sourcé)
B70: Gemini 2.5-pro | C70: Hors grille | E70: =IF(B70="","",IF(D70<>"",D70,IF('Contrôles'!$J$102>0,"Exclusive",IF('Contrôles'!$U$102<>"",'Contrôles'!$U$102,IFERROR(INDEX(F_Conv,MATCH(C70,F_Fam,0)),"Inclusive"))))) -> Inclusive | F70: =IF(B70="","",IF(D70<>"","Forcée",IF('Contrôles'!$J$102>0,"C2",IF('Contrôles'!$U$102<>"","C3","Défaut API")))) -> Défaut API | G70: =IF(B70="","",IF(E70="Exclusive",0,1)) -> 1 | H70: =IF(B70="","",IF(E70="Inclusive",1,0)) -> 1 | N70: =IF(B70="","",IF(N(L70)>0,I70/L70,0.2)) -> 0.2 | O70: =IF(B70="","",IF(N(L70)>0,J70/L70,0.02)) -> 0.02 | P70: =IF(B70="","",IF(N(L70)>0,IF(K70="",I70,K70)/L70,0.25)) -> 0.25 | Q70: gpt-5.4 (proxy) | R70: 0.0017884687 | S70: 1.2 | T70: 5.090409e-08 | U70: 4.69e-06 | V70: S | X70: =IF(B70="","",R70*S70*P_Mix/1000000+IF(P_Fab="Oui",T70,0)) -> 1.6057299e-07 | Y70: =IF(B70="","",IF(W70<>"",W70,IF(AND(P_Source="Table fournie",U70<>""),U70,X70))) -> 4.69e-06 | Z70: =IF(B70="","",IF(W70<>"","Forcé",IF(AND(P_Source="Table fournie",U70<>""),IF(V70="H","Table (hypothèse)","Table (sourcé)"),"Calculateur de Boris"))) -> Table (sourcé)
B71: gemini-2.5-flash-lite | C71: Hors grille | E71: =IF(B71="","",IF(D71<>"",D71,IF('Contrôles'!$J$103>0,"Exclusive",IF('Contrôles'!$U$103<>"",'Contrôles'!$U$103,IFERROR(INDEX(F_Conv,MATCH(C71,F_Fam,0)),"Inclusive"))))) -> Inclusive | F71: =IF(B71="","",IF(D71<>"","Forcée",IF('Contrôles'!$J$103>0,"C2",IF('Contrôles'!$U$103<>"","C3","Défaut API")))) -> Défaut API | G71: =IF(B71="","",IF(E71="Exclusive",0,1)) -> 1 | H71: =IF(B71="","",IF(E71="Inclusive",1,0)) -> 1 | N71: =IF(B71="","",IF(N(L71)>0,I71/L71,0.2)) -> 0.2 | O71: =IF(B71="","",IF(N(L71)>0,J71/L71,0.02)) -> 0.02 | P71: =IF(B71="","",IF(N(L71)>0,IF(K71="",I71,K71)/L71,0.25)) -> 0.25 | Q71: gpt-5.4 (proxy) | R71: 0.0017884687 | S71: 1.2 | T71: 5.090409e-08 | U71: 1.761e-08 | V71: S | X71: =IF(B71="","",R71*S71*P_Mix/1000000+IF(P_Fab="Oui",T71,0)) -> 1.6057299e-07 | Y71: =IF(B71="","",IF(W71<>"",W71,IF(AND(P_Source="Table fournie",U71<>""),U71,X71))) -> 1.761e-08 | Z71: =IF(B71="","",IF(W71<>"","Forcé",IF(AND(P_Source="Table fournie",U71<>""),IF(V71="H","Table (hypothèse)","Table (sourcé)"),"Calculateur de Boris"))) -> Table (sourcé)
B72: gemini-2.5-flash-tts | C72: Hors grille | E72: =IF(B72="","",IF(D72<>"",D72,IF('Contrôles'!$J$104>0,"Exclusive",IF('Contrôles'!$U$104<>"",'Contrôles'!$U$104,IFERROR(INDEX(F_Conv,MATCH(C72,F_Fam,0)),"Inclusive"))))) -> Inclusive | F72: =IF(B72="","",IF(D72<>"","Forcée",IF('Contrôles'!$J$104>0,"C2",IF('Contrôles'!$U$104<>"","C3","Défaut API")))) -> Défaut API | G72: =IF(B72="","",IF(E72="Exclusive",0,1)) -> 1 | H72: =IF(B72="","",IF(E72="Inclusive",1,0)) -> 1 | N72: =IF(B72="","",IF(N(L72)>0,I72/L72,0.2)) -> 0.2 | O72: =IF(B72="","",IF(N(L72)>0,J72/L72,0.02)) -> 0.02 | P72: =IF(B72="","",IF(N(L72)>0,IF(K72="",I72,K72)/L72,0.25)) -> 0.25 | Q72: gpt-5.4 (proxy) | R72: 0.0017884687 | S72: 1.2 | T72: 5.090409e-08 | U72: 1.761e-08 | V72: H | X72: =IF(B72="","",R72*S72*P_Mix/1000000+IF(P_Fab="Oui",T72,0)) -> 1.6057299e-07 | Y72: =IF(B72="","",IF(W72<>"",W72,IF(AND(P_Source="Table fournie",U72<>""),U72,X72))) -> 1.761e-08 | Z72: =IF(B72="","",IF(W72<>"","Forcé",IF(AND(P_Source="Table fournie",U72<>""),IF(V72="H","Table (hypothèse)","Table (sourcé)"),"Calculateur de Boris"))) -> Table (hypothèse)
B73: gemini-2.5-pro-tts | C73: Hors grille | E73: =IF(B73="","",IF(D73<>"",D73,IF('Contrôles'!$J$105>0,"Exclusive",IF('Contrôles'!$U$105<>"",'Contrôles'!$U$105,IFERROR(INDEX(F_Conv,MATCH(C73,F_Fam,0)),"Inclusive"))))) -> Inclusive | F73: =IF(B73="","",IF(D73<>"","Forcée",IF('Contrôles'!$J$105>0,"C2",IF('Contrôles'!$U$105<>"","C3","Défaut API")))) -> Défaut API | G73: =IF(B73="","",IF(E73="Exclusive",0,1)) -> 1 | H73: =IF(B73="","",IF(E73="Inclusive",1,0)) -> 1 | N73: =IF(B73="","",IF(N(L73)>0,I73/L73,0.2)) -> 0.2 | O73: =IF(B73="","",IF(N(L73)>0,J73/L73,0.02)) -> 0.02 | P73: =IF(B73="","",IF(N(L73)>0,IF(K73="",I73,K73)/L73,0.25)) -> 0.25 | Q73: gpt-5.4 (proxy) | R73: 0.0017884687 | S73: 1.2 | T73: 5.090409e-08 | U73: 4.69e-06 | V73: H | X73: =IF(B73="","",R73*S73*P_Mix/1000000+IF(P_Fab="Oui",T73,0)) -> 1.6057299e-07 | Y73: =IF(B73="","",IF(W73<>"",W73,IF(AND(P_Source="Table fournie",U73<>""),U73,X73))) -> 4.69e-06 | Z73: =IF(B73="","",IF(W73<>"","Forcé",IF(AND(P_Source="Table fournie",U73<>""),IF(V73="H","Table (hypothèse)","Table (sourcé)"),"Calculateur de Boris"))) -> Table (hypothèse)
B74: GPT 4.1 | C74: Hors grille | E74: =IF(B74="","",IF(D74<>"",D74,IF('Contrôles'!$J$106>0,"Exclusive",IF('Contrôles'!$U$106<>"",'Contrôles'!$U$106,IFERROR(INDEX(F_Conv,MATCH(C74,F_Fam,0)),"Inclusive"))))) -> Inclusive | F74: =IF(B74="","",IF(D74<>"","Forcée",IF('Contrôles'!$J$106>0,"C2",IF('Contrôles'!$U$106<>"","C3","Défaut API")))) -> Défaut API | G74: =IF(B74="","",IF(E74="Exclusive",0,1)) -> 1 | H74: =IF(B74="","",IF(E74="Inclusive",1,0)) -> 1 | N74: =IF(B74="","",IF(N(L74)>0,I74/L74,0.2)) -> 0.2 | O74: =IF(B74="","",IF(N(L74)>0,J74/L74,0.02)) -> 0.02 | P74: =IF(B74="","",IF(N(L74)>0,IF(K74="",I74,K74)/L74,0.25)) -> 0.25 | Q74: gpt-5.4 (proxy) | R74: 0.0017884687 | S74: 1.2 | T74: 5.090409e-08 | U74: 5.121e-07 | V74: S | X74: =IF(B74="","",R74*S74*P_Mix/1000000+IF(P_Fab="Oui",T74,0)) -> 1.6057299e-07 | Y74: =IF(B74="","",IF(W74<>"",W74,IF(AND(P_Source="Table fournie",U74<>""),U74,X74))) -> 5.121e-07 | Z74: =IF(B74="","",IF(W74<>"","Forcé",IF(AND(P_Source="Table fournie",U74<>""),IF(V74="H","Table (hypothèse)","Table (sourcé)"),"Calculateur de Boris"))) -> Table (sourcé)
B75: GPT-4.1 mini | C75: Hors grille | E75: =IF(B75="","",IF(D75<>"",D75,IF('Contrôles'!$J$107>0,"Exclusive",IF('Contrôles'!$U$107<>"",'Contrôles'!$U$107,IFERROR(INDEX(F_Conv,MATCH(C75,F_Fam,0)),"Inclusive"))))) -> Inclusive | F75: =IF(B75="","",IF(D75<>"","Forcée",IF('Contrôles'!$J$107>0,"C2",IF('Contrôles'!$U$107<>"","C3","Défaut API")))) -> Défaut API | G75: =IF(B75="","",IF(E75="Exclusive",0,1)) -> 1 | H75: =IF(B75="","",IF(E75="Inclusive",1,0)) -> 1 | N75: =IF(B75="","",IF(N(L75)>0,I75/L75,0.2)) -> 0.2 | O75: =IF(B75="","",IF(N(L75)>0,J75/L75,0.02)) -> 0.02 | P75: =IF(B75="","",IF(N(L75)>0,IF(K75="",I75,K75)/L75,0.25)) -> 0.25 | Q75: gpt-5.4 (proxy) | R75: 0.0017884687 | S75: 1.2 | T75: 5.090409e-08 | U75: 1.1853e-07 | V75: S | X75: =IF(B75="","",R75*S75*P_Mix/1000000+IF(P_Fab="Oui",T75,0)) -> 1.6057299e-07 | Y75: =IF(B75="","",IF(W75<>"",W75,IF(AND(P_Source="Table fournie",U75<>""),U75,X75))) -> 1.1853e-07 | Z75: =IF(B75="","",IF(W75<>"","Forcé",IF(AND(P_Source="Table fournie",U75<>""),IF(V75="H","Table (hypothèse)","Table (sourcé)"),"Calculateur de Boris"))) -> Table (sourcé)
B76: GPT-4.1 nano | C76: Hors grille | E76: =IF(B76="","",IF(D76<>"",D76,IF('Contrôles'!$J$108>0,"Exclusive",IF('Contrôles'!$U$108<>"",'Contrôles'!$U$108,IFERROR(INDEX(F_Conv,MATCH(C76,F_Fam,0)),"Inclusive"))))) -> Inclusive | F76: =IF(B76="","",IF(D76<>"","Forcée",IF('Contrôles'!$J$108>0,"C2",IF('Contrôles'!$U$108<>"","C3","Défaut API")))) -> Défaut API | G76: =IF(B76="","",IF(E76="Exclusive",0,1)) -> 1 | H76: =IF(B76="","",IF(E76="Inclusive",1,0)) -> 1 | N76: =IF(B76="","",IF(N(L76)>0,I76/L76,0.2)) -> 0.2 | O76: =IF(B76="","",IF(N(L76)>0,J76/L76,0.02)) -> 0.02 | P76: =IF(B76="","",IF(N(L76)>0,IF(K76="",I76,K76)/L76,0.25)) -> 0.25 | Q76: gpt-5.4 (proxy) | R76: 0.0017884687 | S76: 1.2 | T76: 5.090409e-08 | U76: 1.738e-08 | V76: S | X76: =IF(B76="","",R76*S76*P_Mix/1000000+IF(P_Fab="Oui",T76,0)) -> 1.6057299e-07 | Y76: =IF(B76="","",IF(W76<>"",W76,IF(AND(P_Source="Table fournie",U76<>""),U76,X76))) -> 1.738e-08 | Z76: =IF(B76="","",IF(W76<>"","Forcé",IF(AND(P_Source="Table fournie",U76<>""),IF(V76="H","Table (hypothèse)","Table (sourcé)"),"Calculateur de Boris"))) -> Table (sourcé)
B77: gpt-4o-2024-11-20 | C77: Hors grille | E77: =IF(B77="","",IF(D77<>"",D77,IF('Contrôles'!$J$109>0,"Exclusive",IF('Contrôles'!$U$109<>"",'Contrôles'!$U$109,IFERROR(INDEX(F_Conv,MATCH(C77,F_Fam,0)),"Inclusive"))))) -> Inclusive | F77: =IF(B77="","",IF(D77<>"","Forcée",IF('Contrôles'!$J$109>0,"C2",IF('Contrôles'!$U$109<>"","C3","Défaut API")))) -> Défaut API | G77: =IF(B77="","",IF(E77="Exclusive",0,1)) -> 1 | H77: =IF(B77="","",IF(E77="Inclusive",1,0)) -> 1 | N77: =IF(B77="","",IF(N(L77)>0,I77/L77,0.2)) -> 0.2 | O77: =IF(B77="","",IF(N(L77)>0,J77/L77,0.02)) -> 0.02 | P77: =IF(B77="","",IF(N(L77)>0,IF(K77="",I77,K77)/L77,0.25)) -> 0.25 | Q77: gpt-5.4 (proxy) | R77: 0.0017884687 | S77: 1.2 | T77: 5.090409e-08 | U77: 2.28e-06 | V77: S | X77: =IF(B77="","",R77*S77*P_Mix/1000000+IF(P_Fab="Oui",T77,0)) -> 1.6057299e-07 | Y77: =IF(B77="","",IF(W77<>"",W77,IF(AND(P_Source="Table fournie",U77<>""),U77,X77))) -> 2.28e-06 | Z77: =IF(B77="","",IF(W77<>"","Forcé",IF(AND(P_Source="Table fournie",U77<>""),IF(V77="H","Table (hypothèse)","Table (sourcé)"),"Calculateur de Boris"))) -> Table (sourcé)
B78: gpt-4o-mini-2024-07-18 | C78: Hors grille | E78: =IF(B78="","",IF(D78<>"",D78,IF('Contrôles'!$J$110>0,"Exclusive",IF('Contrôles'!$U$110<>"",'Contrôles'!$U$110,IFERROR(INDEX(F_Conv,MATCH(C78,F_Fam,0)),"Inclusive"))))) -> Inclusive | F78: =IF(B78="","",IF(D78<>"","Forcée",IF('Contrôles'!$J$110>0,"C2",IF('Contrôles'!$U$110<>"","C3","Défaut API")))) -> Défaut API | G78: =IF(B78="","",IF(E78="Exclusive",0,1)) -> 1 | H78: =IF(B78="","",IF(E78="Inclusive",1,0)) -> 1 | N78: =IF(B78="","",IF(N(L78)>0,I78/L78,0.2)) -> 0.2 | O78: =IF(B78="","",IF(N(L78)>0,J78/L78,0.02)) -> 0.02 | P78: =IF(B78="","",IF(N(L78)>0,IF(K78="",I78,K78)/L78,0.25)) -> 0.25 | Q78: gpt-5.4 (proxy) | R78: 0.0017884687 | S78: 1.2 | T78: 5.090409e-08 | U78: 1e-08 | V78: S | X78: =IF(B78="","",R78*S78*P_Mix/1000000+IF(P_Fab="Oui",T78,0)) -> 1.6057299e-07 | Y78: =IF(B78="","",IF(W78<>"",W78,IF(AND(P_Source="Table fournie",U78<>""),U78,X78))) -> 1e-08 | Z78: =IF(B78="","",IF(W78<>"","Forcé",IF(AND(P_Source="Table fournie",U78<>""),IF(V78="H","Table (hypothèse)","Table (sourcé)"),"Calculateur de Boris"))) -> Table (sourcé)
B79: gpt-4o-transcribe-2025-03-20 | C79: Hors grille | E79: =IF(B79="","",IF(D79<>"",D79,IF('Contrôles'!$J$111>0,"Exclusive",IF('Contrôles'!$U$111<>"",'Contrôles'!$U$111,IFERROR(INDEX(F_Conv,MATCH(C79,F_Fam,0)),"Inclusive"))))) -> Inclusive | F79: =IF(B79="","",IF(D79<>"","Forcée",IF('Contrôles'!$J$111>0,"C2",IF('Contrôles'!$U$111<>"","C3","Défaut API")))) -> Défaut API | G79: =IF(B79="","",IF(E79="Exclusive",0,1)) -> 1 | H79: =IF(B79="","",IF(E79="Inclusive",1,0)) -> 1 | N79: =IF(B79="","",IF(N(L79)>0,I79/L79,0.2)) -> 0.2 | O79: =IF(B79="","",IF(N(L79)>0,J79/L79,0.02)) -> 0.02 | P79: =IF(B79="","",IF(N(L79)>0,IF(K79="",I79,K79)/L79,0.25)) -> 0.25 | Q79: gpt-5.4 (proxy) | R79: 0.0017884687 | S79: 1.2 | T79: 5.090409e-08 | U79: 2e-08 | V79: S | X79: =IF(B79="","",R79*S79*P_Mix/1000000+IF(P_Fab="Oui",T79,0)) -> 1.6057299e-07 | Y79: =IF(B79="","",IF(W79<>"",W79,IF(AND(P_Source="Table fournie",U79<>""),U79,X79))) -> 2e-08 | Z79: =IF(B79="","",IF(W79<>"","Forcé",IF(AND(P_Source="Table fournie",U79<>""),IF(V79="H","Table (hypothèse)","Table (sourcé)"),"Calculateur de Boris"))) -> Table (sourcé)
B80: GPT-5 | C80: Hors grille | E80: =IF(B80="","",IF(D80<>"",D80,IF('Contrôles'!$J$112>0,"Exclusive",IF('Contrôles'!$U$112<>"",'Contrôles'!$U$112,IFERROR(INDEX(F_Conv,MATCH(C80,F_Fam,0)),"Inclusive"))))) -> Inclusive | F80: =IF(B80="","",IF(D80<>"","Forcée",IF('Contrôles'!$J$112>0,"C2",IF('Contrôles'!$U$112<>"","C3","Défaut API")))) -> Défaut API | G80: =IF(B80="","",IF(E80="Exclusive",0,1)) -> 1 | H80: =IF(B80="","",IF(E80="Inclusive",1,0)) -> 1 | N80: =IF(B80="","",IF(N(L80)>0,I80/L80,0.2)) -> 0.2 | O80: =IF(B80="","",IF(N(L80)>0,J80/L80,0.02)) -> 0.02 | P80: =IF(B80="","",IF(N(L80)>0,IF(K80="",I80,K80)/L80,0.25)) -> 0.25 | Q80: gpt-5.4 (proxy) | R80: 0.0017884687 | S80: 1.2 | T80: 5.090409e-08 | U80: 6.4628e-07 | V80: S | X80: =IF(B80="","",R80*S80*P_Mix/1000000+IF(P_Fab="Oui",T80,0)) -> 1.6057299e-07 | Y80: =IF(B80="","",IF(W80<>"",W80,IF(AND(P_Source="Table fournie",U80<>""),U80,X80))) -> 6.4628e-07 | Z80: =IF(B80="","",IF(W80<>"","Forcé",IF(AND(P_Source="Table fournie",U80<>""),IF(V80="H","Table (hypothèse)","Table (sourcé)"),"Calculateur de Boris"))) -> Table (sourcé)
B81: GPT-5 nano | C81: Hors grille | E81: =IF(B81="","",IF(D81<>"",D81,IF('Contrôles'!$J$113>0,"Exclusive",IF('Contrôles'!$U$113<>"",'Contrôles'!$U$113,IFERROR(INDEX(F_Conv,MATCH(C81,F_Fam,0)),"Inclusive"))))) -> Inclusive | F81: =IF(B81="","",IF(D81<>"","Forcée",IF('Contrôles'!$J$113>0,"C2",IF('Contrôles'!$U$113<>"","C3","Défaut API")))) -> Défaut API | G81: =IF(B81="","",IF(E81="Exclusive",0,1)) -> 1 | H81: =IF(B81="","",IF(E81="Inclusive",1,0)) -> 1 | N81: =IF(B81="","",IF(N(L81)>0,I81/L81,0.2)) -> 0.2 | O81: =IF(B81="","",IF(N(L81)>0,J81/L81,0.02)) -> 0.02 | P81: =IF(B81="","",IF(N(L81)>0,IF(K81="",I81,K81)/L81,0.25)) -> 0.25 | Q81: gpt-5.4 (proxy) | R81: 0.0017884687 | S81: 1.2 | T81: 5.090409e-08 | U81: 1.659e-08 | V81: S | X81: =IF(B81="","",R81*S81*P_Mix/1000000+IF(P_Fab="Oui",T81,0)) -> 1.6057299e-07 | Y81: =IF(B81="","",IF(W81<>"",W81,IF(AND(P_Source="Table fournie",U81<>""),U81,X81))) -> 1.659e-08 | Z81: =IF(B81="","",IF(W81<>"","Forcé",IF(AND(P_Source="Table fournie",U81<>""),IF(V81="H","Table (hypothèse)","Table (sourcé)"),"Calculateur de Boris"))) -> Table (sourcé)
B82: mistral-document-ai-2512 | C82: Hors grille | E82: =IF(B82="","",IF(D82<>"",D82,IF('Contrôles'!$J$114>0,"Exclusive",IF('Contrôles'!$U$114<>"",'Contrôles'!$U$114,IFERROR(INDEX(F_Conv,MATCH(C82,F_Fam,0)),"Inclusive"))))) -> Inclusive | F82: =IF(B82="","",IF(D82<>"","Forcée",IF('Contrôles'!$J$114>0,"C2",IF('Contrôles'!$U$114<>"","C3","Défaut API")))) -> Défaut API | G82: =IF(B82="","",IF(E82="Exclusive",0,1)) -> 1 | H82: =IF(B82="","",IF(E82="Inclusive",1,0)) -> 1 | N82: =IF(B82="","",IF(N(L82)>0,I82/L82,0.2)) -> 0.2 | O82: =IF(B82="","",IF(N(L82)>0,J82/L82,0.02)) -> 0.02 | P82: =IF(B82="","",IF(N(L82)>0,IF(K82="",I82,K82)/L82,0.25)) -> 0.25 | Q82: gpt-5.4 (proxy) | R82: 0.0017884687 | S82: 1.2 | T82: 5.090409e-08 | U82: 4e-06 | V82: S | X82: =IF(B82="","",R82*S82*P_Mix/1000000+IF(P_Fab="Oui",T82,0)) -> 1.6057299e-07 | Y82: =IF(B82="","",IF(W82<>"",W82,IF(AND(P_Source="Table fournie",U82<>""),U82,X82))) -> 4e-06 | Z82: =IF(B82="","",IF(W82<>"","Forcé",IF(AND(P_Source="Table fournie",U82<>""),IF(V82="H","Table (hypothèse)","Table (sourcé)"),"Calculateur de Boris"))) -> Table (sourcé)
B83: mistral-large-2512 | C83: Hors grille | E83: =IF(B83="","",IF(D83<>"",D83,IF('Contrôles'!$J$115>0,"Exclusive",IF('Contrôles'!$U$115<>"",'Contrôles'!$U$115,IFERROR(INDEX(F_Conv,MATCH(C83,F_Fam,0)),"Inclusive"))))) -> Inclusive | F83: =IF(B83="","",IF(D83<>"","Forcée",IF('Contrôles'!$J$115>0,"C2",IF('Contrôles'!$U$115<>"","C3","Défaut API")))) -> Défaut API | G83: =IF(B83="","",IF(E83="Exclusive",0,1)) -> 1 | H83: =IF(B83="","",IF(E83="Inclusive",1,0)) -> 1 | N83: =IF(B83="","",IF(N(L83)>0,I83/L83,0.2)) -> 0.2 | O83: =IF(B83="","",IF(N(L83)>0,J83/L83,0.02)) -> 0.02 | P83: =IF(B83="","",IF(N(L83)>0,IF(K83="",I83,K83)/L83,0.25)) -> 0.25 | Q83: gpt-5.4 (proxy) | R83: 0.0017884687 | S83: 1.2 | T83: 5.090409e-08 | U83: 1.3e-07 | V83: S | X83: =IF(B83="","",R83*S83*P_Mix/1000000+IF(P_Fab="Oui",T83,0)) -> 1.6057299e-07 | Y83: =IF(B83="","",IF(W83<>"",W83,IF(AND(P_Source="Table fournie",U83<>""),U83,X83))) -> 1.3e-07 | Z83: =IF(B83="","",IF(W83<>"","Forcé",IF(AND(P_Source="Table fournie",U83<>""),IF(V83="H","Table (hypothèse)","Table (sourcé)"),"Calculateur de Boris"))) -> Table (sourcé)
B84: mistral-medium-2505 | C84: Hors grille | E84: =IF(B84="","",IF(D84<>"",D84,IF('Contrôles'!$J$116>0,"Exclusive",IF('Contrôles'!$U$116<>"",'Contrôles'!$U$116,IFERROR(INDEX(F_Conv,MATCH(C84,F_Fam,0)),"Inclusive"))))) -> Inclusive | F84: =IF(B84="","",IF(D84<>"","Forcée",IF('Contrôles'!$J$116>0,"C2",IF('Contrôles'!$U$116<>"","C3","Défaut API")))) -> Défaut API | G84: =IF(B84="","",IF(E84="Exclusive",0,1)) -> 1 | H84: =IF(B84="","",IF(E84="Inclusive",1,0)) -> 1 | N84: =IF(B84="","",IF(N(L84)>0,I84/L84,0.2)) -> 0.2 | O84: =IF(B84="","",IF(N(L84)>0,J84/L84,0.02)) -> 0.02 | P84: =IF(B84="","",IF(N(L84)>0,IF(K84="",I84,K84)/L84,0.25)) -> 0.25 | Q84: gpt-5.4 (proxy) | R84: 0.0017884687 | S84: 1.2 | T84: 5.090409e-08 | U84: 1.5e-07 | V84: S | X84: =IF(B84="","",R84*S84*P_Mix/1000000+IF(P_Fab="Oui",T84,0)) -> 1.6057299e-07 | Y84: =IF(B84="","",IF(W84<>"",W84,IF(AND(P_Source="Table fournie",U84<>""),U84,X84))) -> 1.5e-07 | Z84: =IF(B84="","",IF(W84<>"","Forcé",IF(AND(P_Source="Table fournie",U84<>""),IF(V84="H","Table (hypothèse)","Table (sourcé)"),"Calculateur de Boris"))) -> Table (sourcé)
B85: mistral-small-2503 | C85: Hors grille | E85: =IF(B85="","",IF(D85<>"",D85,IF('Contrôles'!$J$117>0,"Exclusive",IF('Contrôles'!$U$117<>"",'Contrôles'!$U$117,IFERROR(INDEX(F_Conv,MATCH(C85,F_Fam,0)),"Inclusive"))))) -> Inclusive | F85: =IF(B85="","",IF(D85<>"","Forcée",IF('Contrôles'!$J$117>0,"C2",IF('Contrôles'!$U$117<>"","C3","Défaut API")))) -> Défaut API | G85: =IF(B85="","",IF(E85="Exclusive",0,1)) -> 1 | H85: =IF(B85="","",IF(E85="Inclusive",1,0)) -> 1 | N85: =IF(B85="","",IF(N(L85)>0,I85/L85,0.2)) -> 0.2 | O85: =IF(B85="","",IF(N(L85)>0,J85/L85,0.02)) -> 0.02 | P85: =IF(B85="","",IF(N(L85)>0,IF(K85="",I85,K85)/L85,0.25)) -> 0.25 | Q85: gpt-5.4 (proxy) | R85: 0.0017884687 | S85: 1.2 | T85: 5.090409e-08 | U85: 1e-08 | V85: S | X85: =IF(B85="","",R85*S85*P_Mix/1000000+IF(P_Fab="Oui",T85,0)) -> 1.6057299e-07 | Y85: =IF(B85="","",IF(W85<>"",W85,IF(AND(P_Source="Table fournie",U85<>""),U85,X85))) -> 1e-08 | Z85: =IF(B85="","",IF(W85<>"","Forcé",IF(AND(P_Source="Table fournie",U85<>""),IF(V85="H","Table (hypothèse)","Table (sourcé)"),"Calculateur de Boris"))) -> Table (sourcé)
B86: o3-mini (2025-01-31) | C86: Hors grille | E86: =IF(B86="","",IF(D86<>"",D86,IF('Contrôles'!$J$118>0,"Exclusive",IF('Contrôles'!$U$118<>"",'Contrôles'!$U$118,IFERROR(INDEX(F_Conv,MATCH(C86,F_Fam,0)),"Inclusive"))))) -> Inclusive | F86: =IF(B86="","",IF(D86<>"","Forcée",IF('Contrôles'!$J$118>0,"C2",IF('Contrôles'!$U$118<>"","C3","Défaut API")))) -> Défaut API | G86: =IF(B86="","",IF(E86="Exclusive",0,1)) -> 1 | H86: =IF(B86="","",IF(E86="Inclusive",1,0)) -> 1 | N86: =IF(B86="","",IF(N(L86)>0,I86/L86,0.2)) -> 0.2 | O86: =IF(B86="","",IF(N(L86)>0,J86/L86,0.02)) -> 0.02 | P86: =IF(B86="","",IF(N(L86)>0,IF(K86="",I86,K86)/L86,0.25)) -> 0.25 | Q86: gpt-5.4 (proxy) | R86: 0.0017884687 | S86: 1.2 | T86: 5.090409e-08 | U86: 3.2e-07 | V86: S | X86: =IF(B86="","",R86*S86*P_Mix/1000000+IF(P_Fab="Oui",T86,0)) -> 1.6057299e-07 | Y86: =IF(B86="","",IF(W86<>"",W86,IF(AND(P_Source="Table fournie",U86<>""),U86,X86))) -> 3.2e-07 | Z86: =IF(B86="","",IF(W86<>"","Forcé",IF(AND(P_Source="Table fournie",U86<>""),IF(V86="H","Table (hypothèse)","Table (sourcé)"),"Calculateur de Boris"))) -> Table (sourcé)
B87: o3-2025-04-16 | C87: Hors grille | E87: =IF(B87="","",IF(D87<>"",D87,IF('Contrôles'!$J$119>0,"Exclusive",IF('Contrôles'!$U$119<>"",'Contrôles'!$U$119,IFERROR(INDEX(F_Conv,MATCH(C87,F_Fam,0)),"Inclusive"))))) -> Inclusive | F87: =IF(B87="","",IF(D87<>"","Forcée",IF('Contrôles'!$J$119>0,"C2",IF('Contrôles'!$U$119<>"","C3","Défaut API")))) -> Défaut API | G87: =IF(B87="","",IF(E87="Exclusive",0,1)) -> 1 | H87: =IF(B87="","",IF(E87="Inclusive",1,0)) -> 1 | N87: =IF(B87="","",IF(N(L87)>0,I87/L87,0.2)) -> 0.2 | O87: =IF(B87="","",IF(N(L87)>0,J87/L87,0.02)) -> 0.02 | P87: =IF(B87="","",IF(N(L87)>0,IF(K87="",I87,K87)/L87,0.25)) -> 0.25 | Q87: gpt-5.4 (proxy) | R87: 0.0017884687 | S87: 1.2 | T87: 5.090409e-08 | U87: 5e-07 | V87: S | X87: =IF(B87="","",R87*S87*P_Mix/1000000+IF(P_Fab="Oui",T87,0)) -> 1.6057299e-07 | Y87: =IF(B87="","",IF(W87<>"",W87,IF(AND(P_Source="Table fournie",U87<>""),U87,X87))) -> 5e-07 | Z87: =IF(B87="","",IF(W87<>"","Forcé",IF(AND(P_Source="Table fournie",U87<>""),IF(V87="H","Table (hypothèse)","Table (sourcé)"),"Calculateur de Boris"))) -> Table (sourcé)
B88: o4-mini-2025-04-16 | C88: Hors grille | E88: =IF(B88="","",IF(D88<>"",D88,IF('Contrôles'!$J$120>0,"Exclusive",IF('Contrôles'!$U$120<>"",'Contrôles'!$U$120,IFERROR(INDEX(F_Conv,MATCH(C88,F_Fam,0)),"Inclusive"))))) -> Inclusive | F88: =IF(B88="","",IF(D88<>"","Forcée",IF('Contrôles'!$J$120>0,"C2",IF('Contrôles'!$U$120<>"","C3","Défaut API")))) -> Défaut API | G88: =IF(B88="","",IF(E88="Exclusive",0,1)) -> 1 | H88: =IF(B88="","",IF(E88="Inclusive",1,0)) -> 1 | N88: =IF(B88="","",IF(N(L88)>0,I88/L88,0.2)) -> 0.2 | O88: =IF(B88="","",IF(N(L88)>0,J88/L88,0.02)) -> 0.02 | P88: =IF(B88="","",IF(N(L88)>0,IF(K88="",I88,K88)/L88,0.25)) -> 0.25 | Q88: gpt-5.4 (proxy) | R88: 0.0017884687 | S88: 1.2 | T88: 5.090409e-08 | U88: 3.2e-07 | V88: S | X88: =IF(B88="","",R88*S88*P_Mix/1000000+IF(P_Fab="Oui",T88,0)) -> 1.6057299e-07 | Y88: =IF(B88="","",IF(W88<>"",W88,IF(AND(P_Source="Table fournie",U88<>""),U88,X88))) -> 3.2e-07 | Z88: =IF(B88="","",IF(W88<>"","Forcé",IF(AND(P_Source="Table fournie",U88<>""),IF(V88="H","Table (hypothèse)","Table (sourcé)"),"Calculateur de Boris"))) -> Table (sourcé)
B89: text-embedding-3-large-1 | C89: Hors grille | E89: =IF(B89="","",IF(D89<>"",D89,IF('Contrôles'!$J$121>0,"Exclusive",IF('Contrôles'!$U$121<>"",'Contrôles'!$U$121,IFERROR(INDEX(F_Conv,MATCH(C89,F_Fam,0)),"Inclusive"))))) -> Inclusive | F89: =IF(B89="","",IF(D89<>"","Forcée",IF('Contrôles'!$J$121>0,"C2",IF('Contrôles'!$U$121<>"","C3","Défaut API")))) -> Défaut API | G89: =IF(B89="","",IF(E89="Exclusive",0,1)) -> 1 | H89: =IF(B89="","",IF(E89="Inclusive",1,0)) -> 1 | N89: =IF(B89="","",IF(N(L89)>0,I89/L89,0.2)) -> 0.2 | O89: =IF(B89="","",IF(N(L89)>0,J89/L89,0.02)) -> 0.02 | P89: =IF(B89="","",IF(N(L89)>0,IF(K89="",I89,K89)/L89,0.25)) -> 0.25 | Q89: gpt-5.4 (proxy) | R89: 0.0017884687 | S89: 1.2 | T89: 5.090409e-08 | U89: 1e-08 | V89: S | X89: =IF(B89="","",R89*S89*P_Mix/1000000+IF(P_Fab="Oui",T89,0)) -> 1.6057299e-07 | Y89: =IF(B89="","",IF(W89<>"",W89,IF(AND(P_Source="Table fournie",U89<>""),U89,X89))) -> 1e-08 | Z89: =IF(B89="","",IF(W89<>"","Forcé",IF(AND(P_Source="Table fournie",U89<>""),IF(V89="H","Table (hypothèse)","Table (sourcé)"),"Calculateur de Boris"))) -> Table (sourcé)
B90: text-embedding-ada-002 | C90: Hors grille | E90: =IF(B90="","",IF(D90<>"",D90,IF('Contrôles'!$J$122>0,"Exclusive",IF('Contrôles'!$U$122<>"",'Contrôles'!$U$122,IFERROR(INDEX(F_Conv,MATCH(C90,F_Fam,0)),"Inclusive"))))) -> Inclusive | F90: =IF(B90="","",IF(D90<>"","Forcée",IF('Contrôles'!$J$122>0,"C2",IF('Contrôles'!$U$122<>"","C3","Défaut API")))) -> Défaut API | G90: =IF(B90="","",IF(E90="Exclusive",0,1)) -> 1 | H90: =IF(B90="","",IF(E90="Inclusive",1,0)) -> 1 | N90: =IF(B90="","",IF(N(L90)>0,I90/L90,0.2)) -> 0.2 | O90: =IF(B90="","",IF(N(L90)>0,J90/L90,0.02)) -> 0.02 | P90: =IF(B90="","",IF(N(L90)>0,IF(K90="",I90,K90)/L90,0.25)) -> 0.25 | Q90: gpt-5.4 (proxy) | R90: 0.0017884687 | S90: 1.2 | T90: 5.090409e-08 | U90: 1e-08 | V90: S | X90: =IF(B90="","",R90*S90*P_Mix/1000000+IF(P_Fab="Oui",T90,0)) -> 1.6057299e-07 | Y90: =IF(B90="","",IF(W90<>"",W90,IF(AND(P_Source="Table fournie",U90<>""),U90,X90))) -> 1e-08 | Z90: =IF(B90="","",IF(W90<>"","Forcé",IF(AND(P_Source="Table fournie",U90<>""),IF(V90="H","Table (hypothèse)","Table (sourcé)"),"Calculateur de Boris"))) -> Table (sourcé)
B91: qwen3-235b-a22b-instruct-2507 | C91: Hors grille | E91: =IF(B91="","",IF(D91<>"",D91,IF('Contrôles'!$J$123>0,"Exclusive",IF('Contrôles'!$U$123<>"",'Contrôles'!$U$123,IFERROR(INDEX(F_Conv,MATCH(C91,F_Fam,0)),"Inclusive"))))) -> Inclusive | F91: =IF(B91="","",IF(D91<>"","Forcée",IF('Contrôles'!$J$123>0,"C2",IF('Contrôles'!$U$123<>"","C3","Défaut API")))) -> Défaut API | G91: =IF(B91="","",IF(E91="Exclusive",0,1)) -> 1 | H91: =IF(B91="","",IF(E91="Inclusive",1,0)) -> 1 | N91: =IF(B91="","",IF(N(L91)>0,I91/L91,0.2)) -> 0.2 | O91: =IF(B91="","",IF(N(L91)>0,J91/L91,0.02)) -> 0.02 | P91: =IF(B91="","",IF(N(L91)>0,IF(K91="",I91,K91)/L91,0.25)) -> 0.25 | Q91: gpt-5.4 (proxy) | R91: 0.0017884687 | S91: 1.2 | T91: 5.090409e-08 | U91: 0 | V91: S | X91: =IF(B91="","",R91*S91*P_Mix/1000000+IF(P_Fab="Oui",T91,0)) -> 1.6057299e-07 | Y91: =IF(B91="","",IF(W91<>"",W91,IF(AND(P_Source="Table fournie",U91<>""),U91,X91))) -> 0 | Z91: =IF(B91="","",IF(W91<>"","Forcé",IF(AND(P_Source="Table fournie",U91<>""),IF(V91="H","Table (hypothèse)","Table (sourcé)"),"Calculateur de Boris"))) -> Table (sourcé)
B92: Code Review model | C92: Hors grille | E92: =IF(B92="","",IF(D92<>"",D92,IF('Contrôles'!$J$124>0,"Exclusive",IF('Contrôles'!$U$124<>"",'Contrôles'!$U$124,IFERROR(INDEX(F_Conv,MATCH(C92,F_Fam,0)),"Inclusive"))))) -> Inclusive | F92: =IF(B92="","",IF(D92<>"","Forcée",IF('Contrôles'!$J$124>0,"C2",IF('Contrôles'!$U$124<>"","C3","Défaut API")))) -> Défaut API | G92: =IF(B92="","",IF(E92="Exclusive",0,1)) -> 1 | H92: =IF(B92="","",IF(E92="Inclusive",1,0)) -> 1 | N92: =IF(B92="","",IF(N(L92)>0,I92/L92,0.2)) -> 0.2 | O92: =IF(B92="","",IF(N(L92)>0,J92/L92,0.02)) -> 0.02 | P92: =IF(B92="","",IF(N(L92)>0,IF(K92="",I92,K92)/L92,0.25)) -> 0.25 | Q92: gpt-5.4 (proxy) | R92: 0.0017884687 | S92: 1.2 | T92: 5.090409e-08 | U92: 1e-08 | V92: H | X92: =IF(B92="","",R92*S92*P_Mix/1000000+IF(P_Fab="Oui",T92,0)) -> 1.6057299e-07 | Y92: =IF(B92="","",IF(W92<>"",W92,IF(AND(P_Source="Table fournie",U92<>""),U92,X92))) -> 1e-08 | Z92: =IF(B92="","",IF(W92<>"","Forcé",IF(AND(P_Source="Table fournie",U92<>""),IF(V92="H","Table (hypothèse)","Table (sourcé)"),"Calculateur de Boris"))) -> Table (hypothèse)
B93: (Autre modèle) | C93: Hors grille | E93: =IF(B93="","",IF(D93<>"",D93,IF('Contrôles'!$J$125>0,"Exclusive",IF('Contrôles'!$U$125<>"",'Contrôles'!$U$125,IFERROR(INDEX(F_Conv,MATCH(C93,F_Fam,0)),"Inclusive"))))) -> Inclusive | F93: =IF(B93="","",IF(D93<>"","Forcée",IF('Contrôles'!$J$125>0,"C2",IF('Contrôles'!$U$125<>"","C3","Défaut API")))) -> Défaut API | G93: =IF(B93="","",IF(E93="Exclusive",0,1)) -> 1 | H93: =IF(B93="","",IF(E93="Inclusive",1,0)) -> 1 | N93: =IF(B93="","",IF(N(L93)>0,I93/L93,0.2)) -> 0.2 | O93: =IF(B93="","",IF(N(L93)>0,J93/L93,0.02)) -> 0.02 | P93: =IF(B93="","",IF(N(L93)>0,IF(K93="",I93,K93)/L93,0.25)) -> 0.25 | Q93: gpt-5.4 (proxy) | R93: 0.0017884687 | S93: 1.2 | T93: 5.090409e-08 | X93: =IF(B93="","",R93*S93*P_Mix/1000000+IF(P_Fab="Oui",T93,0)) -> 1.6057299e-07 | Y93: =IF(B93="","",IF(W93<>"",W93,IF(AND(P_Source="Table fournie",U93<>""),U93,X93))) -> 1.6057299e-07 | Z93: =IF(B93="","",IF(W93<>"","Forcé",IF(AND(P_Source="Table fournie",U93<>""),IF(V93="H","Table (hypothèse)","Table (sourcé)"),"Calculateur de Boris"))) -> Calculateur de Boris
E94: =IF(B94="","",IF(D94<>"",D94,IF('Contrôles'!$J$126>0,"Exclusive",IF('Contrôles'!$U$126<>"",'Contrôles'!$U$126,IFERROR(INDEX(F_Conv,MATCH(C94,F_Fam,0)),"Inclusive"))))) | F94: =IF(B94="","",IF(D94<>"","Forcée",IF('Contrôles'!$J$126>0,"C2",IF('Contrôles'!$U$126<>"","C3","Défaut API")))) | G94: =IF(B94="","",IF(E94="Exclusive",0,1)) | H94: =IF(B94="","",IF(E94="Inclusive",1,0)) | N94: =IF(B94="","",IF(N(L94)>0,I94/L94,0.2)) | O94: =IF(B94="","",IF(N(L94)>0,J94/L94,0.02)) | P94: =IF(B94="","",IF(N(L94)>0,IF(K94="",I94,K94)/L94,0.25)) | X94: =IF(B94="","",R94*S94*P_Mix/1000000+IF(P_Fab="Oui",T94,0)) | Y94: =IF(B94="","",IF(W94<>"",W94,IF(AND(P_Source="Table fournie",U94<>""),U94,X94))) | Z94: =IF(B94="","",IF(W94<>"","Forcé",IF(AND(P_Source="Table fournie",U94<>""),IF(V94="H","Table (hypothèse)","Table (sourcé)"),"Calculateur de Boris")))
E95: =IF(B95="","",IF(D95<>"",D95,IF('Contrôles'!$J$127>0,"Exclusive",IF('Contrôles'!$U$127<>"",'Contrôles'!$U$127,IFERROR(INDEX(F_Conv,MATCH(C95,F_Fam,0)),"Inclusive"))))) | F95: =IF(B95="","",IF(D95<>"","Forcée",IF('Contrôles'!$J$127>0,"C2",IF('Contrôles'!$U$127<>"","C3","Défaut API")))) | G95: =IF(B95="","",IF(E95="Exclusive",0,1)) | H95: =IF(B95="","",IF(E95="Inclusive",1,0)) | N95: =IF(B95="","",IF(N(L95)>0,I95/L95,0.2)) | O95: =IF(B95="","",IF(N(L95)>0,J95/L95,0.02)) | P95: =IF(B95="","",IF(N(L95)>0,IF(K95="",I95,K95)/L95,0.25)) | X95: =IF(B95="","",R95*S95*P_Mix/1000000+IF(P_Fab="Oui",T95,0)) | Y95: =IF(B95="","",IF(W95<>"",W95,IF(AND(P_Source="Table fournie",U95<>""),U95,X95))) | Z95: =IF(B95="","",IF(W95<>"","Forcé",IF(AND(P_Source="Table fournie",U95<>""),IF(V95="H","Table (hypothèse)","Table (sourcé)"),"Calculateur de Boris")))
E96: =IF(B96="","",IF(D96<>"",D96,IF('Contrôles'!$J$128>0,"Exclusive",IF('Contrôles'!$U$128<>"",'Contrôles'!$U$128,IFERROR(INDEX(F_Conv,MATCH(C96,F_Fam,0)),"Inclusive"))))) | F96: =IF(B96="","",IF(D96<>"","Forcée",IF('Contrôles'!$J$128>0,"C2",IF('Contrôles'!$U$128<>"","C3","Défaut API")))) | G96: =IF(B96="","",IF(E96="Exclusive",0,1)) | H96: =IF(B96="","",IF(E96="Inclusive",1,0)) | N96: =IF(B96="","",IF(N(L96)>0,I96/L96,0.2)) | O96: =IF(B96="","",IF(N(L96)>0,J96/L96,0.02)) | P96: =IF(B96="","",IF(N(L96)>0,IF(K96="",I96,K96)/L96,0.25)) | X96: =IF(B96="","",R96*S96*P_Mix/1000000+IF(P_Fab="Oui",T96,0)) | Y96: =IF(B96="","",IF(W96<>"",W96,IF(AND(P_Source="Table fournie",U96<>""),U96,X96))) | Z96: =IF(B96="","",IF(W96<>"","Forcé",IF(AND(P_Source="Table fournie",U96<>""),IF(V96="H","Table (hypothèse)","Table (sourcé)"),"Calculateur de Boris")))
E97: =IF(B97="","",IF(D97<>"",D97,IF('Contrôles'!$J$129>0,"Exclusive",IF('Contrôles'!$U$129<>"",'Contrôles'!$U$129,IFERROR(INDEX(F_Conv,MATCH(C97,F_Fam,0)),"Inclusive"))))) | F97: =IF(B97="","",IF(D97<>"","Forcée",IF('Contrôles'!$J$129>0,"C2",IF('Contrôles'!$U$129<>"","C3","Défaut API")))) | G97: =IF(B97="","",IF(E97="Exclusive",0,1)) | H97: =IF(B97="","",IF(E97="Inclusive",1,0)) | N97: =IF(B97="","",IF(N(L97)>0,I97/L97,0.2)) | O97: =IF(B97="","",IF(N(L97)>0,J97/L97,0.02)) | P97: =IF(B97="","",IF(N(L97)>0,IF(K97="",I97,K97)/L97,0.25)) | X97: =IF(B97="","",R97*S97*P_Mix/1000000+IF(P_Fab="Oui",T97,0)) | Y97: =IF(B97="","",IF(W97<>"",W97,IF(AND(P_Source="Table fournie",U97<>""),U97,X97))) | Z97: =IF(B97="","",IF(W97<>"","Forcé",IF(AND(P_Source="Table fournie",U97<>""),IF(V97="H","Table (hypothèse)","Table (sourcé)"),"Calculateur de Boris")))
E98: =IF(B98="","",IF(D98<>"",D98,IF('Contrôles'!$J$130>0,"Exclusive",IF('Contrôles'!$U$130<>"",'Contrôles'!$U$130,IFERROR(INDEX(F_Conv,MATCH(C98,F_Fam,0)),"Inclusive"))))) | F98: =IF(B98="","",IF(D98<>"","Forcée",IF('Contrôles'!$J$130>0,"C2",IF('Contrôles'!$U$130<>"","C3","Défaut API")))) | G98: =IF(B98="","",IF(E98="Exclusive",0,1)) | H98: =IF(B98="","",IF(E98="Inclusive",1,0)) | N98: =IF(B98="","",IF(N(L98)>0,I98/L98,0.2)) | O98: =IF(B98="","",IF(N(L98)>0,J98/L98,0.02)) | P98: =IF(B98="","",IF(N(L98)>0,IF(K98="",I98,K98)/L98,0.25)) | X98: =IF(B98="","",R98*S98*P_Mix/1000000+IF(P_Fab="Oui",T98,0)) | Y98: =IF(B98="","",IF(W98<>"",W98,IF(AND(P_Source="Table fournie",U98<>""),U98,X98))) | Z98: =IF(B98="","",IF(W98<>"","Forcé",IF(AND(P_Source="Table fournie",U98<>""),IF(V98="H","Table (hypothèse)","Table (sourcé)"),"Calculateur de Boris")))
E99: =IF(B99="","",IF(D99<>"",D99,IF('Contrôles'!$J$131>0,"Exclusive",IF('Contrôles'!$U$131<>"",'Contrôles'!$U$131,IFERROR(INDEX(F_Conv,MATCH(C99,F_Fam,0)),"Inclusive"))))) | F99: =IF(B99="","",IF(D99<>"","Forcée",IF('Contrôles'!$J$131>0,"C2",IF('Contrôles'!$U$131<>"","C3","Défaut API")))) | G99: =IF(B99="","",IF(E99="Exclusive",0,1)) | H99: =IF(B99="","",IF(E99="Inclusive",1,0)) | N99: =IF(B99="","",IF(N(L99)>0,I99/L99,0.2)) | O99: =IF(B99="","",IF(N(L99)>0,J99/L99,0.02)) | P99: =IF(B99="","",IF(N(L99)>0,IF(K99="",I99,K99)/L99,0.25)) | X99: =IF(B99="","",R99*S99*P_Mix/1000000+IF(P_Fab="Oui",T99,0)) | Y99: =IF(B99="","",IF(W99<>"",W99,IF(AND(P_Source="Table fournie",U99<>""),U99,X99))) | Z99: =IF(B99="","",IF(W99<>"","Forcé",IF(AND(P_Source="Table fournie",U99<>""),IF(V99="H","Table (hypothèse)","Table (sourcé)"),"Calculateur de Boris")))
E100: =IF(B100="","",IF(D100<>"",D100,IF('Contrôles'!$J$132>0,"Exclusive",IF('Contrôles'!$U$132<>"",'Contrôles'!$U$132,IFERROR(INDEX(F_Conv,MATCH(C100,F_Fam,0)),"Inclusive"))))) | F100: =IF(B100="","",IF(D100<>"","Forcée",IF('Contrôles'!$J$132>0,"C2",IF('Contrôles'!$U$132<>"","C3","Défaut API")))) | G100: =IF(B100="","",IF(E100="Exclusive",0,1)) | H100: =IF(B100="","",IF(E100="Inclusive",1,0)) | N100: =IF(B100="","",IF(N(L100)>0,I100/L100,0.2)) | O100: =IF(B100="","",IF(N(L100)>0,J100/L100,0.02)) | P100: =IF(B100="","",IF(N(L100)>0,IF(K100="",I100,K100)/L100,0.25)) | X100: =IF(B100="","",R100*S100*P_Mix/1000000+IF(P_Fab="Oui",T100,0)) | Y100: =IF(B100="","",IF(W100<>"",W100,IF(AND(P_Source="Table fournie",U100<>""),U100,X100))) | Z100: =IF(B100="","",IF(W100<>"","Forcé",IF(AND(P_Source="Table fournie",U100<>""),IF(V100="H","Table (hypothèse)","Table (sourcé)"),"Calculateur de Boris")))
E101: =IF(B101="","",IF(D101<>"",D101,IF('Contrôles'!$J$133>0,"Exclusive",IF('Contrôles'!$U$133<>"",'Contrôles'!$U$133,IFERROR(INDEX(F_Conv,MATCH(C101,F_Fam,0)),"Inclusive"))))) | F101: =IF(B101="","",IF(D101<>"","Forcée",IF('Contrôles'!$J$133>0,"C2",IF('Contrôles'!$U$133<>"","C3","Défaut API")))) | G101: =IF(B101="","",IF(E101="Exclusive",0,1)) | H101: =IF(B101="","",IF(E101="Inclusive",1,0)) | N101: =IF(B101="","",IF(N(L101)>0,I101/L101,0.2)) | O101: =IF(B101="","",IF(N(L101)>0,J101/L101,0.02)) | P101: =IF(B101="","",IF(N(L101)>0,IF(K101="",I101,K101)/L101,0.25)) | X101: =IF(B101="","",R101*S101*P_Mix/1000000+IF(P_Fab="Oui",T101,0)) | Y101: =IF(B101="","",IF(W101<>"",W101,IF(AND(P_Source="Table fournie",U101<>""),U101,X101))) | Z101: =IF(B101="","",IF(W101<>"","Forcé",IF(AND(P_Source="Table fournie",U101<>""),IF(V101="H","Table (hypothèse)","Table (sourcé)"),"Calculateur de Boris")))
E102: =IF(B102="","",IF(D102<>"",D102,IF('Contrôles'!$J$134>0,"Exclusive",IF('Contrôles'!$U$134<>"",'Contrôles'!$U$134,IFERROR(INDEX(F_Conv,MATCH(C102,F_Fam,0)),"Inclusive"))))) | F102: =IF(B102="","",IF(D102<>"","Forcée",IF('Contrôles'!$J$134>0,"C2",IF('Contrôles'!$U$134<>"","C3","Défaut API")))) | G102: =IF(B102="","",IF(E102="Exclusive",0,1)) | H102: =IF(B102="","",IF(E102="Inclusive",1,0)) | N102: =IF(B102="","",IF(N(L102)>0,I102/L102,0.2)) | O102: =IF(B102="","",IF(N(L102)>0,J102/L102,0.02)) | P102: =IF(B102="","",IF(N(L102)>0,IF(K102="",I102,K102)/L102,0.25)) | X102: =IF(B102="","",R102*S102*P_Mix/1000000+IF(P_Fab="Oui",T102,0)) | Y102: =IF(B102="","",IF(W102<>"",W102,IF(AND(P_Source="Table fournie",U102<>""),U102,X102))) | Z102: =IF(B102="","",IF(W102<>"","Forcé",IF(AND(P_Source="Table fournie",U102<>""),IF(V102="H","Table (hypothèse)","Table (sourcé)"),"Calculateur de Boris")))
E103: =IF(B103="","",IF(D103<>"",D103,IF('Contrôles'!$J$135>0,"Exclusive",IF('Contrôles'!$U$135<>"",'Contrôles'!$U$135,IFERROR(INDEX(F_Conv,MATCH(C103,F_Fam,0)),"Inclusive"))))) | F103: =IF(B103="","",IF(D103<>"","Forcée",IF('Contrôles'!$J$135>0,"C2",IF('Contrôles'!$U$135<>"","C3","Défaut API")))) | G103: =IF(B103="","",IF(E103="Exclusive",0,1)) | H103: =IF(B103="","",IF(E103="Inclusive",1,0)) | N103: =IF(B103="","",IF(N(L103)>0,I103/L103,0.2)) | O103: =IF(B103="","",IF(N(L103)>0,J103/L103,0.02)) | P103: =IF(B103="","",IF(N(L103)>0,IF(K103="",I103,K103)/L103,0.25)) | X103: =IF(B103="","",R103*S103*P_Mix/1000000+IF(P_Fab="Oui",T103,0)) | Y103: =IF(B103="","",IF(W103<>"",W103,IF(AND(P_Source="Table fournie",U103<>""),U103,X103))) | Z103: =IF(B103="","",IF(W103<>"","Forcé",IF(AND(P_Source="Table fournie",U103<>""),IF(V103="H","Table (hypothèse)","Table (sourcé)"),"Calculateur de Boris")))
E104: =IF(B104="","",IF(D104<>"",D104,IF('Contrôles'!$J$136>0,"Exclusive",IF('Contrôles'!$U$136<>"",'Contrôles'!$U$136,IFERROR(INDEX(F_Conv,MATCH(C104,F_Fam,0)),"Inclusive"))))) | F104: =IF(B104="","",IF(D104<>"","Forcée",IF('Contrôles'!$J$136>0,"C2",IF('Contrôles'!$U$136<>"","C3","Défaut API")))) | G104: =IF(B104="","",IF(E104="Exclusive",0,1)) | H104: =IF(B104="","",IF(E104="Inclusive",1,0)) | N104: =IF(B104="","",IF(N(L104)>0,I104/L104,0.2)) | O104: =IF(B104="","",IF(N(L104)>0,J104/L104,0.02)) | P104: =IF(B104="","",IF(N(L104)>0,IF(K104="",I104,K104)/L104,0.25)) | X104: =IF(B104="","",R104*S104*P_Mix/1000000+IF(P_Fab="Oui",T104,0)) | Y104: =IF(B104="","",IF(W104<>"",W104,IF(AND(P_Source="Table fournie",U104<>""),U104,X104))) | Z104: =IF(B104="","",IF(W104<>"","Forcé",IF(AND(P_Source="Table fournie",U104<>""),IF(V104="H","Table (hypothèse)","Table (sourcé)"),"Calculateur de Boris")))
E105: =IF(B105="","",IF(D105<>"",D105,IF('Contrôles'!$J$137>0,"Exclusive",IF('Contrôles'!$U$137<>"",'Contrôles'!$U$137,IFERROR(INDEX(F_Conv,MATCH(C105,F_Fam,0)),"Inclusive"))))) | F105: =IF(B105="","",IF(D105<>"","Forcée",IF('Contrôles'!$J$137>0,"C2",IF('Contrôles'!$U$137<>"","C3","Défaut API")))) | G105: =IF(B105="","",IF(E105="Exclusive",0,1)) | H105: =IF(B105="","",IF(E105="Inclusive",1,0)) | N105: =IF(B105="","",IF(N(L105)>0,I105/L105,0.2)) | O105: =IF(B105="","",IF(N(L105)>0,J105/L105,0.02)) | P105: =IF(B105="","",IF(N(L105)>0,IF(K105="",I105,K105)/L105,0.25)) | X105: =IF(B105="","",R105*S105*P_Mix/1000000+IF(P_Fab="Oui",T105,0)) | Y105: =IF(B105="","",IF(W105<>"",W105,IF(AND(P_Source="Table fournie",U105<>""),U105,X105))) | Z105: =IF(B105="","",IF(W105<>"","Forcé",IF(AND(P_Source="Table fournie",U105<>""),IF(V105="H","Table (hypothèse)","Table (sourcé)"),"Calculateur de Boris")))
E106: =IF(B106="","",IF(D106<>"",D106,IF('Contrôles'!$J$138>0,"Exclusive",IF('Contrôles'!$U$138<>"",'Contrôles'!$U$138,IFERROR(INDEX(F_Conv,MATCH(C106,F_Fam,0)),"Inclusive"))))) | F106: =IF(B106="","",IF(D106<>"","Forcée",IF('Contrôles'!$J$138>0,"C2",IF('Contrôles'!$U$138<>"","C3","Défaut API")))) | G106: =IF(B106="","",IF(E106="Exclusive",0,1)) | H106: =IF(B106="","",IF(E106="Inclusive",1,0)) | N106: =IF(B106="","",IF(N(L106)>0,I106/L106,0.2)) | O106: =IF(B106="","",IF(N(L106)>0,J106/L106,0.02)) | P106: =IF(B106="","",IF(N(L106)>0,IF(K106="",I106,K106)/L106,0.25)) | X106: =IF(B106="","",R106*S106*P_Mix/1000000+IF(P_Fab="Oui",T106,0)) | Y106: =IF(B106="","",IF(W106<>"",W106,IF(AND(P_Source="Table fournie",U106<>""),U106,X106))) | Z106: =IF(B106="","",IF(W106<>"","Forcé",IF(AND(P_Source="Table fournie",U106<>""),IF(V106="H","Table (hypothèse)","Table (sourcé)"),"Calculateur de Boris")))
...

Sheet Contrôles
B2: Contrôles
B3: Contrôles de cohérence de la méthode (C1 à C6), sur toutes les données importées sauf C6 (année affichée).
B5: C1 · Complétude de l'import
B6: Lignes importées | C6: =MAX(0,COUNTA(D_Date)-1) -> 0
B7: Lignes avec une date lisible | C7: =COUNT(D_Jour) -> 0
B8: Lignes hors Copilot (exclues) | C8: =MAX(0,COUNTA(D_Prod)-1-COUNTIF(D_Prod,"*copilot*")) -> 0 | D8: =IF(C8>0,"⚠ Ces lignes ne sont pas comptées.","")
B9: Lignes sans aucun token | C9: =COUNTIFS(D_I,0,D_O,0,D_CR,0,D_CW,0) -> 0
B10: Lignes de modèles inconnus (« Autre modèle ») | C10: =COUNTIF(D_Grp,"(Autre modèle)") -> 0 | D10: =IF(C10>0,"⚠ Ajoutez ces modèles dans Calcul (ligne vide en bas de la table) ; en attendant ils utilisent la ligne « (Autre modèle) ».","✓ Tous les modèles sont reconnus.") -> ✓ Tous les modèles sont reconnus.
B11: Premier jour de données | C11: =S_First -> 46023
B12: Dernier jour de données | C12: =S_Last -> 46023
B14: C3 · Rapprochement des coûts par famille (montant brut ÷ coût recalculé)
B15: Pour chaque hypothèse de convention, le coût est recalculé avec la grille GitHub. La bonne hypothèse donne un rapport entre 0,90 et 1,00 (remises éventuelles). Calcul agrégé par famille.
B16: Famille | C16: Montant brut ($) | D16: Coût inclusive ($) | E16: Coût mixte ($) | F16: Coût exclusive ($) | G16: R inclusive | H16: R mixte | I16: R exclusive | J16: Décision C3
B17: Anthropic | C17: =SUMIF(K_Fam,B17,K_BrutP) -> 0 | D17: =SUMIF(K_Fam,B17,K_Ci) -> 0 | E17: =SUMIF(K_Fam,B17,K_Cm) -> 0 | F17: =SUMIF(K_Fam,B17,K_Ce) -> 0 | G17: =IF(D17>0,C17/D17,"") | H17: =IF(E17>0,C17/E17,"") | I17: =IF(F17>0,C17/F17,"") | J17: =IF(C17<=0,"",IF(AND(N(G17)>=0.895,N(G17)<=1.005),"Inclusive",IF(AND(N(H17)>=0.895,N(H17)<=1.005),"Mixte",IF(AND(N(I17)>=0.895,N(I17)<=1.005),"Exclusive",""))))
B18: OpenAI ≥ GPT-5.6 | C18: =SUMIF(K_Fam,B18,K_BrutP) -> 0 | D18: =SUMIF(K_Fam,B18,K_Ci) -> 0 | E18: =SUMIF(K_Fam,B18,K_Cm) -> 0 | F18: =SUMIF(K_Fam,B18,K_Ce) -> 0 | G18: =IF(D18>0,C18/D18,"") | H18: =IF(E18>0,C18/E18,"") | I18: =IF(F18>0,C18/F18,"") | J18: =IF(C18<=0,"",IF(AND(N(G18)>=0.895,N(G18)<=1.005),"Inclusive",IF(AND(N(H18)>=0.895,N(H18)<=1.005),"Mixte",IF(AND(N(I18)>=0.895,N(I18)<=1.005),"Exclusive",""))))
B19: OpenAI < GPT-5.6 | C19: =SUMIF(K_Fam,B19,K_BrutP) -> 0 | D19: =SUMIF(K_Fam,B19,K_Ci) -> 0 | E19: =SUMIF(K_Fam,B19,K_Cm) -> 0 | F19: =SUMIF(K_Fam,B19,K_Ce) -> 0 | G19: =IF(D19>0,C19/D19,"") | H19: =IF(E19>0,C19/E19,"") | I19: =IF(F19>0,C19/F19,"") | J19: =IF(C19<=0,"",IF(AND(N(G19)>=0.895,N(G19)<=1.005),"Inclusive",IF(AND(N(H19)>=0.895,N(H19)<=1.005),"Mixte",IF(AND(N(I19)>=0.895,N(I19)<=1.005),"Exclusive",""))))
B20: Google Gemini | C20: =SUMIF(K_Fam,B20,K_BrutP) -> 0 | D20: =SUMIF(K_Fam,B20,K_Ci) -> 0 | E20: =SUMIF(K_Fam,B20,K_Cm) -> 0 | F20: =SUMIF(K_Fam,B20,K_Ce) -> 0 | G20: =IF(D20>0,C20/D20,"") | H20: =IF(E20>0,C20/E20,"") | I20: =IF(F20>0,C20/F20,"") | J20: =IF(C20<=0,"",IF(AND(N(G20)>=0.895,N(G20)<=1.005),"Inclusive",IF(AND(N(H20)>=0.895,N(H20)<=1.005),"Mixte",IF(AND(N(I20)>=0.895,N(I20)<=1.005),"Exclusive",""))))
B21: xAI Grok | C21: =SUMIF(K_Fam,B21,K_BrutP) -> 0 | D21: =SUMIF(K_Fam,B21,K_Ci) -> 0 | E21: =SUMIF(K_Fam,B21,K_Cm) -> 0 | F21: =SUMIF(K_Fam,B21,K_Ce) -> 0 | G21: =IF(D21>0,C21/D21,"") | H21: =IF(E21>0,C21/E21,"") | I21: =IF(F21>0,C21/F21,"") | J21: =IF(C21<=0,"",IF(AND(N(G21)>=0.895,N(G21)<=1.005),"Inclusive",IF(AND(N(H21)>=0.895,N(H21)<=1.005),"Mixte",IF(AND(N(I21)>=0.895,N(I21)<=1.005),"Exclusive",""))))
B22: Moonshot Kimi | C22: =SUMIF(K_Fam,B22,K_BrutP) -> 0 | D22: =SUMIF(K_Fam,B22,K_Ci) -> 0 | E22: =SUMIF(K_Fam,B22,K_Cm) -> 0 | F22: =SUMIF(K_Fam,B22,K_Ce) -> 0 | G22: =IF(D22>0,C22/D22,"") | H22: =IF(E22>0,C22/E22,"") | I22: =IF(F22>0,C22/F22,"") | J22: =IF(C22<=0,"",IF(AND(N(G22)>=0.895,N(G22)<=1.005),"Inclusive",IF(AND(N(H22)>=0.895,N(H22)<=1.005),"Mixte",IF(AND(N(I22)>=0.895,N(I22)<=1.005),"Exclusive",""))))
B23: Microsoft MAI | C23: =SUMIF(K_Fam,B23,K_BrutP) -> 0 | D23: =SUMIF(K_Fam,B23,K_Ci) -> 0 | E23: =SUMIF(K_Fam,B23,K_Cm) -> 0 | F23: =SUMIF(K_Fam,B23,K_Ce) -> 0 | G23: =IF(D23>0,C23/D23,"") | H23: =IF(E23>0,C23/E23,"") | I23: =IF(F23>0,C23/F23,"") | J23: =IF(C23<=0,"",IF(AND(N(G23)>=0.895,N(G23)<=1.005),"Inclusive",IF(AND(N(H23)>=0.895,N(H23)<=1.005),"Mixte",IF(AND(N(I23)>=0.895,N(I23)<=1.005),"Exclusive",""))))
B24: Hors grille | C24: =SUMIF(K_Fam,B24,K_BrutP) -> 0 | D24: =SUMIF(K_Fam,B24,K_Ci) -> 0 | E24: =SUMIF(K_Fam,B24,K_Cm) -> 0 | F24: =SUMIF(K_Fam,B24,K_Ce) -> 0 | G24: =IF(D24>0,C24/D24,"") | H24: =IF(E24>0,C24/E24,"") | I24: =IF(F24>0,C24/F24,"") | J24: =IF(C24<=0,"",IF(AND(N(G24)>=0.895,N(G24)<=1.005),"Inclusive",IF(AND(N(H24)>=0.895,N(H24)<=1.005),"Mixte",IF(AND(N(I24)>=0.895,N(I24)<=1.005),"Exclusive",""))))
B27: C4 · Cas particuliers
B28: Lignes avec cache write non facturé (s_CW = s_I appliqué) | C28: =SUM(D_C4CW) -> 0
B29: Lignes où I − δ·CR − ε·CW < 0 (input frais ramené à 0) | C29: =SUM(D_C4F) -> 0 | D29: =IF(C29>0,"⚠ Vérifiez la convention des modèles concernés (colonne C4_input_frais_negatif de Données).","")
B31: C5 · Boucle globale des coûts
B32: Montant brut des modèles tarifés ($) | C32: =SUMIF(K_Cr,">0",K_BrutP) -> 0
B33: Coût recalculé, conventions appliquées ($) | C33: =SUM(K_Cr) -> 0
B34: Rapport | C34: =IF(C33>0,C32/C33,"") | D34: =IF(C33<=0,"",IF(AND(C34>=0.895,C34<=1.005),"✓ Dans la plage 0,90–1,00","⚠ Hors plage 0,90–1,00 : vérifier conventions, tarifs ou remises"))
B36: C6 · Sensibilité (année affichée) | C36: kgCO₂e | D36: Écart / central
B37: Résultat central | C37: =SUM(I_CO2) -> 0 | D37: =IF($C$37>0,C37/$C$37-1,"")
B38: Tout au Calculateur de Boris, mix retenu | C38: =SUMPRODUCT(I_TO,M_FEC) -> 0 | D38: =IF($C$37>0,C38/$C$37-1,"")
B39: Calculateur de Boris, France (2020, EEA) 51,1 g/kWh | C39: =SUMPRODUCT(I_TO,M_eO,M_PUE)*51.1/1000000+IF(P_Fab="Oui",SUMPRODUCT(I_TO,M_Fab),0) -> 0 | D39: =IF($C$37>0,C39/$C$37-1,"")
B40: Calculateur de Boris, Union européenne (2025, IEA) 170 g/kWh | C40: =SUMPRODUCT(I_TO,M_eO,M_PUE)*170/1000000+IF(P_Fab="Oui",SUMPRODUCT(I_TO,M_Fab),0) -> 0 | D40: =IF($C$37>0,C40/$C$37-1,"")
B41: Calculateur de Boris, Monde (2025, IEA) 435 g/kWh | C41: =SUMPRODUCT(I_TO,M_eO,M_PUE)*435/1000000+IF(P_Fab="Oui",SUMPRODUCT(I_TO,M_Fab),0) -> 0 | D41: =IF($C$37>0,C41/$C$37-1,"")
B42: Calculateur de Boris, mix retenu, sans fabrication | C42: =SUMPRODUCT(I_TO,M_eO,M_PUE)*P_Mix/1000000 -> 0 | D42: =IF($C$37>0,C42/$C$37-1,"")
B43: Fourchette basse (résultat central × basse) | C43: =C37*P_Lo -> 0 | D43: =IF($C$37>0,C43/$C$37-1,"")
B44: Fourchette haute (résultat central × haute) | C44: =C37*P_Hi -> 0 | D44: =IF($C$37>0,C44/$C$37-1,"")
B59: C2 et C3 par modèle (toutes données)
B60: C2 : si CR + CW dépasse I sur au moins une ligne, l'input ne contient pas le cache (convention exclusive). Coûts recalculés sans le plancher à 0 de l'input frais.
B61: Modèle | C61: Famille | D61: Lignes | E61: Σ input | F61: Σ cache read | G61: Σ cache write | H61: Σ output | I61: Montant brut ($) | J61: C2 : lignes cache > input | K61: Coût inclusive ($) | L61: Coût mixte ($) | M61: Coût exclusive ($) | N61: R inclusive | O61: R mixte | P61: R exclusive | Q61: Convention appliquée | R61: Coût retenu ($) | S61: R retenu | T61: Verdict | U61: Décision C3 (famille)
B62: =IF(Calcul!B30="","",Calcul!B30) -> GPT-5.3-Codex | C62: =IF(B62="","",Calcul!C30) -> OpenAI < GPT-5.6 | D62: =IF(B62="",0,COUNTIF(D_Cle,B62)) -> 0 | E62: =IF(B62="",0,SUMIF(D_Cle,B62,D_I)) -> 0 | F62: =IF(B62="",0,SUMIF(D_Cle,B62,D_CR)) -> 0 | G62: =IF(B62="",0,SUMIF(D_Cle,B62,D_CW)) -> 0 | H62: =IF(B62="",0,SUMIF(D_Cle,B62,D_O)) -> 0 | I62: =IF(B62="",0,SUMIF(D_Cle,B62,D_Brut)) -> 0 | J62: =IF(B62="",0,SUMIF(D_Cle,B62,D_C2)) -> 0 | K62: =IF(AND(B62<>"",N(Calcul!L30)>0),(Calcul!I30*(E62-F62-G62)+N(Calcul!J30)*F62+IF(Calcul!K30="",Calcul!I30,Calcul!K30)*G62+N(Calcul!L30)*H62)/1000000,0) -> 0 | L62: =IF(AND(B62<>"",N(Calcul!L30)>0),(Calcul!I30*(E62-F62)+N(Calcul!J30)*F62+IF(Calcul!K30="",Calcul!I30,Calcul!K30)*G62+N(Calcul!L30)*H62)/1000000,0) -> 0 | M62: =IF(AND(B62<>"",N(Calcul!L30)>0),(Calcul!I30*E62+N(Calcul!J30)*F62+IF(Calcul!K30="",Calcul!I30,Calcul!K30)*G62+N(Calcul!L30)*H62)/1000000,0) -> 0 | N62: =IF(K62>0,I62/K62,"") | O62: =IF(L62>0,I62/L62,"") | P62: =IF(M62>0,I62/M62,"") | Q62: =IF(B62="","",Calcul!E30) -> Inclusive | R62: =IF(AND(B62<>"",N(Calcul!L30)>0),(Calcul!I30*(E62-Calcul!G30*F62-Calcul!H30*G62)+N(Calcul!J30)*F62+IF(Calcul!K30="",Calcul!I30,Calcul!K30)*G62+N(Calcul!L30)*H62)/1000000,0) -> 0 | S62: =IF(R62>0,I62/R62,"") | T62: =IF(OR(B62="",D62=0),"",IF(S62="","Sans tarif",IF(AND(S62>=0.895,S62<=1.005),"✓ Cohérent","⚠ Hors plage"))) | U62: =IF(B62="","",IFERROR(INDEX(K_FamDec,MATCH(C62,K_FamNom,0)),""))
B63: =IF(Calcul!B31="","",Calcul!B31) -> GPT-5.4 nano | C63: =IF(B63="","",Calcul!C31) -> OpenAI < GPT-5.6 | D63: =IF(B63="",0,COUNTIF(D_Cle,B63)) -> 0 | E63: =IF(B63="",0,SUMIF(D_Cle,B63,D_I)) -> 0 | F63: =IF(B63="",0,SUMIF(D_Cle,B63,D_CR)) -> 0 | G63: =IF(B63="",0,SUMIF(D_Cle,B63,D_CW)) -> 0 | H63: =IF(B63="",0,SUMIF(D_Cle,B63,D_O)) -> 0 | I63: =IF(B63="",0,SUMIF(D_Cle,B63,D_Brut)) -> 0 | J63: =IF(B63="",0,SUMIF(D_Cle,B63,D_C2)) -> 0 | K63: =IF(AND(B63<>"",N(Calcul!L31)>0),(Calcul!I31*(E63-F63-G63)+N(Calcul!J31)*F63+IF(Calcul!K31="",Calcul!I31,Calcul!K31)*G63+N(Calcul!L31)*H63)/1000000,0) -> 0 | L63: =IF(AND(B63<>"",N(Calcul!L31)>0),(Calcul!I31*(E63-F63)+N(Calcul!J31)*F63+IF(Calcul!K31="",Calcul!I31,Calcul!K31)*G63+N(Calcul!L31)*H63)/1000000,0) -> 0 | M63: =IF(AND(B63<>"",N(Calcul!L31)>0),(Calcul!I31*E63+N(Calcul!J31)*F63+IF(Calcul!K31="",Calcul!I31,Calcul!K31)*G63+N(Calcul!L31)*H63)/1000000,0) -> 0 | N63: =IF(K63>0,I63/K63,"") | O63: =IF(L63>0,I63/L63,"") | P63: =IF(M63>0,I63/M63,"") | Q63: =IF(B63="","",Calcul!E31) -> Inclusive | R63: =IF(AND(B63<>"",N(Calcul!L31)>0),(Calcul!I31*(E63-Calcul!G31*F63-Calcul!H31*G63)+N(Calcul!J31)*F63+IF(Calcul!K31="",Calcul!I31,Calcul!K31)*G63+N(Calcul!L31)*H63)/1000000,0) -> 0 | S63: =IF(R63>0,I63/R63,"") | T63: =IF(OR(B63="",D63=0),"",IF(S63="","Sans tarif",IF(AND(S63>=0.895,S63<=1.005),"✓ Cohérent","⚠ Hors plage"))) | U63: =IF(B63="","",IFERROR(INDEX(K_FamDec,MATCH(C63,K_FamNom,0)),""))
B64: =IF(Calcul!B32="","",Calcul!B32) -> GPT-5.6 Luna | C64: =IF(B64="","",Calcul!C32) -> OpenAI ≥ GPT-5.6 | D64: =IF(B64="",0,COUNTIF(D_Cle,B64)) -> 0 | E64: =IF(B64="",0,SUMIF(D_Cle,B64,D_I)) -> 0 | F64: =IF(B64="",0,SUMIF(D_Cle,B64,D_CR)) -> 0 | G64: =IF(B64="",0,SUMIF(D_Cle,B64,D_CW)) -> 0 | H64: =IF(B64="",0,SUMIF(D_Cle,B64,D_O)) -> 0 | I64: =IF(B64="",0,SUMIF(D_Cle,B64,D_Brut)) -> 0 | J64: =IF(B64="",0,SUMIF(D_Cle,B64,D_C2)) -> 0 | K64: =IF(AND(B64<>"",N(Calcul!L32)>0),(Calcul!I32*(E64-F64-G64)+N(Calcul!J32)*F64+IF(Calcul!K32="",Calcul!I32,Calcul!K32)*G64+N(Calcul!L32)*H64)/1000000,0) -> 0 | L64: =IF(AND(B64<>"",N(Calcul!L32)>0),(Calcul!I32*(E64-F64)+N(Calcul!J32)*F64+IF(Calcul!K32="",Calcul!I32,Calcul!K32)*G64+N(Calcul!L32)*H64)/1000000,0) -> 0 | M64: =IF(AND(B64<>"",N(Calcul!L32)>0),(Calcul!I32*E64+N(Calcul!J32)*F64+IF(Calcul!K32="",Calcul!I32,Calcul!K32)*G64+N(Calcul!L32)*H64)/1000000,0) -> 0 | N64: =IF(K64>0,I64/K64,"") | O64: =IF(L64>0,I64/L64,"") | P64: =IF(M64>0,I64/M64,"") | Q64: =IF(B64="","",Calcul!E32) -> Inclusive | R64: =IF(AND(B64<>"",N(Calcul!L32)>0),(Calcul!I32*(E64-Calcul!G32*F64-Calcul!H32*G64)+N(Calcul!J32)*F64+IF(Calcul!K32="",Calcul!I32,Calcul!K32)*G64+N(Calcul!L32)*H64)/1000000,0) -> 0 | S64: =IF(R64>0,I64/R64,"") | T64: =IF(OR(B64="",D64=0),"",IF(S64="","Sans tarif",IF(AND(S64>=0.895,S64<=1.005),"✓ Cohérent","⚠ Hors plage"))) | U64: =IF(B64="","",IFERROR(INDEX(K_FamDec,MATCH(C64,K_FamNom,0)),""))
B65: =IF(Calcul!B33="","",Calcul!B33) -> GPT-5.6 Terra | C65: =IF(B65="","",Calcul!C33) -> OpenAI ≥ GPT-5.6 | D65: =IF(B65="",0,COUNTIF(D_Cle,B65)) -> 0 | E65: =IF(B65="",0,SUMIF(D_Cle,B65,D_I)) -> 0 | F65: =IF(B65="",0,SUMIF(D_Cle,B65,D_CR)) -> 0 | G65: =IF(B65="",0,SUMIF(D_Cle,B65,D_CW)) -> 0 | H65: =IF(B65="",0,SUMIF(D_Cle,B65,D_O)) -> 0 | I65: =IF(B65="",0,SUMIF(D_Cle,B65,D_Brut)) -> 0 | J65: =IF(B65="",0,SUMIF(D_Cle,B65,D_C2)) -> 0 | K65: =IF(AND(B65<>"",N(Calcul!L33)>0),(Calcul!I33*(E65-F65-G65)+N(Calcul!J33)*F65+IF(Calcul!K33="",Calcul!I33,Calcul!K33)*G65+N(Calcul!L33)*H65)/1000000,0) -> 0 | L65: =IF(AND(B65<>"",N(Calcul!L33)>0),(Calcul!I33*(E65-F65)+N(Calcul!J33)*F65+IF(Calcul!K33="",Calcul!I33,Calcul!K33)*G65+N(Calcul!L33)*H65)/1000000,0) -> 0 | M65: =IF(AND(B65<>"",N(Calcul!L33)>0),(Calcul!I33*E65+N(Calcul!J33)*F65+IF(Calcul!K33="",Calcul!I33,Calcul!K33)*G65+N(Calcul!L33)*H65)/1000000,0) -> 0 | N65: =IF(K65>0,I65/K65,"") | O65: =IF(L65>0,I65/L65,"") | P65: =IF(M65>0,I65/M65,"") | Q65: =IF(B65="","",Calcul!E33) -> Inclusive | R65: =IF(AND(B65<>"",N(Calcul!L33)>0),(Calcul!I33*(E65-Calcul!G33*F65-Calcul!H33*G65)+N(Calcul!J33)*F65+IF(Calcul!K33="",Calcul!I33,Calcul!K33)*G65+N(Calcul!L33)*H65)/1000000,0) -> 0 | S65: =IF(R65>0,I65/R65,"") | T65: =IF(OR(B65="",D65=0),"",IF(S65="","Sans tarif",IF(AND(S65>=0.895,S65<=1.005),"✓ Cohérent","⚠ Hors plage"))) | U65: =IF(B65="","",IFERROR(INDEX(K_FamDec,MATCH(C65,K_FamNom,0)),""))
B66: =IF(Calcul!B34="","",Calcul!B34) -> GPT-5.6 Sol | C66: =IF(B66="","",Calcul!C34) -> OpenAI ≥ GPT-5.6 | D66: =IF(B66="",0,COUNTIF(D_Cle,B66)) -> 0 | E66: =IF(B66="",0,SUMIF(D_Cle,B66,D_I)) -> 0 | F66: =IF(B66="",0,SUMIF(D_Cle,B66,D_CR)) -> 0 | G66: =IF(B66="",0,SUMIF(D_Cle,B66,D_CW)) -> 0 | H66: =IF(B66="",0,SUMIF(D_Cle,B66,D_O)) -> 0 | I66: =IF(B66="",0,SUMIF(D_Cle,B66,D_Brut)) -> 0 | J66: =IF(B66="",0,SUMIF(D_Cle,B66,D_C2)) -> 0 | K66: =IF(AND(B66<>"",N(Calcul!L34)>0),(Calcul!I34*(E66-F66-G66)+N(Calcul!J34)*F66+IF(Calcul!K34="",Calcul!I34,Calcul!K34)*G66+N(Calcul!L34)*H66)/1000000,0) -> 0 | L66: =IF(AND(B66<>"",N(Calcul!L34)>0),(Calcul!I34*(E66-F66)+N(Calcul!J34)*F66+IF(Calcul!K34="",Calcul!I34,Calcul!K34)*G66+N(Calcul!L34)*H66)/1000000,0) -> 0 | M66: =IF(AND(B66<>"",N(Calcul!L34)>0),(Calcul!I34*E66+N(Calcul!J34)*F66+IF(Calcul!K34="",Calcul!I34,Calcul!K34)*G66+N(Calcul!L34)*H66)/1000000,0) -> 0 | N66: =IF(K66>0,I66/K66,"") | O66: =IF(L66>0,I66/L66,"") | P66: =IF(M66>0,I66/M66,"") | Q66: =IF(B66="","",Calcul!E34) -> Inclusive | R66: =IF(AND(B66<>"",N(Calcul!L34)>0),(Calcul!I34*(E66-Calcul!G34*F66-Calcul!H34*G66)+N(Calcul!J34)*F66+IF(Calcul!K34="",Calcul!I34,Calcul!K34)*G66+N(Calcul!L34)*H66)/1000000,0) -> 0 | S66: =IF(R66>0,I66/R66,"") | T66: =IF(OR(B66="",D66=0),"",IF(S66="","Sans tarif",IF(AND(S66>=0.895,S66<=1.005),"✓ Cohérent","⚠ Hors plage"))) | U66: =IF(B66="","",IFERROR(INDEX(K_FamDec,MATCH(C66,K_FamNom,0)),""))
B67: =IF(Calcul!B35="","",Calcul!B35) -> GPT-6 Luna | C67: =IF(B67="","",Calcul!C35) -> OpenAI ≥ GPT-5.6 | D67: =IF(B67="",0,COUNTIF(D_Cle,B67)) -> 0 | E67: =IF(B67="",0,SUMIF(D_Cle,B67,D_I)) -> 0 | F67: =IF(B67="",0,SUMIF(D_Cle,B67,D_CR)) -> 0 | G67: =IF(B67="",0,SUMIF(D_Cle,B67,D_CW)) -> 0 | H67: =IF(B67="",0,SUMIF(D_Cle,B67,D_O)) -> 0 | I67: =IF(B67="",0,SUMIF(D_Cle,B67,D_Brut)) -> 0 | J67: =IF(B67="",0,SUMIF(D_Cle,B67,D_C2)) -> 0 | K67: =IF(AND(B67<>"",N(Calcul!L35)>0),(Calcul!I35*(E67-F67-G67)+N(Calcul!J35)*F67+IF(Calcul!K35="",Calcul!I35,Calcul!K35)*G67+N(Calcul!L35)*H67)/1000000,0) -> 0 | L67: =IF(AND(B67<>"",N(Calcul!L35)>0),(Calcul!I35*(E67-F67)+N(Calcul!J35)*F67+IF(Calcul!K35="",Calcul!I35,Calcul!K35)*G67+N(Calcul!L35)*H67)/1000000,0) -> 0 | M67: =IF(AND(B67<>"",N(Calcul!L35)>0),(Calcul!I35*E67+N(Calcul!J35)*F67+IF(Calcul!K35="",Calcul!I35,Calcul!K35)*G67+N(Calcul!L35)*H67)/1000000,0) -> 0 | N67: =IF(K67>0,I67/K67,"") | O67: =IF(L67>0,I67/L67,"") | P67: =IF(M67>0,I67/M67,"") | Q67: =IF(B67="","",Calcul!E35) -> Inclusive | R67: =IF(AND(B67<>"",N(Calcul!L35)>0),(Calcul!I35*(E67-Calcul!G35*F67-Calcul!H35*G67)+N(Calcul!J35)*F67+IF(Calcul!K35="",Calcul!I35,Calcul!K35)*G67+N(Calcul!L35)*H67)/1000000,0) -> 0 | S67: =IF(R67>0,I67/R67,"") | T67: =IF(OR(B67="",D67=0),"",IF(S67="","Sans tarif",IF(AND(S67>=0.895,S67<=1.005),"✓ Cohérent","⚠ Hors plage"))) | U67: =IF(B67="","",IFERROR(INDEX(K_FamDec,MATCH(C67,K_FamNom,0)),""))
B68: =IF(Calcul!B36="","",Calcul!B36) -> GPT-6 Sol | C68: =IF(B68="","",Calcul!C36) -> OpenAI ≥ GPT-5.6 | D68: =IF(B68="",0,COUNTIF(D_Cle,B68)) -> 0 | E68: =IF(B68="",0,SUMIF(D_Cle,B68,D_I)) -> 0 | F68: =IF(B68="",0,SUMIF(D_Cle,B68,D_CR)) -> 0 | G68: =IF(B68="",0,SUMIF(D_Cle,B68,D_CW)) -> 0 | H68: =IF(B68="",0,SUMIF(D_Cle,B68,D_O)) -> 0 | I68: =IF(B68="",0,SUMIF(D_Cle,B68,D_Brut)) -> 0 | J68: =IF(B68="",0,SUMIF(D_Cle,B68,D_C2)) -> 0 | K68: =IF(AND(B68<>"",N(Calcul!L36)>0),(Calcul!I36*(E68-F68-G68)+N(Calcul!J36)*F68+IF(Calcul!K36="",Calcul!I36,Calcul!K36)*G68+N(Calcul!L36)*H68)/1000000,0) -> 0 | L68: =IF(AND(B68<>"",N(Calcul!L36)>0),(Calcul!I36*(E68-F68)+N(Calcul!J36)*F68+IF(Calcul!K36="",Calcul!I36,Calcul!K36)*G68+N(Calcul!L36)*H68)/1000000,0) -> 0 | M68: =IF(AND(B68<>"",N(Calcul!L36)>0),(Calcul!I36*E68+N(Calcul!J36)*F68+IF(Calcul!K36="",Calcul!I36,Calcul!K36)*G68+N(Calcul!L36)*H68)/1000000,0) -> 0 | N68: =IF(K68>0,I68/K68,"") | O68: =IF(L68>0,I68/L68,"") | P68: =IF(M68>0,I68/M68,"") | Q68: =IF(B68="","",Calcul!E36) -> Inclusive | R68: =IF(AND(B68<>"",N(Calcul!L36)>0),(Calcul!I36*(E68-Calcul!G36*F68-Calcul!H36*G68)+N(Calcul!J36)*F68+IF(Calcul!K36="",Calcul!I36,Calcul!K36)*G68+N(Calcul!L36)*H68)/1000000,0) -> 0 | S68: =IF(R68>0,I68/R68,"") | T68: =IF(OR(B68="",D68=0),"",IF(S68="","Sans tarif",IF(AND(S68>=0.895,S68<=1.005),"✓ Cohérent","⚠ Hors plage"))) | U68: =IF(B68="","",IFERROR(INDEX(K_FamDec,MATCH(C68,K_FamNom,0)),""))
B69: =IF(Calcul!B37="","",Calcul!B37) -> GPT-6 Astra | C69: =IF(B69="","",Calcul!C37) -> OpenAI ≥ GPT-5.6 | D69: =IF(B69="",0,COUNTIF(D_Cle,B69)) -> 0 | E69: =IF(B69="",0,SUMIF(D_Cle,B69,D_I)) -> 0 | F69: =IF(B69="",0,SUMIF(D_Cle,B69,D_CR)) -> 0 | G69: =IF(B69="",0,SUMIF(D_Cle,B69,D_CW)) -> 0 | H69: =IF(B69="",0,SUMIF(D_Cle,B69,D_O)) -> 0 | I69: =IF(B69="",0,SUMIF(D_Cle,B69,D_Brut)) -> 0 | J69: =IF(B69="",0,SUMIF(D_Cle,B69,D_C2)) -> 0 | K69: =IF(AND(B69<>"",N(Calcul!L37)>0),(Calcul!I37*(E69-F69-G69)+N(Calcul!J37)*F69+IF(Calcul!K37="",Calcul!I37,Calcul!K37)*G69+N(Calcul!L37)*H69)/1000000,0) -> 0 | L69: =IF(AND(B69<>"",N(Calcul!L37)>0),(Calcul!I37*(E69-F69)+N(Calcul!J37)*F69+IF(Calcul!K37="",Calcul!I37,Calcul!K37)*G69+N(Calcul!L37)*H69)/1000000,0) -> 0 | M69: =IF(AND(B69<>"",N(Calcul!L37)>0),(Calcul!I37*E69+N(Calcul!J37)*F69+IF(Calcul!K37="",Calcul!I37,Calcul!K37)*G69+N(Calcul!L37)*H69)/1000000,0) -> 0 | N69: =IF(K69>0,I69/K69,"") | O69: =IF(L69>0,I69/L69,"") | P69: =IF(M69>0,I69/M69,"") | Q69: =IF(B69="","",Calcul!E37) -> Inclusive | R69: =IF(AND(B69<>"",N(Calcul!L37)>0),(Calcul!I37*(E69-Calcul!G37*F69-Calcul!H37*G69)+N(Calcul!J37)*F69+IF(Calcul!K37="",Calcul!I37,Calcul!K37)*G69+N(Calcul!L37)*H69)/1000000,0) -> 0 | S69: =IF(R69>0,I69/R69,"") | T69: =IF(OR(B69="",D69=0),"",IF(S69="","Sans tarif",IF(AND(S69>=0.895,S69<=1.005),"✓ Cohérent","⚠ Hors plage"))) | U69: =IF(B69="","",IFERROR(INDEX(K_FamDec,MATCH(C69,K_FamNom,0)),""))
B70: =IF(Calcul!B38="","",Calcul!B38) -> GPT-6.1 Sol | C70: =IF(B70="","",Calcul!C38) -> OpenAI ≥ GPT-5.6 | D70: =IF(B70="",0,COUNTIF(D_Cle,B70)) -> 0 | E70: =IF(B70="",0,SUMIF(D_Cle,B70,D_I)) -> 0 | F70: =IF(B70="",0,SUMIF(D_Cle,B70,D_CR)) -> 0 | G70: =IF(B70="",0,SUMIF(D_Cle,B70,D_CW)) -> 0 | H70: =IF(B70="",0,SUMIF(D_Cle,B70,D_O)) -> 0 | I70: =IF(B70="",0,SUMIF(D_Cle,B70,D_Brut)) -> 0 | J70: =IF(B70="",0,SUMIF(D_Cle,B70,D_C2)) -> 0 | K70: =IF(AND(B70<>"",N(Calcul!L38)>0),(Calcul!I38*(E70-F70-G70)+N(Calcul!J38)*F70+IF(Calcul!K38="",Calcul!I38,Calcul!K38)*G70+N(Calcul!L38)*H70)/1000000,0) -> 0 | L70: =IF(AND(B70<>"",N(Calcul!L38)>0),(Calcul!I38*(E70-F70)+N(Calcul!J38)*F70+IF(Calcul!K38="",Calcul!I38,Calcul!K38)*G70+N(Calcul!L38)*H70)/1000000,0) -> 0 | M70: =IF(AND(B70<>"",N(Calcul!L38)>0),(Calcul!I38*E70+N(Calcul!J38)*F70+IF(Calcul!K38="",Calcul!I38,Calcul!K38)*G70+N(Calcul!L38)*H70)/1000000,0) -> 0 | N70: =IF(K70>0,I70/K70,"") | O70: =IF(L70>0,I70/L70,"") | P70: =IF(M70>0,I70/M70,"") | Q70: =IF(B70="","",Calcul!E38) -> Inclusive | R70: =IF(AND(B70<>"",N(Calcul!L38)>0),(Calcul!I38*(E70-Calcul!G38*F70-Calcul!H38*G70)+N(Calcul!J38)*F70+IF(Calcul!K38="",Calcul!I38,Calcul!K38)*G70+N(Calcul!L38)*H70)/1000000,0) -> 0 | S70: =IF(R70>0,I70/R70,"") | T70: =IF(OR(B70="",D70=0),"",IF(S70="","Sans tarif",IF(AND(S70>=0.895,S70<=1.005),"✓ Cohérent","⚠ Hors plage"))) | U70: =IF(B70="","",IFERROR(INDEX(K_FamDec,MATCH(C70,K_FamNom,0)),""))
B71: =IF(Calcul!B39="","",Calcul!B39) -> GPT-5 mini | C71: =IF(B71="","",Calcul!C39) -> OpenAI < GPT-5.6 | D71: =IF(B71="",0,COUNTIF(D_Cle,B71)) -> 0 | E71: =IF(B71="",0,SUMIF(D_Cle,B71,D_I)) -> 0 | F71: =IF(B71="",0,SUMIF(D_Cle,B71,D_CR)) -> 0 | G71: =IF(B71="",0,SUMIF(D_Cle,B71,D_CW)) -> 0 | H71: =IF(B71="",0,SUMIF(D_Cle,B71,D_O)) -> 0 | I71: =IF(B71="",0,SUMIF(D_Cle,B71,D_Brut)) -> 0 | J71: =IF(B71="",0,SUMIF(D_Cle,B71,D_C2)) -> 0 | K71: =IF(AND(B71<>"",N(Calcul!L39)>0),(Calcul!I39*(E71-F71-G71)+N(Calcul!J39)*F71+IF(Calcul!K39="",Calcul!I39,Calcul!K39)*G71+N(Calcul!L39)*H71)/1000000,0) -> 0 | L71: =IF(AND(B71<>"",N(Calcul!L39)>0),(Calcul!I39*(E71-F71)+N(Calcul!J39)*F71+IF(Calcul!K39="",Calcul!I39,Calcul!K39)*G71+N(Calcul!L39)*H71)/1000000,0) -> 0 | M71: =IF(AND(B71<>"",N(Calcul!L39)>0),(Calcul!I39*E71+N(Calcul!J39)*F71+IF(Calcul!K39="",Calcul!I39,Calcul!K39)*G71+N(Calcul!L39)*H71)/1000000,0) -> 0 | N71: =IF(K71>0,I71/K71,"") | O71: =IF(L71>0,I71/L71,"") | P71: =IF(M71>0,I71/M71,"") | Q71: =IF(B71="","",Calcul!E39) -> Inclusive | R71: =IF(AND(B71<>"",N(Calcul!L39)>0),(Calcul!I39*(E71-Calcul!G39*F71-Calcul!H39*G71)+N(Calcul!J39)*F71+IF(Calcul!K39="",Calcul!I39,Calcul!K39)*G71+N(Calcul!L39)*H71)/1000000,0) -> 0 | S71: =IF(R71>0,I71/R71,"") | T71: =IF(OR(B71="",D71=0),"",IF(S71="","Sans tarif",IF(AND(S71>=0.895,S71<=1.005),"✓ Cohérent","⚠ Hors plage"))) | U71: =IF(B71="","",IFERROR(INDEX(K_FamDec,MATCH(C71,K_FamNom,0)),""))
B72: =IF(Calcul!B40="","",Calcul!B40) -> GPT-5.4 mini | C72: =IF(B72="","",Calcul!C40) -> OpenAI < GPT-5.6 | D72: =IF(B72="",0,COUNTIF(D_Cle,B72)) -> 0 | E72: =IF(B72="",0,SUMIF(D_Cle,B72,D_I)) -> 0 | F72: =IF(B72="",0,SUMIF(D_Cle,B72,D_CR)) -> 0 | G72: =IF(B72="",0,SUMIF(D_Cle,B72,D_CW)) -> 0 | H72: =IF(B72="",0,SUMIF(D_Cle,B72,D_O)) -> 0 | I72: =IF(B72="",0,SUMIF(D_Cle,B72,D_Brut)) -> 0 | J72: =IF(B72="",0,SUMIF(D_Cle,B72,D_C2)) -> 0 | K72: =IF(AND(B72<>"",N(Calcul!L40)>0),(Calcul!I40*(E72-F72-G72)+N(Calcul!J40)*F72+IF(Calcul!K40="",Calcul!I40,Calcul!K40)*G72+N(Calcul!L40)*H72)/1000000,0) -> 0 | L72: =IF(AND(B72<>"",N(Calcul!L40)>0),(Calcul!I40*(E72-F72)+N(Calcul!J40)*F72+IF(Calcul!K40="",Calcul!I40,Calcul!K40)*G72+N(Calcul!L40)*H72)/1000000,0) -> 0 | M72: =IF(AND(B72<>"",N(Calcul!L40)>0),(Calcul!I40*E72+N(Calcul!J40)*F72+IF(Calcul!K40="",Calcul!I40,Calcul!K40)*G72+N(Calcul!L40)*H72)/1000000,0) -> 0 | N72: =IF(K72>0,I72/K72,"") | O72: =IF(L72>0,I72/L72,"") | P72: =IF(M72>0,I72/M72,"") | Q72: =IF(B72="","",Calcul!E40) -> Inclusive | R72: =IF(AND(B72<>"",N(Calcul!L40)>0),(Calcul!I40*(E72-Calcul!G40*F72-Calcul!H40*G72)+N(Calcul!J40)*F72+IF(Calcul!K40="",Calcul!I40,Calcul!K40)*G72+N(Calcul!L40)*H72)/1000000,0) -> 0 | S72: =IF(R72>0,I72/R72,"") | T72: =IF(OR(B72="",D72=0),"",IF(S72="","Sans tarif",IF(AND(S72>=0.895,S72<=1.005),"✓ Cohérent","⚠ Hors plage"))) | U72: =IF(B72="","",IFERROR(INDEX(K_FamDec,MATCH(C72,K_FamNom,0)),""))
B73: =IF(Calcul!B41="","",Calcul!B41) -> GPT-5.4 | C73: =IF(B73="","",Calcul!C41) -> OpenAI < GPT-5.6 | D73: =IF(B73="",0,COUNTIF(D_Cle,B73)) -> 0 | E73: =IF(B73="",0,SUMIF(D_Cle,B73,D_I)) -> 0 | F73: =IF(B73="",0,SUMIF(D_Cle,B73,D_CR)) -> 0 | G73: =IF(B73="",0,SUMIF(D_Cle,B73,D_CW)) -> 0 | H73: =IF(B73="",0,SUMIF(D_Cle,B73,D_O)) -> 0 | I73: =IF(B73="",0,SUMIF(D_Cle,B73,D_Brut)) -> 0 | J73: =IF(B73="",0,SUMIF(D_Cle,B73,D_C2)) -> 0 | K73: =IF(AND(B73<>"",N(Calcul!L41)>0),(Calcul!I41*(E73-F73-G73)+N(Calcul!J41)*F73+IF(Calcul!K41="",Calcul!I41,Calcul!K41)*G73+N(Calcul!L41)*H73)/1000000,0) -> 0 | L73: =IF(AND(B73<>"",N(Calcul!L41)>0),(Calcul!I41*(E73-F73)+N(Calcul!J41)*F73+IF(Calcul!K41="",Calcul!I41,Calcul!K41)*G73+N(Calcul!L41)*H73)/1000000,0) -> 0 | M73: =IF(AND(B73<>"",N(Calcul!L41)>0),(Calcul!I41*E73+N(Calcul!J41)*F73+IF(Calcul!K41="",Calcul!I41,Calcul!K41)*G73+N(Calcul!L41)*H73)/1000000,0) -> 0 | N73: =IF(K73>0,I73/K73,"") | O73: =IF(L73>0,I73/L73,"") | P73: =IF(M73>0,I73/M73,"") | Q73: =IF(B73="","",Calcul!E41) -> Inclusive | R73: =IF(AND(B73<>"",N(Calcul!L41)>0),(Calcul!I41*(E73-Calcul!G41*F73-Calcul!H41*G73)+N(Calcul!J41)*F73+IF(Calcul!K41="",Calcul!I41,Calcul!K41)*G73+N(Calcul!L41)*H73)/1000000,0) -> 0 | S73: =IF(R73>0,I73/R73,"") | T73: =IF(OR(B73="",D73=0),"",IF(S73="","Sans tarif",IF(AND(S73>=0.895,S73<=1.005),"✓ Cohérent","⚠ Hors plage"))) | U73: =IF(B73="","",IFERROR(INDEX(K_FamDec,MATCH(C73,K_FamNom,0)),""))
... B150: =IF(Calcul!B118="","",Calcul!B118) | C150: =IF(B150="","",Calcul!C118) | D150: =IF(B150="",0,COUNTIF(D_Cle,B150)) -> 0 | E150: =IF(B150="",0,SUMIF(D_Cle,B150,D_I)) -> 0 | F150: =IF(B150="",0,SUMIF(D_Cle,B150,D_CR)) -> 0 | G150: =IF(B150="",0,SUMIF(D_Cle,B150,D_CW)) -> 0 | H150: =IF(B150="",0,SUMIF(D_Cle,B150,D_O)) -> 0 | I150: =IF(B150="",0,SUMIF(D_Cle,B150,D_Brut)) -> 0 | J150: =IF(B150="",0,SUMIF(D_Cle,B150,D_C2)) -> 0 | K150: =IF(AND(B150<>"",N(Calcul!L118)>0),(Calcul!I118*(E150-F150-G150)+N(Calcul!J118)*F150+IF(Calcul!K118="",Calcul!I118,Calcul!K118)*G150+N(Calcul!L118)*H150)/1000000,0) -> 0 | L150: =IF(AND(B150<>"",N(Calcul!L118)>0),(Calcul!I118*(E150-F150)+N(Calcul!J118)*F150+IF(Calcul!K118="",Calcul!I118,Calcul!K118)*G150+N(Calcul!L118)*H150)/1000000,0) -> 0 | M150: =IF(AND(B150<>"",N(Calcul!L118)>0),(Calcul!I118*E150+N(Calcul!J118)*F150+IF(Calcul!K118="",Calcul!I118,Calcul!K118)*G150+N(Calcul!L118)*H150)/1000000,0) -> 0 | N150: =IF(K150>0,I150/K150,"") | O150: =IF(L150>0,I150/L150,"") | P150: =IF(M150>0,I150/M150,"") | Q150: =IF(B150="","",Calcul!E118) | R150: =IF(AND(B150<>"",N(Calcul!L118)>0),(Calcul!I118*(E150-Calcul!G118*F150-Calcul!H118*G150)+N(Calcul!J118)*F150+IF(Calcul!K118="",Calcul!I118,Calcul!K118)*G150+N(Calcul!L118)*H150)/1000000,0) -> 0 | S150: =IF(R150>0,I150/R150,"") | T150: =IF(OR(B150="",D150=0),"",IF(S150="","Sans tarif",IF(AND(S150>=0.895,S150<=1.005),"✓ Cohérent","⚠ Hors plage"))) | U150: =IF(B150="","",IFERROR(INDEX(K_FamDec,MATCH(C150,K_FamNom,0)),""))

Sheet Méthodologie
B2: Méthodologie
B3: Méthode « Contrôle des tokens GitHub Copilot pour l'empreinte carbone de l'inférence » du 20 octobre 2026.
B5: Objet
B6: Le classeur estime l'empreinte carbone de l'inférence des modèles utilisés via GitHub Copilot, jour par jour, à partir de l'export « AI usage report ». C'est la déclinaison Excel du tableau de bord HTML : mêmes formules, mêmes facteurs, mêmes contrôles.
B8: Formules
B9: Input frais : F = max(0, I − δ·CR − ε·CW). Tokens équivalent output : T_O = F·s_I + CR·s_CR + CW·s_CW + O, chaque catégorie étant pondérée par son prix rapporté au prix de l'output du même modèle (s_I = P_I / P_O, etc.). Énergie : E = T_O × e_O × PUE / 1000. Empreinte : CO₂e = T_O × FE_token.
B11: Convention de l'input (δ, ε)
B12: GitHub ne documente pas si la colonne input de l'export contient déjà le cache. Pour chaque modèle : convention forcée dans Calcul, sinon C2 (si CR + CW dépasse I sur au moins une ligne, la convention est forcément exclusive), sinon C3 (rapprochement des coûts de la famille), sinon la convention documentée de l'API du fournisseur.
B14: Prix
B15: Grille GitHub du 20 octobre 2026, palier standard, en dollars par million de tokens. Le palier long contexte n'est pas identifiable dans l'export. Quand le cache write n'est pas facturé mais que CW > 0, s_CW = s_I. Le prix du cache read de Claude Sonnet 5.5 était de 0,20 $ avant le 1er octobre 2026 : les lignes antérieures utilisent la ligne « [ancien tarif] ». Claude Opus 4.5, 4.6, 4.7 et Claude Sonnet 4.5 ne figurent plus dans la grille GitHub : leurs tarifs publics de l'API Anthropic sont utilisés. Les modèles « Auto: X » utilisent les paramètres de X.
B17: Facteurs d'émission
B18: FE_token provient de votre table de facteurs en kgCO₂e par token (transmise le 23 octobre 2026), dont chaque ligne est marquée S (sourcé) ou H (hypothèse). Les modèles absents de la table sont calculés avec le Calculateur de Boris (carbon-footprint-modeling-tool de Boris Ruf, scénarios EcoLogits v2, commit 50bc8b0) : FE = PUE (1,2) × énergie GPU + serveur par token × intensité du mix électrique + fabrication du matériel par token (scope 3). Les modèles de 2026 absents du Calculateur de Boris sont rattachés au scénario le plus proche (marqués « proxy »).
... B30: EcoLogits ne compte que les tokens générés : appliquer un facteur par token généré à T_O, qui intègre l'input et le cache pondérés par les prix, est une extension de méthode à déclarer. L'export ne contient pas de nombre de requêtes.

Sheet Données
A1: date | B1: username | C1: product | D1: sku | E1: model | F1: quantity | G1: unit-type | H1: applied_cost_per_quantity | I1: gross_amount | J1: discount_amount | K1: net_amount | L1: total_monthly_quota | M1: organization | N1: app_client_id | O1: repository | P1: cost_center_name | Q1: aic_quantity | R1: aic_gross_amount | S1: input | T1: output | U1: cache_read | V1: cache_write | W1: Modele | X1: Jour | Y1: Modele_cle | Z1: Ligne | AA1: Groupe | AB1: F_input_frais | AC1: T_O | AD1: Energie_kWh | AE1: CO2e_kg | AF1: Montant_brut | AG1: Annee | AH1: Mois | AI1: C2_cache_sup_input | AJ1: C4_input_frais_negatif | AK1: C4_CW_sans_tarif
W2: =IF(TData[[#This Row],[date]]="","",IF(LEFT(TRIM(TData[[#This Row],[model]]),5)="Auto:",TRIM(MID(TRIM(TData[[#This Row],[model]]),6,200)),TRIM(TData[[#This Row],[model]]))) | X2: =IF(TData[[#This Row],[date]]="","",IFERROR(IF(ISNUMBER(TData[[#This Row],[date]]),INT(TData[[#This Row],[date]]),DATEVALUE(TData[[#This Row],[date]])),"")) | Y2: =IF(TData[[#This Row],[Modele]]="","",IF(COUNTIFS(M_Nom,TData[[#This Row],[Modele]]&" [ancien tarif]",M_Avant,">"&TData[[#This Row],[Jour]])>0,TData[[#This Row],[Modele]]&" [ancien tarif]",TData[[#This Row],[Modele]])) | Z2: =IF(OR(TData[[#This Row],[Modele_cle]]="",AND(TData[[#This Row],[product]]<>"",ISERROR(SEARCH("copilot",TData[[#This Row],[product]])))),"",IFERROR(MATCH(TData[[#This Row],[Modele_cle]],M_Nom,0),MATCH("(Autre modèle)",M_Nom,0))) | AA2: =IF(TData[[#This Row],[Ligne]]="","",SUBSTITUTE(INDEX(M_Nom,TData[[#This Row],[Ligne]])," [ancien tarif]","")) | AB2: =IF(TData[[#This Row],[Ligne]]="","",MAX(0,N(TData[[#This Row],[input]])-INDEX(M_Delta,TData[[#This Row],[Ligne]])*N(TData[[#This Row],[cache_read]])-INDEX(M_Eps,TData[[#This Row],[Ligne]])*N(TData[[#This Row],[cache_write]]))) | AC2: =IF(TData[[#This Row],[Ligne]]="","",TData[[#This Row],[F_input_frais]]*INDEX(M_sI,TData[[#This Row],[Ligne]])+N(TData[[#This Row],[cache_read]])*INDEX(M_sCR,TData[[#This Row],[Ligne]])+N(TData[[#This Row],[cache_write]])*INDEX(M_sCW,TData[[#This Row],[Ligne]])+N(TData[[#This Row],[output]])) | AD2: =IF(TData[[#This Row],[Ligne]]="","",TData[[#This Row],[T_O]]*INDEX(M_eO,TData[[#This Row],[Ligne]])*INDEX(M_PUE,TData[[#This Row],[Ligne]])/1000) | AE2: =IF(TData[[#This Row],[Ligne]]="","",TData[[#This Row],[T_O]]*INDEX(M_FE,TData[[#This Row],[Ligne]])) | AF2: =IF(TData[[#This Row],[date]]="","",IF(ISNUMBER(TData[[#This Row],[gross_amount]]),TData[[#This Row],[gross_amount]],IFERROR(VALUE(SUBSTITUTE(TData[[#This Row],[gross_amount]],".",MID(1/2,2,1))),0))) | AG2: =IF(TData[[#This Row],[Jour]]="","",YEAR(TData[[#This Row],[Jour]])) | AH2: =IF(TData[[#This Row],[Jour]]="","",MONTH(TData[[#This Row],[Jour]])) | AI2: =IF(TData[[#This Row],[Ligne]]="","",IF(N(TData[[#This Row],[cache_read]])+N(TData[[#This Row],[cache_write]])>N(TData[[#This Row],[input]]),1,0)) | AJ2: =IF(TData[[#This Row],[Ligne]]="","",IF(N(TData[[#This Row],[input]])-INDEX(M_Delta,TData[[#This Row],[Ligne]])*N(TData[[#This Row],[cache_read]])-INDEX(M_Eps,TData[[#This Row],[Ligne]])*N(TData[[#This Row],[cache_write]])<0,1,0)) | AK2: =IF(TData[[#This Row],[Ligne]]="","",IF(AND(N(TData[[#This Row],[cache_write]])>0,INDEX(M_PCW,TData[[#This Row],[Ligne]])="",N(INDEX(M_PO,TData[[#This Row],[Ligne]]))>0),1,0))

Sheet Interne
B2: Calculs intermédiaires (ne pas modifier)
J3: Rang | K3: Top modèle | L3: Ligne
B4: Données présentes | C4: =COUNT(D_Jour)>0 -> FALSE | J4: 1 | K4: =IF(INDEX(I_CO2,L4)>0,INDEX(I_Nom,L4),"") | L4: =MATCH(LARGE(I_Key,J4),I_Key,0) -> 1
B5: Dernier jour de données | C5: =IF(S_Has,MAX(D_Jour),DATE(S_An,1,1)) -> 46023 | J5: 2 | K5: =IF(INDEX(I_CO2,L5)>0,INDEX(I_Nom,L5),"") | L5: =MATCH(LARGE(I_Key,J5),I_Key,0) -> 2
B6: Premier jour de données | C6: =IF(S_Has,MIN(D_Jour),DATE(S_An,1,1)) -> 46023 | J6: 3 | K6: =IF(INDEX(I_CO2,L6)>0,INDEX(I_Nom,L6),"") | L6: =MATCH(LARGE(I_Key,J6),I_Key,0) -> 3
B7: Année en cours (projection active) | C7: =AND(S_Has,YEAR(S_Last)=S_An,S_Last<DATE(S_An,12,31)) -> FALSE | J7: 4 | K7: =IF(INDEX(I_CO2,L7)>0,INDEX(I_Nom,L7),"") | L7: =MATCH(LARGE(I_Key,J7),I_Key,0) -> 4
B8: Rythme projeté (kgCO₂e/jour) | C8: =IF(S_Has,SUMIFS(D_CO2,D_Jour,">"&(S_Last-P_N),D_Jour,"<="&S_Last)/MAX(1,P_N)*(1+P_Adj),0) -> 0 | J8: 5 | K8: =IF(INDEX(I_CO2,L8)>0,INDEX(I_Nom,L8),"") | L8: =MATCH(LARGE(I_Key,J8),I_Key,0) -> 5
B9: Émissions de l'année (kg) | C9: =SUMIFS(D_CO2,D_An,S_An) -> 0 | J9: 6 | K9: =IF(INDEX(I_CO2,L9)>0,INDEX(I_Nom,L9),"") | L9: =MATCH(LARGE(I_Key,J9),I_Key,0) -> 6
B10: Jours restants projetés | C10: =IF(S_Cur,DATE(S_An,12,31)-S_Last,0) -> 0 | J10: 7 | K10: =IF(INDEX(I_CO2,L10)>0,INDEX(I_Nom,L10),"") | L10: =MATCH(LARGE(I_Key,J10),I_Key,0) -> 7
B11: Atterrissage fin d'année (kg) | C11: =S_YTD+S_Rate*S_Rest -> 0 | J11: 8 | K11: =IF(INDEX(I_CO2,L11)>0,INDEX(I_Nom,L11),"") | L11: =MATCH(LARGE(I_Key,J11),I_Key,0) -> 8
B12: Date de coupure comparaisons | C12: =IF(S_Cur,S_Last,DATE(S_An,12,31)) -> 46387
B13: Année, jusqu'à la coupure (kg) | C13: =SUMIFS(D_CO2,D_Jour,">="&DATE(S_An,1,1),D_Jour,"<="&S_Cut) -> 0
B14: Année précédente, même période (kg) | C14: =SUMIFS(D_CO2,D_Jour,">="&DATE(S_An-1,1,1),D_Jour,"<="&EDATE(S_Cut,-12)) -> 0
B15: Fin du dernier mois complet | C15: =IF(S_Cur,IF(S_Last=EOMONTH(S_Last,0),S_Last,EOMONTH(S_Last,-1)),DATE(S_An,12,31)) -> 46387
B16: Dernier mois complet (kg) | C16: =IF(S_LCM<DATE(S_An,1,1),0,SUMIFS(D_CO2,D_Jour,">"&EOMONTH(S_LCM,-1),D_Jour,"<="&S_LCM)) -> 0
B17: Même mois, année précédente (kg) | C17: =SUMIFS(D_CO2,D_Jour,">"&EOMONTH(S_LCM,-13),D_Jour,"<="&EOMONTH(S_LCM,-12)) -> 0
B18: Année précédente complète (kg) | C18: =SUMIFS(D_CO2,D_An,S_An-1) -> 0
B19: Tokens éq. output de l'année | C19: =SUMIFS(D_TO,D_An,S_An) -> 0
B20: Énergie de l'année (kWh) | C20: =SUMIFS(D_kWh,D_An,S_An) -> 0
B21: Coût brut de l'année ($) | C21: =SUMIFS(D_Brut,D_An,S_An) -> 0
B22: Lignes de l'année | C22: =COUNTIFS(D_An,S_An) -> 0
B24: Agrégats par modèle (alignés ligne à ligne sur la table des modèles de Calcul) et série quotidienne de l'année affichée.
B29: Modèle | C29: kgCO₂e année | D29: kWh année | E29: T_O année | F29: Coût brut année | G29: Clé de tri | H29: T_O toutes années | J29: Jour | K29: kgCO₂e
B30: =IF(Calcul!B30="","",Calcul!B30) -> GPT-5.3-Codex | C30: =IF(B30="",0,SUMIFS(D_CO2,D_Grp,B30,D_An,S_An)) -> 0 | D30: =IF(B30="",0,SUMIFS(D_kWh,D_Grp,B30,D_An,S_An)) -> 0 | E30: =IF(B30="",0,SUMIFS(D_TO,D_Grp,B30,D_An,S_An)) -> 0 | F30: =IF(B30="",0,SUMIFS(D_Brut,D_Grp,B30,D_An,S_An)) -> 0 | G30: =IF(B30="",-1,C30)-ROW()*1E-12 -> -3e-11 | H30: =IF(B30="",0,SUMIFS(D_TO,D_Grp,B30)) -> 0 | J30: =DATE(S_An,1,1)+0 -> 46023 | K30: =SUMIFS(D_CO2,D_Jour,J30) -> 0
B31: =IF(Calcul!B31="","",Calcul!B31) -> GPT-5.4 nano | C31: =IF(B31="",0,SUMIFS(D_CO2,D_Grp,B31,D_An,S_An)) -> 0 | D31: =IF(B31="",0,SUMIFS(D_kWh,D_Grp,B31,D_An,S_An)) -> 0 | E31: =IF(B31="",0,SUMIFS(D_TO,D_Grp,B31,D_An,S_An)) -> 0 | F31: =IF(B31="",0,SUMIFS(D_Brut,D_Grp,B31,D_An,S_An)) -> 0 | G31: =IF(B31="",-1,C31)-ROW()*1E-12 -> -3.1e-11 | H31: =IF(B31="",0,SUMIFS(D_TO,D_Grp,B31)) -> 0 | J31: =DATE(S_An,1,1)+1 -> 46024 | K31: =SUMIFS(D_CO2,D_Jour,J31) -> 0
B32: =IF(Calcul!B32="","",Calcul!B32) -> GPT-5.6 Luna | C32: =IF(B32="",0,SUMIFS(D_CO2,D_Grp,B32,D_An,S_An)) -> 0 | D32: =IF(B32="",0,SUMIFS(D_kWh,D_Grp,B32,D_An,S_An)) -> 0 | E32: =IF(B32="",0,SUMIFS(D_TO,D_Grp,B32,D_An,S_An)) -> 0 | F32: =IF(B32="",0,SUMIFS(D_Brut,D_Grp,B32,D_An,S_An)) -> 0 | G32: =IF(B32="",-1,C32)-ROW()*1E-12 -> -3.2e-11 | H32: =IF(B32="",0,SUMIFS(D_TO,D_Grp,B32)) -> 0 | J32: =DATE(S_An,1,1)+2 -> 46025 | K32: =SUMIFS(D_CO2,D_Jour,J32) -> 0
B33: =IF(Calcul!B33="","",Calcul!B33) -> GPT-5.6 Terra | C33: =IF(B33="",0,SUMIFS(D_CO2,D_Grp,B33,D_An,S_An)) -> 0 | D33: =IF(B33="",0,SUMIFS(D_kWh,D_Grp,B33,D_An,S_An)) -> 0 | E33: =IF(B33="",0,SUMIFS(D_TO,D_Grp,B33,D_An,S_An)) -> 0 | F33: =IF(B33="",0,SUMIFS(D_Brut,D_Grp,B33,D_An,S_An)) -> 0 | G33: =IF(B33="",-1,C33)-ROW()*1E-12 -> -3.3e-11 | H33: =IF(B33="",0,SUMIFS(D_TO,D_Grp,B33)) -> 0 | J33: =DATE(S_An,1,1)+3 -> 46026 | K33: =SUMIFS(D_CO2,D_Jour,J33) -> 0
B34: =IF(Calcul!B34="","",Calcul!B34) -> GPT-5.6 Sol | C34: =IF(B34="",0,SUMIFS(D_CO2,D_Grp,B34,D_An,S_An)) -> 0 | D34: =IF(B34="",0,SUMIFS(D_kWh,D_Grp,B34,D_An,S_An)) -> 0 | E34: =IF(B34="",0,SUMIFS(D_TO,D_Grp,B34,D_An,S_An)) -> 0 | F34: =IF(B34="",0,SUMIFS(D_Brut,D_Grp,B34,D_An,S_An)) -> 0 | G34: =IF(B34="",-1,C34)-ROW()*1E-12 -> -3.4e-11 | H34: =IF(B34="",0,SUMIFS(D_TO,D_Grp,B34)) -> 0 | J34: =DATE(S_An,1,1)+4 -> 46027 | K34: =SUMIFS(D_CO2,D_Jour,J34) -> 0
B35: =IF(Calcul!B35="","",Calcul!B35) -> GPT-6 Luna | C35: =IF(B35="",0,SUMIFS(D_CO2,D_Grp,B35,D_An,S_An)) -> 0 | D35: =IF(B35="",0,SUMIFS(D_kWh,D_Grp,B35,D_An,S_An)) -> 0 | E35: =IF(B35="",0,SUMIFS(D_TO,D_Grp,B35,D_An,S_An)) -> 0 | F35: =IF(B35="",0,SUMIFS(D_Brut,D_Grp,B35,D_An,S_An)) -> 0 | G35: =IF(B35="",-1,C35)-ROW()*1E-12 -> -3.5e-11 | H35: =IF(B35="",0,SUMIFS(D_TO,D_Grp,B35)) -> 0 | J35: =DATE(S_An,1,1)+5 -> 46028 | K35: =SUMIFS(D_CO2,D_Jour,J35) -> 0
B36: =IF(Calcul!B36="","",Calcul!B36) -> GPT-6 Sol | C36: =IF(B36="",0,SUMIFS(D_CO2,D_Grp,B36,D_An,S_An)) -> 0 | D36: =IF(B36="",0,SUMIFS(D_kWh,D_Grp,B36,D_An,S_An)) -> 0 | E36: =IF(B36="",0,SUMIFS(D_TO,D_Grp,B36,D_An,S_An)) -> 0 | F36: =IF(B36="",0,SUMIFS(D_Brut,D_Grp,B36,D_An,S_An)) -> 0 | G36: =IF(B36="",-1,C36)-ROW()*1E-12 -> -3.6e-11 | H36: =IF(B36="",0,SUMIFS(D_TO,D_Grp,B36)) -> 0 | J36: =DATE(S_An,1,1)+6 -> 46029 | K36: =SUMIFS(D_CO2,D_Jour,J36) -> 0
B37: =IF(Calcul!B37="","",Calcul!B37) -> GPT-6 Astra | C37: =IF(B37="",0,SUMIFS(D_CO2,D_Grp,B37,D_An,S_An)) -> 0 | D37: =IF(B37="",0,SUMIFS(D_kWh,D_Grp,B37,D_An,S_An)) -> 0 | E37: =IF(B37="",0,SUMIFS(D_TO,D_Grp,B37,D_An,S_An)) -> 0 | F37: =IF(B37="",0,SUMIFS(D_Brut,D_Grp,B37,D_An,S_An)) -> 0 | G37: =IF(B37="",-1,C37)-ROW()*1E-12 -> -3.7e-11 | H37: =IF(B37="",0,SUMIFS(D_TO,D_Grp,B37)) -> 0 | J37: =DATE(S_An,1,1)+7 -> 46030 | K37: =SUMIFS(D_CO2,D_Jour,J37) -> 0
B38: =IF(Calcul!B38="","",Calcul!B38) -> GPT-6.1 Sol | C38: =IF(B38="",0,SUMIFS(D_CO2,D_Grp,B38,D_An,S_An)) -> 0 | D38: =IF(B38="",0,SUMIFS(D_kWh,D_Grp,B38,D_An,S_An)) -> 0 | E38: =IF(B38="",0,SUMIFS(D_TO,D_Grp,B38,D_An,S_An)) -> 0 | F38: =IF(B38="",0,SUMIFS(D_Brut,D_Grp,B38,D_An,S_An)) -> 0 | G38: =IF(B38="",-1,C38)-ROW()*1E-12 -> -3.8e-11 | H38: =IF(B38="",0,SUMIFS(D_TO,D_Grp,B38)) -> 0 | J38: =DATE(S_An,1,1)+8 -> 46031 | K38: =SUMIFS(D_CO2,D_Jour,J38) -> 0
B39: =IF(Calcul!B39="","",Calcul!B39) -> GPT-5 mini | C39: =IF(B39="",0,SUMIFS(D_CO2,D_Grp,B39,D_An,S_An)) -> 0 | D39: =IF(B39="",0,SUMIFS(D_kWh,D_Grp,B39,D_An,S_An)) -> 0 | E39: =IF(B39="",0,SUMIFS(D_TO,D_Grp,B39,D_An,S_An)) -> 0 | F39: =IF(B39="",0,SUMIFS(D_Brut,D_Grp,B39,D_An,S_An)) -> 0 | G39: =IF(B39="",-1,C39)-ROW()*1E-12 -> -3.9e-11 | H39: =IF(B39="",0,SUMIFS(D_TO,D_Grp,B39)) -> 0 | J39: =DATE(S_An,1,1)+9 -> 46032 | K39: =SUMIFS(D_CO2,D_Jour,J39) -> 0
B40: =IF(Calcul!B40="","",Calcul!B40) -> GPT-5.4 mini | C40: =IF(B40="",0,SUMIFS(D_CO2,D_Grp,B40,D_An,S_An)) -> 0 | D40: =IF(B40="",0,SUMIFS(D_kWh,D_Grp,B40,D_An,S_An)) -> 0 | E40: =IF(B40="",0,SUMIFS(D_TO,D_Grp,B40,D_An,S_An)) -> 0 | F40: =IF(B40="",0,SUMIFS(D_Brut,D_Grp,B40,D_An,S_An)) -> 0 | G40: =IF(B40="",-1,C40)-ROW()*1E-12 -> -4e-11 | H40: =IF(B40="",0,SUMIFS(D_TO,D_Grp,B40)) -> 0 | J40: =DATE(S_An,1,1)+10 -> 46033 | K40: =SUMIFS(D_CO2,D_Jour,J40) -> 0
B41: =IF(Calcul!B41="","",Calcul!B41) -> GPT-5.4 | C41: =IF(B41="",0,SUMIFS(D_CO2,D_Grp,B41,D_An,S_An)) -> 0 | D41: =IF(B41="",0,SUMIFS(D_kWh,D_Grp,B41,D_An,S_An)) -> 0 | E41: =IF(B41="",0,SUMIFS(D_TO,D_Grp,B41,D_An,S_An)) -> 0 | F41: =IF(B41="",0,SUMIFS(D_Brut,D_Grp,B41,D_An,S_An)) -> 0 | G41: =IF(B41="",-1,C41)-ROW()*1E-12 -> -4.1e-11 | H41: =IF(B41="",0,SUMIFS(D_TO,D_Grp,B41)) -> 0 | J41: =DATE(S_An,1,1)+11 -> 46034 | K41: =SUMIFS(D_CO2,D_Jour,J41) -> 0
B42: =IF(Calcul!B42="","",Calcul!B42) -> GPT-5.5 | C42: =IF(B42="",0,SUMIFS(D_CO2,D_Grp,B42,D_An,S_An)) -> 0 | D42: =IF(B42="",0,SUMIFS(D_kWh,D_Grp,B42,D_An,S_An)) -> 0 | E42: =IF(B42="",0,SUMIFS(D_TO,D_Grp,B42,D_An,S_An)) -> 0 | F42: =IF(B42="",0,SUMIFS(D_Brut,D_Grp,B42,D_An,S_An)) -> 0 | G42: =IF(B42="",-1,C42)-ROW()*1E-12 -> -4.2e-11 | H42: =IF(B42="",0,SUMIFS(D_TO,D_Grp,B42)) -> 0 | J42: =DATE(S_An,1,1)+12 -> 46035 | K42: =SUMIFS(D_CO2,D_Jour,J42) -> 0
B43: =IF(Calcul!B43="","",Calcul!B43) -> Claude Haiku 4.5 | C43: =IF(B43="",0,SUMIFS(D_CO2,D_Grp,B43,D_An,S_An)) -> 0 | D43: =IF(B43="",0,SUMIFS(D_kWh,D_Grp,B43,D_An,S_An)) -> 0 | E43: =IF(B43="",0,SUMIFS(D_TO,D_Grp,B43,D_An,S_An)) -> 0 | F43: =IF(B43="",0,SUMIFS(D_Brut,D_Grp,B43,D_An,S_An)) -> 0 | G43: =IF(B43="",-1,C43)-ROW()*1E-12 -> -4.3e-11 | H43: =IF(B43="",0,SUMIFS(D_TO,D_Grp,B43)) -> 0 | J43: =DATE(S_An,1,1)+13 -> 46036 | K43: =SUMIFS(D_CO2,D_Jour,J43) -> 0
B44: =IF(Calcul!B44="","",Calcul!B44) -> Claude Haiku 5.5 | C44: =IF(B44="",0,SUMIFS(D_CO2,D_Grp,B44,D_An,S_An)) -> 0 | D44: =IF(B44="",0,SUMIFS(D_kWh,D_Grp,B44,D_An,S_An)) -> 0 | E44: =IF(B44="",0,SUMIFS(D_TO,D_Grp,B44,D_An,S_An)) -> 0 | F44: =IF(B44="",0,SUMIFS(D_Brut,D_Grp,B44,D_An,S_An)) -> 0 | G44: =IF(B44="",-1,C44)-ROW()*1E-12 -> -4.4e-11 | H44: =IF(B44="",0,SUMIFS(D_TO,D_Grp,B44)) -> 0 | J44: =DATE(S_An,1,1)+14 -> 46037 | K44: =SUMIFS(D_CO2,D_Jour,J44) -> 0
B45: =IF(Calcul!B45="","",Calcul!B45) -> Claude Sonnet 4 | C45: =IF(B45="",0,SUMIFS(D_CO2,D_Grp,B45,D_An,S_An)) -> 0 | D45: =IF(B45="",0,SUMIFS(D_kWh,D_Grp,B45,D_An,S_An)) -> 0 | E45: =IF(B45="",0,SUMIFS(D_TO,D_Grp,B45,D_An,S_An)) -> 0 | F45: =IF(B45="",0,SUMIFS(D_Brut,D_Grp,B45,D_An,S_An)) -> 0 | G45: =IF(B45="",-1,C45)-ROW()*1E-12 -> -4.5e-11 | H45: =IF(B45="",0,SUMIFS(D_TO,D_Grp,B45)) -> 0 | J45: =DATE(S_An,1,1)+15 -> 46038 | K45: =SUMIFS(D_CO2,D_Jour,J45) -> 0
B46: =IF(Calcul!B46="","",Calcul!B46) -> Claude Sonnet 4.6 | C46: =IF(B46="",0,SUMIFS(D_CO2,D_Grp,B46,D_An,S_An)) -> 0 | D46: =IF(B46="",0,SUMIFS(D_kWh,D_Grp,B46,D_An,S_An)) -> 0 | E46: =IF(B46="",0,SUMIFS(D_TO,D_Grp,B46,D_An,S_An)) -> 0 | F46: =IF(B46="",0,SUMIFS(D_Brut,D_Grp,B46,D_An,S_An)) -> 0 | G46: =IF(B46="",-1,C46)-ROW()*1E-12 -> -4.6e-11 | H46: =IF(B46="",0,SUMIFS(D_TO,D_Grp,B46)) -> 0 | J46: =DATE(S_An,1,1)+16 -> 46039 | K46: =SUMIFS(D_CO2,D_Jour,J46) -> 0
B47: =IF(Calcul!B47="","",Calcul!B47) -> Claude Sonnet 5 | C47: =IF(B47="",0,SUMIFS(D_CO2,D_Grp,B47,D_An,S_An)) -> 0 | D47: =IF(B47="",0,SUMIFS(D_kWh,D_Grp,B47,D_An,S_An)) -> 0 | E47: =IF(B47="",0,SUMIFS(D_TO,D_Grp,B47,D_An,S_An)) -> 0 | F47: =IF(B47="",0,SUMIFS(D_Brut,D_Grp,B47,D_An,S_An)) -> 0 | G47: =IF(B47="",-1,C47)-ROW()*1E-12 -> -4.7e-11 | H47: =IF(B47="",0,SUMIFS(D_TO,D_Grp,B47)) -> 0 | J47: =DATE(S_An,1,1)+17 -> 46040 | K47: =SUMIFS(D_CO2,D_Jour,J47) -> 0
B48: =IF(Calcul!B48="","",Calcul!B48) -> Claude Sonnet 5.5 | C48: =IF(B48="",0,SUMIFS(D_CO2,D_Grp,B48,D_An,S_An)) -> 0 | D48: =IF(B48="",0,SUMIFS(D_kWh,D_Grp,B48,D_An,S_An)) -> 0 | E48: =IF(B48="",0,SUMIFS(D_TO,D_Grp,B48,D_An,S_An)) -> 0 | F48: =IF(B48="",0,SUMIFS(D_Brut,D_Grp,B48,D_An,S_An)) -> 0 | G48: =IF(B48="",-1,C48)-ROW()*1E-12 -> -4.8e-11 | H48: =IF(B48="",0,SUMIFS(D_TO,D_Grp,B48)) -> 0 | J48: =DATE(S_An,1,1)+18 -> 46041 | K48: =SUMIFS(D_CO2,D_Jour,J48) -> 0
B49: =IF(Calcul!B49="","",Calcul!B49) -> Claude Sonnet 5.5 [ancien tarif] | C49: =IF(B49="",0,SUMIFS(D_CO2,D_Grp,B49,D_An,S_An)) -> 0 | D49: =IF(B49="",0,SUMIFS(D_kWh,D_Grp,B49,D_An,S_An)) -> 0 | E49: =IF(B49="",0,SUMIFS(D_TO,D_Grp,B49,D_An,S_An)) -> 0 | F49: =IF(B49="",0,SUMIFS(D_Brut,D_Grp,B49,D_An,S_An)) -> 0 | G49: =IF(B49="",-1,C49)-ROW()*1E-12 -> -4.9e-11 | H49: =IF(B49="",0,SUMIFS(D_TO,D_Grp,B49)) -> 0 | J49: =DATE(S_An,1,1)+19 -> 46042 | K49: =SUMIFS(D_CO2,D_Jour,J49) -> 0
B50: =IF(Calcul!B50="","",Calcul!B50) -> Claude Opus 4.8 | C50: =IF(B50="",0,SUMIFS(D_CO2,D_Grp,B50,D_An,S_An)) -> 0 | D50: =IF(B50="",0,SUMIFS(D_kWh,D_Grp,B50,D_An,S_An)) -> 0 | E50: =IF(B50="",0,SUMIFS(D_TO,D_Grp,B50,D_An,S_An)) -> 0 | F50: =IF(B50="",0,SUMIFS(D_Brut,D_Grp,B50,D_An,S_An)) -> 0 | G50: =IF(B50="",-1,C50)-ROW()*1E-12 -> -5e-11 | H50: =IF(B50="",0,SUMIFS(D_TO,D_Grp,B50)) -> 0 | J50: =DATE(S_An,1,1)+20 -> 46043 | K50: =SUMIFS(D_CO2,D_Jour,J50) -> 0
B51: =IF(Calcul!B51="","",Calcul!B51) -> Claude Opus 4.8 (fast mode) | C51: =IF(B51="",0,SUMIFS(D_CO2,D_Grp,B51,D_An,S_An)) -> 0 | D51: =IF(B51="",0,SUMIFS(D_kWh,D_Grp,B51,D_An,S_An)) -> 0 | E51: =IF(B51="",0,SUMIFS(D_TO,D_Grp,B51,D_An,S_An)) -> 0 | F51: =IF(B51="",0,SUMIFS(D_Brut,D_Grp,B51,D_An,S_An)) -> 0 | G51: =IF(B51="",-1,C51)-ROW()*1E-12 -> -5.1e-11 | H51: =IF(B51="",0,SUMIFS(D_TO,D_Grp,B51)) -> 0 | J51: =DATE(S_An,1,1)+21 -> 46044 | K51: =SUMIFS(D_CO2,D_Jour,J51) -> 0
B52: =IF(Calcul!B52="","",Calcul!B52) -> Claude Opus 5 | C52: =IF(B52="",0,SUMIFS(D_CO2,D_Grp,B52,D_An,S_An)) -> 0 | D52: =IF(B52="",0,SUMIFS(D_kWh,D_Grp,B52,D_An,S_An)) -> 0 | E52: =IF(B52="",0,SUMIFS(D_TO,D_Grp,B52,D_An,S_An)) -> 0 | F52: =IF(B52="",0,SUMIFS(D_Brut,D_Grp,B52,D_An,S_An)) -> 0 | G52: =IF(B52="",-1,C52)-ROW()*1E-12 -> -5.2e-11 | H52: =IF(B52="",0,SUMIFS(D_TO,D_Grp,B52)) -> 0 | J52: =DATE(S_An,1,1)+22 -> 46045 | K52: =SUMIFS(D_CO2,D_Jour,J52) -> 0
B53: =IF(Calcul!B53="","",Calcul!B53) -> Claude Opus 5.5 | C53: =IF(B53="",0,SUMIFS(D_CO2,D_Grp,B53,D_An,S_An)) -> 0 | D53: =IF(B53="",0,SUMIFS(D_kWh,D_Grp,B53,D_An,S_An)) -> 0 | E53: =IF(B53="",0,SUMIFS(D_TO,D_Grp,B53,D_An,S_An)) -> 0 | F53: =IF(B53="",0,SUMIFS(D_Brut,D_Grp,B53,D_An,S_An)) -> 0 | G53: =IF(B53="",-1,C53)-ROW()*1E-12 -> -5.3e-11 | H53: =IF(B53="",0,SUMIFS(D_TO,D_Grp,B53)) -> 0 | J53: =DATE(S_An,1,1)+23 -> 46046 | K53: =SUMIFS(D_CO2,D_Jour,J53) -> 0
B54: =IF(Calcul!B54="","",Calcul!B54) -> Claude Fable 5 | C54: =IF(B54="",0,SUMIFS(D_CO2,D_Grp,B54,D_An,S_An)) -> 0 | D54: =IF(B54="",0,SUMIFS(D_kWh,D_Grp,B54,D_An,S_An)) -> 0 | E54: =IF(B54="",0,SUMIFS(D_TO,D_Grp,B54,D_An,S_An)) -> 0 | F54: =IF(B54="",0,SUMIFS(D_Brut,D_Grp,B54,D_An,S_An)) -> 0 | G54: =IF(B54="",-1,C54)-ROW()*1E-12 -> -5.4e-11 | H54: =IF(B54="",0,SUMIFS(D_TO,D_Grp,B54)) -> 0 | J54: =DATE(S_An,1,1)+24 -> 46047 | K54: =SUMIFS(D_CO2,D_Jour,J54) -> 0
B55: =IF(Calcul!B55="","",Calcul!B55) -> Claude Fable 5.1 | C55: =IF(B55="",0,SUMIFS(D_CO2,D_Grp,B55,D_An,S_An)) -> 0 | D55: =IF(B55="",0,SUMIFS(D_kWh,D_Grp,B55,D_An,S_An)) -> 0 | E55: =IF(B55="",0,SUMIFS(D_TO,D_Grp,B55,D_An,S_An)) -> 0 | F55: =IF(B55="",0,SUMIFS(D_Brut,D_Grp,B55,D_An,S_An)) -> 0 | G55: =IF(B55="",-1,C55)-ROW()*1E-12 -> -5.5e-11 | H55: =IF(B55="",0,SUMIFS(D_TO,D_Grp,B55)) -> 0 | J55: =DATE(S_An,1,1)+25 -> 46048 | K55: =SUMIFS(D_CO2,D_Jour,J55) -> 0
B56: =IF(Calcul!B56="","",Calcul!B56) -> Gemini 3.8 Flash | C56: =IF(B56="",0,SUMIFS(D_CO2,D_Grp,B56,D_An,S_An)) -> 0 | D56: =IF(B56="",0,SUMIFS(D_kWh,D_Grp,B56,D_An,S_An)) -> 0 | E56: =IF(B56="",0,SUMIFS(D_TO,D_Grp,B56,D_An,S_An)) -> 0 | F56: =IF(B56="",0,SUMIFS(D_Brut,D_Grp,B56,D_An,S_An)) -> 0 | G56: =IF(B56="",-1,C56)-ROW()*1E-12 -> -5.6e-11 | H56: =IF(B56="",0,SUMIFS(D_TO,D_Grp,B56)) -> 0 | J56: =DATE(S_An,1,1)+26 -> 46049 | K56: =SUMIFS(D_CO2,D_Jour,J56) -> 0
B57: =IF(Calcul!B57="","",Calcul!B57) -> Gemini 4 Argon | C57: =IF(B57="",0,SUMIFS(D_CO2,D_Grp,B57,D_An,S_An)) -> 0 | D57: =IF(B57="",0,SUMIFS(D_kWh,D_Grp,B57,D_An,S_An)) -> 0 | E57: =IF(B57="",0,SUMIFS(D_TO,D_Grp,B57,D_An,S_An)) -> 0 | F57: =IF(B57="",0,SUMIFS(D_Brut,D_Grp,B57,D_An,S_An)) -> 0 | G57: =IF(B57="",-1,C57)-ROW()*1E-12 -> -5.7e-11 | H57: =IF(B57="",0,SUMIFS(D_TO,D_Grp,B57)) -> 0 | J57: =DATE(S_An,1,1)+27 -> 46050 | K57: =SUMIFS(D_CO2,D_Jour,J57) -> 0
B58: =IF(Calcul!B58="","",Calcul!B58) -> Gemini 3.7 Flash | C58: =IF(B58="",0,SUMIFS(D_CO2,D_Grp,B58,D_An,S_An)) -> 0 | D58: =IF(B58="",0,SUMIFS(D_kWh,D_Grp,B58,D_An,S_An)) -> 0 | E58: =IF(B58="",0,SUMIFS(D_TO,D_Grp,B58,D_An,S_An)) -> 0 | F58: =IF(B58="",0,SUMIFS(D_Brut,D_Grp,B58,D_An,S_An)) -> 0 | G58: =IF(B58="",-1,C58)-ROW()*1E-12 -> -5.8e-11 | H58: =IF(B58="",0,SUMIFS(D_TO,D_Grp,B58)) -> 0 | J58: =DATE(S_An,1,1)+28 -> 46051 | K58: =SUMIFS(D_CO2,D_Jour,J58) -> 0
B59: =IF(Calcul!B59="","",Calcul!B59) -> Gemini 3.5 Flash | C59: =IF(B59="",0,SUMIFS(D_CO2,D_Grp,B59,D_An,S_An)) -> 0 | D59: =IF(B59="",0,SUMIFS(D_kWh,D_Grp,B59,D_An,S_An)) -> 0 | E59: =IF(B59="",0,SUMIFS(D_TO,D_Grp,B59,D_An,S_An)) -> 0 | F59: =IF(B59="",0,SUMIFS(D_Brut,D_Grp,B59,D_An,S_An)) -> 0 | G59: =IF(B59="",-1,C59)-ROW()*1E-12 -> -5.9e-11 | H59: =IF(B59="",0,SUMIFS(D_TO,D_Grp,B59)) -> 0 | J59: =DATE(S_An,1,1)+29 -> 46052 | K59: =SUMIFS(D_CO2,D_Jour,J59) -> 0
B60: =IF(Calcul!B60="","",Calcul!B60) -> MAI-Code-1.1-Flash | C60: =IF(B60="",0,SUMIFS(D_CO2,D_Grp,B60,D_An,S_An)) -> 0 | D60: =IF(B60="",0,SUMIFS(D_kWh,D_Grp,B60,D_An,S_An)) -> 0 | E60: =IF(B60="",0,SUMIFS(D_TO,D_Grp,B60,D_An,S_An)) -> 0 | F60: =IF(B60="",0,SUMIFS(D_Brut,D_Grp,B60,D_An,S_An)) -> 0 | G60: =IF(B60="",-1,C60)-ROW()*1E-12 -> -6e-11 | H60: =IF(B60="",0,SUMIFS(D_TO,D_Grp,B60)) -> 0 | J60: =DATE(S_An,1,1)+30 -> 46053 | K60: =SUMIFS(D_CO2,D_Jour,J60) -> 0
B61: =IF(Calcul!B61="","",Calcul!B61) -> Grok 4.5 | C61: =IF(B61="",0,SUMIFS(D_CO2,D_Grp,B61,D_An,S_An)) -> 0 | D61: =IF(B61="",0,SUMIFS(D_kWh,D_Grp,B61,D_An,S_An)) -> 0 | E61: =IF(B61="",0,SUMIFS(D_TO,D_Grp,B61,D_An,S_An)) -> 0 | F61: =IF(B61="",0,SUMIFS(D_Brut,D_Grp,B61,D_An,S_An)) -> 0 | G61: =IF(B61="",-1,C61)-ROW()*1E-12 -> -6.1e-11 | H61: =IF(B61="",0,SUMIFS(D_TO,D_Grp,B61)) -> 0 | J61: =DATE(S_An,1,1)+31 -> 46054 | K61: =SUMIFS(D_CO2,D_Jour,J61) -> 0
B62: =IF(Calcul!B62="","",Calcul!B62) -> Grok 4.6 | C62: =IF(B62="",0,SUMIFS(D_CO2,D_Grp,B62,D_An,S_An)) -> 0 | D62: =IF(B62="",0,SUMIFS(D_kWh,D_Grp,B62,D_An,S_An)) -> 0 | E62: =IF(B62="",0,SUMIFS(D_TO,D_Grp,B62,D_An,S_An)) -> 0 | F62: =IF(B62="",0,SUMIFS(D_Brut,D_Grp,B62,D_An,S_An)) -> 0 | G62: =IF(B62="",-1,C62)-ROW()*1E-12 -> -6.2e-11 | H62: =IF(B62="",0,SUMIFS(D_TO,D_Grp,B62)) -> 0 | J62: =DATE(S_An,1,1)+32 -> 46055 | K62: =SUMIFS(D_CO2,D_Jour,J62) -> 0
B63: =IF(Calcul!B63="","",Calcul!B63) -> Grok 4.7 | C63: =IF(B63="",0,SUMIFS(D_CO2,D_Grp,B63,D_An,S_An)) -> 0 | D63: =IF(B63="",0,SUMIFS(D_kWh,D_Grp,B63,D_An,S_An)) -> 0 | E63: =IF(B63="",0,SUMIFS(D_TO,D_Grp,B63,D_An,S_An)) -> 0 | F63: =IF(B63="",0,SUMIFS(D_Brut,D_Grp,B63,D_An,S_An)) -> 0 | G63: =IF(B63="",-1,C63)-ROW()*1E-12 -> -6.3e-11 | H63: =IF(B63="",0,SUMIFS(D_TO,D_Grp,B63)) -> 0 | J63: =DATE(S_An,1,1)+33 -> 46056 | K63: =SUMIFS(D_CO2,D_Jour,J63) -> 0
B64: =IF(Calcul!B64="","",Calcul!B64) -> Kimi K3 | C64: =IF(B64="",0,SUMIFS(D_CO2,D_Grp,B64,D_An,S_An)) -> 0 | D64: =IF(B64="",0,SUMIFS(D_kWh,D_Grp,B64,D_An,S_An)) -> 0 | E64: =IF(B64="",0,SUMIFS(D_TO,D_Grp,B64,D_An,S_An)) -> 0 | F64: =IF(B64="",0,SUMIFS(D_Brut,D_Grp,B64,D_An,S_An)) -> 0 | G64: =IF(B64="",-1,C64)-ROW()*1E-12 -> -6.4e-11 | H64: =IF(B64="",0,SUMIFS(D_TO,D_Grp,B64)) -> 0 | J64: =DATE(S_An,1,1)+34 -> 46057 | K64: =SUMIFS(D_CO2,D_Jour,J64) -> 0
B65: =IF(Calcul!B65="","",Calcul!B65) -> Claude Opus 4.5 | C65: =IF(B65="",0,SUMIFS(D_CO2,D_Grp,B65,D_An,S_An)) -> 0 | D65: =IF(B65="",0,SUMIFS(D_kWh,D_Grp,B65,D_An,S_An)) -> 0 | E65: =IF(B65="",0,SUMIFS(D_TO,D_Grp,B65,D_An,S_An)) -> 0 | F65: =IF(B65="",0,SUMIFS(D_Brut,D_Grp,B65,D_An,S_An)) -> 0 | G65: =IF(B65="",-1,C65)-ROW()*1E-12 -> -6.5e-11 | H65: =IF(B65="",0,SUMIFS(D_TO,D_Grp,B65)) -> 0 | J65: =DATE(S_An,1,1)+35 -> 46058 | K65: =SUMIFS(D_CO2,D_Jour,J65) -> 0
B66: =IF(Calcul!B66="","",Calcul!B66) -> Claude Opus 4.6 | C66: =IF(B66="",0,SUMIFS(D_CO2,D_Grp,B66,D_An,S_An)) -> 0 | D66: =IF(B66="",0,SUMIFS(D_kWh,D_Grp,B66,D_An,S_An)) -> 0 | E66: =IF(B66="",0,SUMIFS(D_TO,D_Grp,B66,D_An,S_An)) -> 0 | F66: =IF(B66="",0,SUMIFS(D_Brut,D_Grp,B66,D_An,S_An)) -> 0 | G66: =IF(B66="",-1,C66)-ROW()*1E-12 -> -6.6e-11 | H66: =IF(B66="",0,SUMIFS(D_TO,D_Grp,B66)) -> 0 | J66: =DATE(S_An,1,1)+36 -> 46059 | K66: =SUMIFS(D_CO2,D_Jour,J66) -> 0
B67: =IF(Calcul!B67="","",Calcul!B67) -> Claude Opus 4.7 | C67: =IF(B67="",0,SUMIFS(D_CO2,D_Grp,B67,D_An,S_An)) -> 0 | D67: =IF(B67="",0,SUMIFS(D_kWh,D_Grp,B67,D_An,S_An)) -> 0 | E67: =IF(B67="",0,SUMIFS(D_TO,D_Grp,B67,D_An,S_An)) -> 0 | F67: =IF(B67="",0,SUMIFS(D_Brut,D_Grp,B67,D_An,S_An)) -> 0 | G67: =IF(B67="",-1,C67)-ROW()*1E-12 -> -6.7e-11 | H67: =IF(B67="",0,SUMIFS(D_TO,D_Grp,B67)) -> 0 | J67: =DATE(S_An,1,1)+37 -> 46060 | K67: =SUMIFS(D_CO2,D_Jour,J67) -> 0
B68: =IF(Calcul!B68="","",Calcul!B68) -> Claude Sonnet 4.5 | C68: =IF(B68="",0,SUMIFS(D_CO2,D_Grp,B68,D_An,S_An)) -> 0 | D68: =IF(B68="",0,SUMIFS(D_kWh,D_Grp,B68,D_An,S_An)) -> 0 | E68: =IF(B68="",0,SUMIFS(D_TO,D_Grp,B68,D_An,S_An)) -> 0 | F68: =IF(B68="",0,SUMIFS(D_Brut,D_Grp,B68,D_An,S_An)) -> 0 | G68: =IF(B68="",-1,C68)-ROW()*1E-12 -> -6.8e-11 | H68: =IF(B68="",0,SUMIFS(D_TO,D_Grp,B68)) -> 0 | J68: =DATE(S_An,1,1)+38 -> 46061 | K68: =SUMIFS(D_CO2,D_Jour,J68) -> 0
B69: =IF(Calcul!B69="","",Calcul!B69) -> Gemini 2.5 Flash | C69: =IF(B69="",0,SUMIFS(D_CO2,D_Grp,B69,D_An,S_An)) -> 0 | D69: =IF(B69="",0,SUMIFS(D_kWh,D_Grp,B69,D_An,S_An)) -> 0 | E69: =IF(B69="",0,SUMIFS(D_TO,D_Grp,B69,D_An,S_An)) -> 0 | F69: =IF(B69="",0,SUMIFS(D_Brut,D_Grp,B69,D_An,S_An)) -> 0 | G69: =IF(B69="",-1,C69)-ROW()*1E-12 -> -6.9e-11 | H69: =IF(B69="",0,SUMIFS(D_TO,D_Grp,B69)) -> 0 | J69: =DATE(S_An,1,1)+39 -> 46062 | K69: =SUMIFS(D_CO2,D_Jour,J69) -> 0
B70: =IF(Calcul!B70="","",Calcul!B70) -> Gemini 2.5-pro | C70: =IF(B70="",0,SUMIFS(D_CO2,D_Grp,B70,D_An,S_An)) -> 0 | D70: =IF(B70="",0,SUMIFS(D_kWh,D_Grp,B70,D_An,S_An)) -> 0 | E70: =IF(B70="",0,SUMIFS(D_TO,D_Grp,B70,D_An,S_An)) -> 0 | F70: =IF(B70="",0,SUMIFS(D_Brut,D_Grp,B70,D_An,S_An)) -> 0 | G70: =IF(B70="",-1,C70)-ROW()*1E-12 -> -7e-11 | H70: =IF(B70="",0,SUMIFS(D_TO,D_Grp,B70)) -> 0 | J70: =DATE(S_An,1,1)+40 -> 46063 | K70: =SUMIFS(D_CO2,D_Jour,J70) -> 0
B71: =IF(Calcul!B71="","",Calcul!B71) -> gemini-2.5-flash-lite | C71: =IF(B71="",0,SUMIFS(D_CO2,D_Grp,B71,D_An,S_An)) -> 0 | D71: =IF(B71="",0,SUMIFS(D_kWh,D_Grp,B71,D_An,S_An)) -> 0 | E71: =IF(B71="",0,SUMIFS(D_TO,D_Grp,B71,D_An,S_An)) -> 0 | F71: =IF(B71="",0,SUMIFS(D_Brut,D_Grp,B71,D_An,S_An)) -> 0 | G71: =IF(B71="",-1,C71)-ROW()*1E-12 -> -7.1e-11 | H71: =IF(B71="",0,SUMIFS(D_TO,D_Grp,B71)) -> 0 | J71: =DATE(S_An,1,1)+41 -> 46064 | K71: =SUMIFS(D_CO2,D_Jour,J71) -> 0
B72: =IF(Calcul!B72="","",Calcul!B72) -> gemini-2.5-flash-tts | C72: =IF(B72="",0,SUMIFS(D_CO2,D_Grp,B72,D_An,S_An)) -> 0 | D72: =IF(B72="",0,SUMIFS(D_kWh,D_Grp,B72,D_An,S_An)) -> 0 | E72: =IF(B72="",0,SUMIFS(D_TO,D_Grp,B72,D_An,S_An)) -> 0 | F72: =IF(B72="",0,SUMIFS(D_Brut,D_Grp,B72,D_An,S_An)) -> 0 | G72: =IF(B72="",-1,C72)-ROW()*1E-12 -> -7.2e-11 | H72: =IF(B72="",0,SUMIFS(D_TO,D_Grp,B72)) -> 0 | J72: =DATE(S_An,1,1)+42 -> 46065 | K72: =SUMIFS(D_CO2,D_Jour,J72) -> 0
B73: =IF(Calcul!B73="","",Calcul!B73) -> gemini-2.5-pro-tts | C73: =IF(B73="",0,SUMIFS(D_CO2,D_Grp,B73,D_An,S_An)) -> 0 | D73: =IF(B73="",0,SUMIFS(D_kWh,D_Grp,B73,D_An,S_An)) -> 0 | E73: =IF(B73="",0,SUMIFS(D_TO,D_Grp,B73,D_An,S_An)) -> 0 | F73: =IF(B73="",0,SUMIFS(D_Brut,D_Grp,B73,D_An,S_An)) -> 0 | G73: =IF(B73="",-1,C73)-ROW()*1E-12 -> -7.3e-11 | H73: =IF(B73="",0,SUMIFS(D_TO,D_Grp,B73)) -> 0 | J73: =DATE(S_An,1,1)+43 -> 46066 | K73: =SUMIFS(D_CO2,D_Jour,J73) -> 0
B74: =IF(Calcul!B74="","",Calcul!B74) -> GPT 4.1 | C74: =IF(B74="",0,SUMIFS(D_CO2,D_Grp,B74,D_An,S_An)) -> 0 | D74: =IF(B74="",0,SUMIFS(D_kWh,D_Grp,B74,D_An,S_An)) -> 0 | E74: =IF(B74="",0,SUMIFS(D_TO,D_Grp,B74,D_An,S_An)) -> 0 | F74: =IF(B74="",0,SUMIFS(D_Brut,D_Grp,B74,D_An,S_An)) -> 0 | G74: =IF(B74="",-1,C74)-ROW()*1E-12 -> -7.4e-11 | H74: =IF(B74="",0,SUMIFS(D_TO,D_Grp,B74)) -> 0 | J74: =DATE(S_An,1,1)+44 -> 46067 | K74: =SUMIFS(D_CO2,D_Jour,J74) -> 0
B75: =IF(Calcul!B75="","",Calcul!B75) -> GPT-4.1 mini | C75: =IF(B75="",0,SUMIFS(D_CO2,D_Grp,B75,D_An,S_An)) -> 0 | D75: =IF(B75="",0,SUMIFS(D_kWh,D_Grp,B75,D_An,S_An)) -> 0 | E75: =IF(B75="",0,SUMIFS(D_TO,D_Grp,B75,D_An,S_An)) -> 0 | F75: =IF(B75="",0,SUMIFS(D_Brut,D_Grp,B75,D_An,S_An)) -> 0 | G75: =IF(B75="",-1,C75)-ROW()*1E-12 -> -7.5e-11 | H75: =IF(B75="",0,SUMIFS(D_TO,D_Grp,B75)) -> 0 | J75: =DATE(S_An,1,1)+45 -> 46068 | K75: =SUMIFS(D_CO2,D_Jour,J75) -> 0
B76: =IF(Calcul!B76="","",Calcul!B76) -> GPT-4.1 nano | C76: =IF(B76="",0,SUMIFS(D_CO2,D_Grp,B76,D_An,S_An)) -> 0 | D76: =IF(B76="",0,SUMIFS(D_kWh,D_Grp,B76,D_An,S_An)) -> 0 | E76: =IF(B76="",0,SUMIFS(D_TO,D_Grp,B76,D_An,S_An)) -> 0 | F76: =IF(B76="",0,SUMIFS(D_Brut,D_Grp,B76,D_An,S_An)) -> 0 | G76: =IF(B76="",-1,C76)-ROW()*1E-12 -> -7.6e-11 | H76: =IF(B76="",0,SUMIFS(D_TO,D_Grp,B76)) -> 0 | J76: =DATE(S_An,1,1)+46 -> 46069 | K76: =SUMIFS(D_CO2,D_Jour,J76) -> 0
B77: =IF(Calcul!B77="","",Calcul!B77) -> gpt-4o-2024-11-20 | C77: =IF(B77="",0,SUMIFS(D_CO2,D_Grp,B77,D_An,S_An)) -> 0 | D77: =IF(B77="",0,SUMIFS(D_kWh,D_Grp,B77,D_An,S_An)) -> 0 | E77: =IF(B77="",0,SUMIFS(D_TO,D_Grp,B77,D_An,S_An)) -> 0 | F77: =IF(B77="",0,SUMIFS(D_Brut,D_Grp,B77,D_An,S_An)) -> 0 | G77: =IF(B77="",-1,C77)-ROW()*1E-12 -> -7.7e-11 | H77: =IF(B77="",0,SUMIFS(D_TO,D_Grp,B77)) -> 0 | J77: =DATE(S_An,1,1)+47 -> 46070 | K77: =SUMIFS(D_CO2,D_Jour,J77) -> 0
B78: =IF(Calcul!B78="","",Calcul!B78) -> gpt-4o-mini-2024-07-18 | C78: =IF(B78="",0,SUMIFS(D_CO2,D_Grp,B78,D_An,S_An)) -> 0 | D78: =IF(B78="",0,SUMIFS(D_kWh,D_Grp,B78,D_An,S_An)) -> 0 | E78: =IF(B78="",0,SUMIFS(D_TO,D_Grp,B78,D_An,S_An)) -> 0 | F78: =IF(B78="",0,SUMIFS(D_Brut,D_Grp,B78,D_An,S_An)) -> 0 | G78: =IF(B78="",-1,C78)-ROW()*1E-12 -> -7.8e-11 | H78: =IF(B78="",0,SUMIFS(D_TO,D_Grp,B78)) -> 0 | J78: =DATE(S_An,1,1)+48 -> 46071 | K78: =SUMIFS(D_CO2,D_Jour,J78) -> 0
B79: =IF(Calcul!B79="","",Calcul!B79) -> gpt-4o-transcribe-2025-03-20 | C79: =IF(B79="",0,SUMIFS(D_CO2,D_Grp,B79,D_An,S_An)) -> 0 | D79: =IF(B79="",0,SUMIFS(D_kWh,D_Grp,B79,D_An,S_An)) -> 0 | E79: =IF(B79="",0,SUMIFS(D_TO,D_Grp,B79,D_An,S_An)) -> 0 | F79: =IF(B79="",0,SUMIFS(D_Brut,D_Grp,B79,D_An,S_An)) -> 0 | G79: =IF(B79="",-1,C79)-ROW()*1E-12 -> -7.9e-11 | H79: =IF(B79="",0,SUMIFS(D_TO,D_Grp,B79)) -> 0 | J79: =DATE(S_An,1,1)+49 -> 46072 | K79: =SUMIFS(D_CO2,D_Jour,J79) -> 0
B80: =IF(Calcul!B80="","",Calcul!B80) -> GPT-5 | C80: =IF(B80="",0,SUMIFS(D_CO2,D_Grp,B80,D_An,S_An)) -> 0 | D80: =IF(B80="",0,SUMIFS(D_kWh,D_Grp,B80,D_An,S_An)) -> 0 | E80: =IF(B80="",0,SUMIFS(D_TO,D_Grp,B80,D_An,S_An)) -> 0 | F80: =IF(B80="",0,SUMIFS(D_Brut,D_Grp,B80,D_An,S_An)) -> 0 | G80: =IF(B80="",-1,C80)-ROW()*1E-12 -> -8e-11 | H80: =IF(B80="",0,SUMIFS(D_TO,D_Grp,B80)) -> 0 | J80: =DATE(S_An,1,1)+50 -> 46073 | K80: =SUMIFS(D_CO2,D_Jour,J80) -> 0
B81: =IF(Calcul!B81="","",Calcul!B81) -> GPT-5 nano | C81: =IF(B81="",0,SUMIFS(D_CO2,D_Grp,B81,D_An,S_An)) -> 0 | D81: =IF(B81="",0,SUMIFS(D_kWh,D_Grp,B81,D_An,S_An)) -> 0 | E81: =IF(B81="",0,SUMIFS(D_TO,D_Grp,B81,D_An,S_An)) -> 0 | F81: =IF(B81="",0,SUMIFS(D_Brut,D_Grp,B81,D_An,S_An)) -> 0 | G81: =IF(B81="",-1,C81)-ROW()*1E-12 -> -8.1e-11 | H81: =IF(B81="",0,SUMIFS(D_TO,D_Grp,B81)) -> 0 | J81: =DATE(S_An,1,1)+51 -> 46074 | K81: =SUMIFS(D_CO2,D_Jour,J81) -> 0
